Workbook
Name Cloth_B_Calc_Base_Stat_List: FRS!$AH$31:$AM$82
Name Cloth_B_Calc_Name_List: FRS!$AH$31:$AH$82
Name Cloth_D_Calc_Base_Stat_List: FRS!$R$31:$W$84
Name Cloth_D_Calc_Name_List: FRS!$R$31:$R$84
Name Cloth_T_Calc_Base_Stat_List: FRS!$Z$31:$AE$82
Name Cloth_T_Calc_Name_List: FRS!$Z$31:$Z$82
Name FRS_Item_Get_Get_List_V: FRS!$AV$93:$AV$119
Name FRS_Item_Get_Give_List_H: FRS!$AW$92:$BW$92
Name FRS_Item_Give_Get_List_V: FRS!$AV$136:$AV$162
Name FRS_Item_Give_Give_List_H: FRS!$AW$135:$BW$135
Name FRS_Trading_List_Get_Full: FRS!$AV$92:$BW$119
Name FRS_Trading_List_Give_Full: FRS!$AV$135:$BW$162
Name Rarity_List_Universal: FRS!$B$18:$B$21
Name Trinkets_Calc_Base_Stat_List: FRS!$B$31:$G$61
Name Trinkets_Calc_Name_List: FRS!$B$31:$B$61
Name Weapon_Calc_Base_Stat_List: FRS!$J$31:$O$74
Name Weapon_Calc_Name_List: FRS!$J$31:$J$74
Name Base_Stat_CD: 'Cloths Dresses'!$W$38
Name Cloth_B_Calc_Base_Stat_List: FRS!$AH$31:$AM$82
Name Cloth_B_Calc_Name_List: FRS!$AH$31:$AH$82
Name Cloth_D_Calc_Base_Stat_A: 'Cloths Dresses'!$W$10
Name Cloth_D_Calc_Base_Stat_F: 'Cloths Dresses'!$Y$10
Name Cloth_D_Calc_Base_Stat_I: 'Cloths Dresses'!$X$10
Name Cloth_D_Calc_Base_Stat_List: FRS!$R$31:$W$84
Name Cloth_D_Calc_Base_Stat_U: 'Cloths Dresses'!$Z$10
Name Cloth_D_Calc_Base_Stat_W: 'Cloths Dresses'!$V$10
Name Cloth_D_Calc_Level: 'Cloths Dresses'!$W$4
Name Cloth_D_Calc_Name: 'Cloths Dresses'!$U$4
Name Cloth_D_Calc_Name_List: FRS!$R$31:$R$84
Name Cloth_D_Calc_Progress_Num_A: 'Cloths Dresses'!$W$9
Name Cloth_D_Calc_Progress_Num_F: 'Cloths Dresses'!$Y$9
Name Cloth_D_Calc_Progress_Num_I: 'Cloths Dresses'!$X$9
Name Cloth_D_Calc_Progress_Num_U: 'Cloths Dresses'!$Z$9
Name Cloth_D_Calc_Progress_Num_W: 'Cloths Dresses'!$V$9
Name Cloth_D_Calc_Rarity: 'Cloths Dresses'!$V$4
Name Cloth_D_Calc_Tier_A: 'Cloths Dresses'!$W$8
Name Cloth_D_Calc_Tier_F: 'Cloths Dresses'!$Y$8
Name Cloth_D_Calc_Tier_I: 'Cloths Dresses'!$X$8
Name Cloth_D_Calc_Tier_U: 'Cloths Dresses'!$Z$8
Name Cloth_D_Calc_Tier_W: 'Cloths Dresses'!$V$8
Name Cloth_T_Calc_Base_Stat_List: FRS!$Z$31:$AE$82
Name Cloth_T_Calc_Name_List: FRS!$Z$31:$Z$82
Name FRS_Item_Get_Get_List_V: FRS!$AV$93:$AV$119
Name FRS_Item_Get_Give_List_H: FRS!$AW$92:$BW$92
Name FRS_Item_Give_Get_List_V: FRS!$AV$136:$AV$162
Name FRS_Item_Give_Give_List_H: FRS!$AW$135:$BW$135
Name FRS_Trading_List_Get_Full: FRS!$AV$92:$BW$119
Name FRS_Trading_List_Give_Full: FRS!$AV$135:$BW$162
Name Item_Level_CD: 'Cloths Dresses'!$U$38
Name Prog_Number_CD: 'Cloths Dresses'!$V$38
Name Rarity_List_Universal: FRS!$B$18:$B$21
Name Trinkets_Calc_Base_Stat_List: FRS!$B$31:$G$61
Name Trinkets_Calc_Name_List: FRS!$B$31:$B$61
Name Weapon_Calc_Base_Stat_List: FRS!$J$31:$O$74
Name Weapon_Calc_Name_List: FRS!$J$31:$J$74
Name Cloth_B_Calc_Base_Stat_List: FRS!$AH$31:$AM$82
Name Cloth_B_Calc_Name_List: FRS!$AH$31:$AH$82
Name Cloth_B_Calc_Progress_Num_A: Combos!$AT$29
Name Cloth_B_Calc_Progress_Num_F: Combos!$AV$29
Name Cloth_B_Calc_Progress_Num_I: Combos!$AU$29

Sheet 有
A1: 名字 | B1: 中名 | C1: 手填 等级 | D1: 获取 | E1: 稀有度(中文) | F1: 技能描述翻译 | G1: 初始 | H1: 游戏内截图翻译（WA近战先手I远程先 | I1: 最佳 | J1: 最差 | K1: 技 | L1: 装备 | M1: 装备备注 | N1: 列1 | O1: 列3 | P1: W | Q1: A | R1: I | S1: F | T1: U | U1: 总属 | V1: 列5 | W1: 等级 推理 | X1: 列7 | Y1: W 意志(裸装) | Z1: A 敏捷(裸装) | AA1: I 智力(裸装) | AB1: F 血量(裸装) | AC1: U 免伤(裸装) | AD1: 列1222 | AE1: W 意志 | AF1: A 敏捷 | AG1: I 智力 | AH1: F 血量 | AI1: U 免伤 | AJ1: 列52 | AL1: 角色 (Name) | AM1: 最佳武器 (Weapon) | AN1: 最佳衣服 (Dress/Top & Bottom) | AO1: 最佳饰品 (Trinket) | AP1: 核心加成
A2: Kim | B2: =IFERROR(VLOOKUP($A2,全人物技能说明!$A$1:$O$99,2,FALSE),"") -> 金 | C2: 36 | D2: =IFERROR(VLOOKUP($A2,全人物技能说明!$A$1:$O$99,3,FALSE),"") -> 2箱子 | E2: =IFERROR(VLOOKUP($A2,全人物技能说明!$A$1:$O$99,4,FALSE),"") -> 稀有 | F2: =IFERROR(VLOOKUP($A2,全人物技能说明!$A$1:$O$99,7,FALSE),"") -> X4或X2武器7次，远X4八次。喷火8次。X4近锋利砍刀单次伤最高，穿甲 | G2: =IFERROR(VLOOKUP($A2,全人物技能说明!$A$1:$O$99,8,FALSE),"") -> 阅读忧郁杰作，使最多 4 名敌人眩晕 2 回合。 | H2: 朗读令人沮丧的名著，使最多 4 名敌人眩晕 2 回合。 | I2: =IFERROR(VLOOKUP($A2,全人物技能说明!$A$1:$O$99,14,FALSE),"") -> I, F, U | J2: =IFERROR(VLOOKUP($A2,全人物技能说明!$A$1:$O$99,15,FALSE),"") -> W | L2: A | M2: =IFERROR(IF(VLOOKUP($A2,全人物技能说明!$A$1:$O$99,7,FALSE)<>"",VLOOKUP($A2,全人物技能说明!$A$1:$O$99,7,FALSE),""),"") -> X4或X2武器7次，远X4八次。喷火8次。X4近锋利砍刀单次伤最高，穿甲 | O2: I | P2: =RANK(Y2,Y:Y) -> 3 | Q2: =RANK(Z2,Z:Z) -> 1 | R2: =RANK(AA2,AA:AA) -> 2 | S2: =RANK(AB2,AB:AB) -> 1 | T2: =RANK(AC2,AC:AC) -> 1 | U2: =Y2+Z2+AA2+AB2+AC2 -> 1713 | W2: =C2 -> 36 | X2: 0 | Y2: =IFERROR(VALUE(LEFT(AE2,FIND("(",AE2)-1))+($W2-1)*VALUE(MID(AE2,FIND("+",AE2)+1,FIND(")",AE2)-FIND("+",AE2)-1)),"") -> 254 | Z2: =IFERROR(VALUE(LEFT(AF2,FIND("(",AF2)-1))+($W2-1)*VALUE(MID(AF2,FIND("+",AF2)+1,FIND(")",AF2)-FIND("+",AF2)-1)),"") -> 334 | AA2: =IFERROR(VALUE(LEFT(AG2,FIND("(",AG2)-1))+($W2-1)*VALUE(MID(AG2,FIND("+",AG2)+1,FIND(")",AG2)-FIND("+",AG2)-1)),"") -> 375 | AB2: =IFERROR(VALUE(LEFT(AH2,FIND("(",AH2)-1))+($W2-1)*VALUE(MID(AH2,FIND("+",AH2)+1,FIND(")",AH2)-FIND("+",AH2)-1)),"") -> 375 | AC2: =IFERROR(VALUE(LEFT(AI2,FIND("(",AI2)-1))+($W2-1)*VALUE(MID(AI2,FIND("+",AI2)+1,FIND(")",AI2)-FIND("+",AI2)-1)),"") -> 375 | AE2: =IFERROR(VLOOKUP($A2,全人物技能说明!$A$1:$O$99,9,FALSE),"") -> 44(+6) | AF2: =IFERROR(VLOOKUP($A2,全人物技能说明!$A$1:$O$99,10,FALSE),"") -> 54(+8) | AG2: =IFERROR(VLOOKUP($A2,全人物技能说明!$A$1:$O$99,11,FALSE),"") -> 60(+9) | AH2: =IFERROR(VLOOKUP($A2,全人物技能说明!$A$1:$O$99,12,FALSE),"") -> 60(+9) | AI2: =IFERROR(VLOOKUP($A2,全人物技能说明!$A$1:$O$99,13,FALSE),"") -> 60(+9) | AL2: 意志组 (Olivia, Allura, Emily, Diana, Karin, Martina, Devi, Samantha, Lane, Trixie) | AM2: 特种冲锋枪 (Special SMG) | AN2: 陆军上校 (Army Colonel) & 陆军底部 (Army Bottom) | AO2: 染发剂 (Hair Dye) | AP2: W (意志)
A3: XX | B3: =IFERROR(VLOOKUP($A3,全人物技能说明!$A$1:$O$99,2,FALSE),"") -> XX | C3: 34 | D3: =IFERROR(VLOOKUP($A3,全人物技能说明!$A$1:$O$99,3,FALSE),"") -> 1剧情 | E3: =IFERROR(VLOOKUP($A3,全人物技能说明!$A$1:$O$99,4,FALSE),"") -> 普通 | F3: =IFERROR(VLOOKUP($A3,全人物技能说明!$A$1:$O$99,7,FALSE),"") -> X4武器6次攻击放技能，X2会更快 | G3: =IFERROR(VLOOKUP($A3,全人物技能说明!$A$1:$O$99,8,FALSE),"") -> 魅惑一名敌人，使其眩晕 2 回合，并使其受到的伤害提升 50%。 | H3: 魅惑一名敌人，使其眩晕 2 回合并增加其受到伤害 30%。 | I3: =IFERROR(VLOOKUP($A3,全人物技能说明!$A$1:$O$99,14,FALSE),"") -> A | J3: =IFERROR(VLOOKUP($A3,全人物技能说明!$A$1:$O$99,15,FALSE),"") -> W, I | L3: A | M3: =IFERROR(IF(VLOOKUP($A3,全人物技能说明!$A$1:$O$99,7,FALSE)<>"",VLOOKUP($A3,全人物技能说明!$A$1:$O$99,7,FALSE),""),"") -> X4武器6次攻击放技能，X2会更快 | O3: A | P3: =RANK(Y3,Y:Y) -> 11 | Q3: =RANK(Z3,Z:Z) -> 2 | R3: =RANK(AA3,AA:AA) -> 9 | S3: =RANK(AB3,AB:AB) -> 3 | T3: =RANK(AC3,AC:AC) -> 6 | U3: =Y3+Z3+AA3+AB3+AC3 -> 1165 | W3: =C3 -> 34 | X3: 0 | Y3: =IFERROR(VALUE(LEFT(AE3,FIND("(",AE3)-1))+($W3-1)*VALUE(MID(AE3,FIND("+",AE3)+1,FIND(")",AE3)-FIND("+",AE3)-1)),"") -> 203 | Z3: =IFERROR(VALUE(LEFT(AF3,FIND("(",AF3)-1))+($W3-1)*VALUE(MID(AF3,FIND("+",AF3)+1,FIND(")",AF3)-FIND("+",AF3)-1)),"") -> 279 | AA3: =IFERROR(VALUE(LEFT(AG3,FIND("(",AG3)-1))+($W3-1)*VALUE(MID(AG3,FIND("+",AG3)+1,FIND(")",AG3)-FIND("+",AG3)-1)),"") -> 203 | AB3: =IFERROR(VALUE(LEFT(AH3,FIND("(",AH3)-1))+($W3-1)*VALUE(MID(AH3,FIND("+",AH3)+1,FIND(")",AH3)-FIND("+",AH3)-1)),"") -> 240 | AC3: =IFERROR(VALUE(LEFT(AI3,FIND("(",AI3)-1))+($W3-1)*VALUE(MID(AI3,FIND("+",AI3)+1,FIND(")",AI3)-FIND("+",AI3)-1)),"") -> 240 | AE3: =IFERROR(VLOOKUP($A3,全人物技能说明!$A$1:$O$99,9,FALSE),"") -> 38(+5) | AF3: =IFERROR(VLOOKUP($A3,全人物技能说明!$A$1:$O$99,10,FALSE),"") -> 48(+7) | AG3: =IFERROR(VLOOKUP($A3,全人物技能说明!$A$1:$O$99,11,FALSE),"") -> 38(+5) | AH3: =IFERROR(VLOOKUP($A3,全人物技能说明!$A$1:$O$99,12,FALSE),"") -> 42(+6) | AI3: =IFERROR(VLOOKUP($A3,全人物技能说明!$A$1:$O$99,13,FALSE),"") -> 42(+6)
A4: TRIXIE | B4: =IFERROR(VLOOKUP($A4,全人物技能说明!$A$1:$O$99,2,FALSE),"") -> 翠克希 | C4: 33 | D4: =IFERROR(VLOOKUP($A4,全人物技能说明!$A$1:$O$99,3,FALSE),"") -> 2剧情 | E4: =IFERROR(VLOOKUP($A4,全人物技能说明!$A$1:$O$99,4,FALSE),"") -> 稀有 | F4: =IFERROR(VLOOKUP($A4,全人物技能说明!$A$1:$O$99,7,FALSE),"") -> 0 | G4: =IFERROR(VLOOKUP($A4,全人物技能说明!$A$1:$O$99,8,FALSE),"") -> 指挥 2 名队友瞬间攻击一名敌人。 | H4: 命令 2 名盟友立即攻击一名敌人。 | I4: =IFERROR(VLOOKUP($A4,全人物技能说明!$A$1:$O$99,14,FALSE),"") -> W | J4: =IFERROR(VLOOKUP($A4,全人物技能说明!$A$1:$O$99,15,FALSE),"") -> A, F | L4: W | M4: =IFERROR(IF(VLOOKUP($A4,全人物技能说明!$A$1:$O$99,7,FALSE)<>"",VLOOKUP($A4,全人物技能说明!$A$1:$O$99,7,FALSE),""),"") | O4: 广播 | P4: =RANK(Y4,Y:Y) -> 2 | Q4: =RANK(Z4,Z:Z) -> 13 | R4: =RANK(AA4,AA:AA) -> 6 | S4: =RANK(AB4,AB:AB) -> 12 | T4: =RANK(AC4,AC:AC) -> 7 | U4: =Y4+Z4+AA4+AB4+AC4 -> 1136 | W4: =C4 -> 33 | Y4: =IFERROR(VALUE(LEFT(AE4,FIND("(",AE4)-1))+($W4-1)*VALUE(MID(AE4,FIND("+",AE4)+1,FIND(")",AE4)-FIND("+",AE4)-1)),"") -> 272 | Z4: =IFERROR(VALUE(LEFT(AF4,FIND("(",AF4)-1))+($W4-1)*VALUE(MID(AF4,FIND("+",AF4)+1,FIND(")",AF4)-FIND("+",AF4)-1)),"") -> 198 | AA4: =IFERROR(VALUE(LEFT(AG4,FIND("(",AG4)-1))+($W4-1)*VALUE(MID(AG4,FIND("+",AG4)+1,FIND(")",AG4)-FIND("+",AG4)-1)),"") -> 234 | AB4: =IFERROR(VALUE(LEFT(AH4,FIND("(",AH4)-1))+($W4-1)*VALUE(MID(AH4,FIND("+",AH4)+1,FIND(")",AH4)-FIND("+",AH4)-1)),"") -> 198 | AC4: =IFERROR(VALUE(LEFT(AI4,FIND("(",AI4)-1))+($W4-1)*VALUE(MID(AI4,FIND("+",AI4)+1,FIND(")",AI4)-FIND("+",AI4)-1)),"") -> 234 | AE4: =IFERROR(VLOOKUP($A4,全人物技能说明!$A$1:$O$99,9,FALSE),"") -> 48(+7) | AF4: =IFERROR(VLOOKUP($A4,全人物技能说明!$A$1:$O$99,10,FALSE),"") -> 38(+5) | AG4: =IFERROR(VLOOKUP($A4,全人物技能说明!$A$1:$O$99,11,FALSE),"") -> 42(+6) | AH4: =IFERROR(VLOOKUP($A4,全人物技能说明!$A$1:$O$99,12,FALSE),"") -> 38(+5) | AI4: =IFERROR(VLOOKUP($A4,全人物技能说明!$A$1:$O$99,13,FALSE),"") -> 42(+6) | AM4: W:4, F:4 | AN4: W:5, F:4 | AO4: W:5, A:3 | AP4: 远程高伤
A5: Sophie | B5: =IFERROR(VLOOKUP($A5,全人物技能说明!$A$1:$O$99,2,FALSE),"") -> 苏菲 | C5: 33 | D5: =IFERROR(VLOOKUP($A5,全人物技能说明!$A$1:$O$99,3,FALSE),"") -> 3剧情 | E5: =IFERROR(VLOOKUP($A5,全人物技能说明!$A$1:$O$99,4,FALSE),"") -> 史诗 | F5: =IFERROR(VLOOKUP($A5,全人物技能说明!$A$1:$O$99,7,FALSE),"") -> 0 | G5: =IFERROR(VLOOKUP($A5,全人物技能说明!$A$1:$O$99,8,FALSE),"") -> 向最多 2 名血量最低的队友递出药剂，回复 [20% INT] 生命值，并在 2 回合内提升其 20% 伤害。 | H5: 向 2 名生命值最低的盟友治疗 [20% 智力] 生命值并提升其 20% 伤害，持续 2 回合。 | I5: =IFERROR(VLOOKUP($A5,全人物技能说明!$A$1:$O$99,14,FALSE),"") -> I, U | J5: =IFERROR(VLOOKUP($A5,全人物技能说明!$A$1:$O$99,15,FALSE),"") -> A | K5: I | L5: I | M5: =IFERROR(IF(VLOOKUP($A5,全人物技能说明!$A$1:$O$99,7,FALSE)<>"",VLOOKUP($A5,全人物技能说明!$A$1:$O$99,7,FALSE),""),"") | O5: 金库 | P5: =RANK(Y5,Y:Y) -> 6 | Q5: =RANK(Z5,Z:Z) -> 18 | R5: =RANK(AA5,AA:AA) -> 3 | S5: =RANK(AB5,AB:AB) -> 12 | T5: =RANK(AC5,AC:AC) -> 2 | U5: =Y5+Z5+AA5+AB5+AC5 -> 1136 | W5: =C5 -> 33 | Y5: =IFERROR(VALUE(LEFT(AE5,FIND("(",AE5)-1))+($W5-1)*VALUE(MID(AE5,FIND("+",AE5)+1,FIND(")",AE5)-FIND("+",AE5)-1)),"") -> 234 | Z5: =IFERROR(VALUE(LEFT(AF5,FIND("(",AF5)-1))+($W5-1)*VALUE(MID(AF5,FIND("+",AF5)+1,FIND(")",AF5)-FIND("+",AF5)-1)),"") -> 160 | AA5: =IFERROR(VALUE(LEFT(AG5,FIND("(",AG5)-1))+($W5-1)*VALUE(MID(AG5,FIND("+",AG5)+1,FIND(")",AG5)-FIND("+",AG5)-1)),"") -> 272 | AB5: =IFERROR(VALUE(LEFT(AH5,FIND("(",AH5)-1))+($W5-1)*VALUE(MID(AH5,FIND("+",AH5)+1,FIND(")",AH5)-FIND("+",AH5)-1)),"") -> 198 | AC5: =IFERROR(VALUE(LEFT(AI5,FIND("(",AI5)-1))+($W5-1)*VALUE(MID(AI5,FIND("+",AI5)+1,FIND(")",AI5)-FIND("+",AI5)-1)),"") -> 272 | AE5: =IFERROR(VLOOKUP($A5,全人物技能说明!$A$1:$O$99,9,FALSE),"") -> 42(+6) | AF5: =IFERROR(VLOOKUP($A5,全人物技能说明!$A$1:$O$99,10,FALSE),"") -> 32(+4) | AG5: =IFERROR(VLOOKUP($A5,全人物技能说明!$A$1:$O$99,11,FALSE),"") -> 48(+7) | AH5: =IFERROR(VLOOKUP($A5,全人物技能说明!$A$1:$O$99,12,FALSE),"") -> 38(+5) | AI5: =IFERROR(VLOOKUP($A5,全人物技能说明!$A$1:$O$99,13,FALSE),"") -> 48(+7) | AL5: 敏捷组 (PAIN, Chelsea, Gaia, Kiara, Amelia, Jane, Sonia, XX, Cloe, Tess) | AM5: 刺客匕首 (Assassin's Dagger) | AN5: 野蛮人上衣 (Barbarian Top) & 野蛮人裙 (Barbarian Skirt) | AO5: 糖弹 (Sugar Bomb) | AP5: A (敏捷)
A6: ASHLEY | B6: =IFERROR(VLOOKUP($A6,全人物技能说明!$A$1:$O$99,2,FALSE),"") -> 艾希莉 | C6: 33 | D6: =IFERROR(VLOOKUP($A6,全人物技能说明!$A$1:$O$99,3,FALSE),"") -> 5箱子 | E6: =IFERROR(VLOOKUP($A6,全人物技能说明!$A$1:$O$99,4,FALSE),"") -> 传说 | F6: =IFERROR(VLOOKUP($A6,全人物技能说明!$A$1:$O$99,7,FALSE),"") -> 无论是近战还是远程攻击，都需要 4 次攻击 | G6: =IFERROR(VLOOKUP($A6,全人物技能说明!$A$1:$O$99,8,FALSE),"") -> 使下 2 次攻击的伤害提升 200%。战斗开始时即就绪。 | H6: 增加接下来3次攻击伤害30% | I6: =IFERROR(VLOOKUP($A6,全人物技能说明!$A$1:$O$99,14,FALSE),"") -> A, U | J6: =IFERROR(VLOOKUP($A6,全人物技能说明!$A$1:$O$99,15,FALSE),"") -> I | L6: A | M6: =IFERROR(IF(VLOOKUP($A6,全人物技能说明!$A$1:$O$99,7,FALSE)<>"",VLOOKUP($A6,全人物技能说明!$A$1:$O$99,7,FALSE),""),"") -> 无论是近战还是远程攻击，都需要 4 次攻击 | O6: 矿石 | P6: =RANK(Y6,Y:Y) -> 12 | Q6: =RANK(Z6,Z:Z) -> 4 | R6: =RANK(AA6,AA:AA) -> 21 | S6: =RANK(AB6,AB:AB) -> 4 | T6: =RANK(AC6,AC:AC) -> 2 | U6: =Y6+Z6+AA6+AB6+AC6 -> 1136 | W6: =C6 -> 33 | Y6: =IFERROR(VALUE(LEFT(AE6,FIND("(",AE6)-1))+($W6-1)*VALUE(MID(AE6,FIND("+",AE6)+1,FIND(")",AE6)-FIND("+",AE6)-1)),"") -> 198 | Z6: =IFERROR(VALUE(LEFT(AF6,FIND("(",AF6)-1))+($W6-1)*VALUE(MID(AF6,FIND("+",AF6)+1,FIND(")",AF6)-FIND("+",AF6)-1)),"") -> 272 | AA6: =IFERROR(VALUE(LEFT(AG6,FIND("(",AG6)-1))+($W6-1)*VALUE(MID(AG6,FIND("+",AG6)+1,FIND(")",AG6)-FIND("+",AG6)-1)),"") -> 160 | AB6: =IFERROR(VALUE(LEFT(AH6,FIND("(",AH6)-1))+($W6-1)*VALUE(MID(AH6,FIND("+",AH6)+1,FIND(")",AH6)-FIND("+",AH6)-1)),"") -> 234 | AC6: =IFERROR(VALUE(LEFT(AI6,FIND("(",AI6)-1))+($W6-1)*VALUE(MID(AI6,FIND("+",AI6)+1,FIND(")",AI6)-FIND("+",AI6)-1)),"") -> 272 | AE6: =IFERROR(VLOOKUP($A6,全人物技能说明!$A$1:$O$99,9,FALSE),"") -> 38(+5) | AF6: =IFERROR(VLOOKUP($A6,全人物技能说明!$A$1:$O$99,10,FALSE),"") -> 48(+7) | AG6: =IFERROR(VLOOKUP($A6,全人物技能说明!$A$1:$O$99,11,FALSE),"") -> 32(+4) | AH6: =IFERROR(VLOOKUP($A6,全人物技能说明!$A$1:$O$99,12,FALSE),"") -> 42(+6) | AI6: =IFERROR(VLOOKUP($A6,全人物技能说明!$A$1:$O$99,13,FALSE),"") -> 48(+7)
A7: ANDREA | B7: =IFERROR(VLOOKUP($A7,全人物技能说明!$A$1:$O$99,2,FALSE),"") -> 安德烈亚 | C7: 32 | D7: =IFERROR(VLOOKUP($A7,全人物技能说明!$A$1:$O$99,3,FALSE),"") -> 1剧情 | E7: =IFERROR(VLOOKUP($A7,全人物技能说明!$A$1:$O$99,4,FALSE),"") -> 稀有 | F7: =IFERROR(VLOOKUP($A7,全人物技能说明!$A$1:$O$99,8,FALSE),"") -> 为 2 名血量最低的队友回复 10% 最大生命值 + [15% INT]。 | G7: =IFERROR(VLOOKUP($A7,全人物技能说明!$A$1:$O$99,8,FALSE),"") -> 为 2 名血量最低的队友回复 10% 最大生命值 + [15% INT]。 | H7: 治疗 2 名生命值最低的盟友，恢复其最大生命值的 10% + [15% 智力]。 | I7: =IFERROR(VLOOKUP($A7,全人物技能说明!$A$1:$O$99,14,FALSE),"") -> I | J7: =IFERROR(VLOOKUP($A7,全人物技能说明!$A$1:$O$99,15,FALSE),"") -> W, F | K7: I | L7: I | M7: =IFERROR(IF(VLOOKUP($A7,全人物技能说明!$A$1:$O$99,7,FALSE)<>"",VLOOKUP($A7,全人物技能说明!$A$1:$O$99,7,FALSE),""),"") -> 高电压电击枪（I 类武器伤害最高） | O7: 金库 | P7: =RANK(Y7,Y:Y) -> 13 | Q7: =RANK(Z7,Z:Z) -> 9 | R7: =RANK(AA7,AA:AA) -> 4 | S7: =RANK(AB7,AB:AB) -> 14 | T7: =RANK(AC7,AC:AC) -> 8 | U7: =Y7+Z7+AA7+AB7+AC7 -> 1107 | W7: =C7 -> 32 | X7: 0 | Y7: =IFERROR(VALUE(LEFT(AE7,FIND("(",AE7)-1))+($W7-1)*VALUE(MID(AE7,FIND("+",AE7)+1,FIND(")",AE7)-FIND("+",AE7)-1)),"") -> 193 | Z7: =IFERROR(VALUE(LEFT(AF7,FIND("(",AF7)-1))+($W7-1)*VALUE(MID(AF7,FIND("+",AF7)+1,FIND(")",AF7)-FIND("+",AF7)-1)),"") -> 228 | AA7: =IFERROR(VALUE(LEFT(AG7,FIND("(",AG7)-1))+($W7-1)*VALUE(MID(AG7,FIND("+",AG7)+1,FIND(")",AG7)-FIND("+",AG7)-1)),"") -> 265 | AB7: =IFERROR(VALUE(LEFT(AH7,FIND("(",AH7)-1))+($W7-1)*VALUE(MID(AH7,FIND("+",AH7)+1,FIND(")",AH7)-FIND("+",AH7)-1)),"") -> 193 | AC7: =IFERROR(VALUE(LEFT(AI7,FIND("(",AI7)-1))+($W7-1)*VALUE(MID(AI7,FIND("+",AI7)+1,FIND(")",AI7)-FIND("+",AI7)-1)),"") -> 228 | AE7: =IFERROR(VLOOKUP($A7,全人物技能说明!$A$1:$O$99,9,FALSE),"") -> 38(+5) | AF7: =IFERROR(VLOOKUP($A7,全人物技能说明!$A$1:$O$99,10,FALSE),"") -> 42(+6) | AG7: =IFERROR(VLOOKUP($A7,全人物技能说明!$A$1:$O$99,11,FALSE),"") -> 48(+7) | AH7: =IFERROR(VLOOKUP($A7,全人物技能说明!$A$1:$O$99,12,FALSE),"") -> 38(+5) | AI7: =IFERROR(VLOOKUP($A7,全人物技能说明!$A$1:$O$99,13,FALSE),"") -> 42(+6) | AM7: A:5, F:4 | AN7: A:5, F:5 | AO7: A:5, I:4 | AP7: 近战/暴击
A8: LADY JUDITH | B8: =IFERROR(VLOOKUP($A8,全人物技能说明!$A$1:$O$99,2,FALSE),"") -> 朱迪丝 | C8: 31 | D8: =IFERROR(VLOOKUP($A8,全人物技能说明!$A$1:$O$99,3,FALSE),"") -> 4箱子 | E8: =IFERROR(VLOOKUP($A8,全人物技能说明!$A$1:$O$99,4,FALSE),"") -> 史诗 | F8: =IFERROR(VLOOKUP($A8,全人物技能说明!$A$1:$O$99,7,FALSE),"") -> 近战X4武器8次攻击，X2稍快，远程x4武器就需要9次 | G8: =IFERROR(VLOOKUP($A8,全人物技能说明!$A$1:$O$99,8,FALSE),"") -> 召唤保镖（继承 [75% HP] 和 [75% DEF]），嘲讽敌人最多 2 回合。 | H8: 击晕所有敌人1回合,并增加接下来3次攻击伤害15% | I8: =IFERROR(VLOOKUP($A8,全人物技能说明!$A$1:$O$99,14,FALSE),"") -> W, I | J8: =IFERROR(VLOOKUP($A8,全人物技能说明!$A$1:$O$99,15,FALSE),"") -> F, U | L8: W | M8: =IFERROR(IF(VLOOKUP($A8,全人物技能说明!$A$1:$O$99,7,FALSE)<>"",VLOOKUP($A8,全人物技能说明!$A$1:$O$99,7,FALSE),""),"") -> 近战X4武器8次攻击，X2稍快，远程x4武器就需要9次 | O8: I | P8: =RANK(Y8,Y:Y) -> 1 | Q8: =RANK(Z8,Z:Z) -> 5 | R8: =RANK(AA8,AA:AA) -> 1 | S8: =RANK(AB8,AB:AB) -> 5 | T8: =RANK(AC8,AC:AC) -> 9 | U8: =Y8+Z8+AA8+AB8+AC8 -> 1490 | W8: =C8 -> 31 | X8: 0 | Y8: =IFERROR(VALUE(LEFT(AE8,FIND("(",AE8)-1))+($W8-1)*VALUE(MID(AE8,FIND("+",AE8)+1,FIND(")",AE8)-FIND("+",AE8)-1)),"") -> 396 | Z8: =IFERROR(VALUE(LEFT(AF8,FIND("(",AF8)-1))+($W8-1)*VALUE(MID(AF8,FIND("+",AF8)+1,FIND(")",AF8)-FIND("+",AF8)-1)),"") -> 258 | AA8: =IFERROR(VALUE(LEFT(AG8,FIND("(",AG8)-1))+($W8-1)*VALUE(MID(AG8,FIND("+",AG8)+1,FIND(")",AG8)-FIND("+",AG8)-1)),"") -> 396 | AB8: =IFERROR(VALUE(LEFT(AH8,FIND("(",AH8)-1))+($W8-1)*VALUE(MID(AH8,FIND("+",AH8)+1,FIND(")",AH8)-FIND("+",AH8)-1)),"") -> 220 | AC8: =IFERROR(VALUE(LEFT(AI8,FIND("(",AI8)-1))+($W8-1)*VALUE(MID(AI8,FIND("+",AI8)+1,FIND(")",AI8)-FIND("+",AI8)-1)),"") -> 220 | AE8: =IFERROR(VLOOKUP($A8,全人物技能说明!$A$1:$O$99,9,FALSE),"") -> 66(+11) | AF8: =IFERROR(VLOOKUP($A8,全人物技能说明!$A$1:$O$99,10,FALSE),"") -> 48(+7) | AG8: =IFERROR(VLOOKUP($A8,全人物技能说明!$A$1:$O$99,11,FALSE),"") -> 66(+11) | AH8: =IFERROR(VLOOKUP($A8,全人物技能说明!$A$1:$O$99,12,FALSE),"") -> 40(+6) | AI8: =IFERROR(VLOOKUP($A8,全人物技能说明!$A$1:$O$99,13,FALSE),"") -> 40(+6) | AL8: 智力组 (Eleanor, Autumn, Allura, Maria, Andrea, Sophie, Kim, Cloe, Lane) | AM8: 特斯拉枪 (Tesla Gun) | AN8: 精巧上衣 (Exquisite Top) & 霓虹灯底部 (Neon Bottom) | AO8: Lovense 礼物 (Lovense Gift) | AP8: I (智力)
A9: MARTHA | B9: =IFERROR(VLOOKUP($A9,全人物技能说明!$A$1:$O$99,2,FALSE),"") -> 玛莎 | C9: 30 | D9: =IFERROR(VLOOKUP($A9,全人物技能说明!$A$1:$O$99,3,FALSE),"") -> 1箱子 | E9: =IFERROR(VLOOKUP($A9,全人物技能说明!$A$1:$O$99,4,FALSE),"") -> 稀有 | F9: =IFERROR(VLOOKUP($A9,全人物技能说明!$A$1:$O$99,7,FALSE),"") -> 使用管武器需要5次攻击 | G9: =IFERROR(VLOOKUP($A9,全人物技能说明!$A$1:$O$99,8,FALSE),"") -> 嘲讽敌人 2 回合；减少 70% 所受到的伤害。 | H9: 对所有敌人灌输流言蜚语。将接下来6次攻击造成的伤害减少50%。 | I9: =IFERROR(VLOOKUP($A9,全人物技能说明!$A$1:$O$99,14,FALSE),"") -> U | J9: =IFERROR(VLOOKUP($A9,全人物技能说明!$A$1:$O$99,15,FALSE),"") -> W, I | L9: A | M9: =IFERROR(IF(VLOOKUP($A9,全人物技能说明!$A$1:$O$99,7,FALSE)<>"",VLOOKUP($A9,全人物技能说明!$A$1:$O$99,7,FALSE),""),"") -> 使用管武器需要5次攻击 | P9: =RANK(Y9,Y:Y) -> 17 | Q9: =RANK(Z9,Z:Z) -> 10 | R9: =RANK(AA9,AA:AA) -> 14 | S9: =RANK(AB9,AB:AB) -> 6 | T9: =RANK(AC9,AC:AC) -> 4 | U9: =Y9+Z9+AA9+AB9+AC9 -> 1049 | W9: =C9 -> 30 | X9: 1 | Y9: =IFERROR(VALUE(LEFT(AE9,FIND("(",AE9)-1))+($W9-1)*VALUE(MID(AE9,FIND("+",AE9)+1,FIND(")",AE9)-FIND("+",AE9)-1)),"") -> 183 | Z9: =IFERROR(VALUE(LEFT(AF9,FIND("(",AF9)-1))+($W9-1)*VALUE(MID(AF9,FIND("+",AF9)+1,FIND(")",AF9)-FIND("+",AF9)-1)),"") -> 216 | AA9: =IFERROR(VALUE(LEFT(AG9,FIND("(",AG9)-1))+($W9-1)*VALUE(MID(AG9,FIND("+",AG9)+1,FIND(")",AG9)-FIND("+",AG9)-1)),"") -> 183 | AB9: =IFERROR(VALUE(LEFT(AH9,FIND("(",AH9)-1))+($W9-1)*VALUE(MID(AH9,FIND("+",AH9)+1,FIND(")",AH9)-FIND("+",AH9)-1)),"") -> 216 | AC9: =IFERROR(VALUE(LEFT(AI9,FIND("(",AI9)-1))+($W9-1)*VALUE(MID(AI9,FIND("+",AI9)+1,FIND(")",AI9)-FIND("+",AI9)-1)),"") -> 251 | AE9: =IFERROR(VLOOKUP($A9,全人物技能说明!$A$1:$O$99,9,FALSE),"") -> 38(+5) | AF9: =IFERROR(VLOOKUP($A9,全人物技能说明!$A$1:$O$99,10,FALSE),"") -> 42(+6) | AG9: =IFERROR(VLOOKUP($A9,全人物技能说明!$A$1:$O$99,11,FALSE),"") -> 38(+5) | AH9: =IFERROR(VLOOKUP($A9,全人物技能说明!$A$1:$O$99,12,FALSE),"") -> 42(+6) | AI9: =IFERROR(VLOOKUP($A9,全人物技能说明!$A$1:$O$99,13,FALSE),"") -> 48(+7)
A10: JANE | B10: =IFERROR(VLOOKUP($A10,全人物技能说明!$A$1:$O$99,2,FALSE),"") -> 简 | C10: 29 | D10: =IFERROR(VLOOKUP($A10,全人物技能说明!$A$1:$O$99,3,FALSE),"") -> 1剧情 | E10: =IFERROR(VLOOKUP($A10,全人物技能说明!$A$1:$O$99,4,FALSE),"") -> 史诗 | F10: =IFERROR(VLOOKUP($A10,全人物技能说明!$A$1:$O$99,7,FALSE),"") -> 无论是近战还是远程攻击，都需要 4 次攻击 | G10: =IFERROR(VLOOKUP($A10,全人物技能说明!$A$1:$O$99,8,FALSE),"") -> 使下 2 次攻击的伤害提升 200%。战斗开始时即就绪。 | H10: 增加接下来2次攻击伤害30% | I10: =IFERROR(VLOOKUP($A10,全人物技能说明!$A$1:$O$99,14,FALSE),"") -> A, F | J10: =IFERROR(VLOOKUP($A10,全人物技能说明!$A$1:$O$99,15,FALSE),"") -> U | L10: A | M10: =IFERROR(IF(VLOOKUP($A10,全人物技能说明!$A$1:$O$99,7,FALSE)<>"",VLOOKUP($A10,全人物技能说明!$A$1:$O$99,7,FALSE),""),"") -> 无论是近战还是远程攻击，都需要 4 次攻击 | O10: F | P10: =RANK(Y10,Y:Y) -> 9 | Q10: =RANK(Z10,Z:Z) -> 6 | R10: =RANK(AA10,AA:AA) -> 17 | S10: =RANK(AB10,AB:AB) -> 2 | T10: =RANK(AC10,AC:AC) -> 23 | U10: =Y10+Z10+AA10+AB10+AC10 -> 1020 | W10: =C10 -> 29 | Y10: =IFERROR(VALUE(LEFT(AE10,FIND("(",AE10)-1))+($W10-1)*VALUE(MID(AE10,FIND("+",AE10)+1,FIND(")",AE10)-FIND("+",AE10)-1)),"") -> 210 | Z10: =IFERROR(VALUE(LEFT(AF10,FIND("(",AF10)-1))+($W10-1)*VALUE(MID(AF10,FIND("+",AF10)+1,FIND(")",AF10)-FIND("+",AF10)-1)),"") -> 244 | AA10: =IFERROR(VALUE(LEFT(AG10,FIND("(",AG10)-1))+($W10-1)*VALUE(MID(AG10,FIND("+",AG10)+1,FIND(")",AG10)-FIND("+",AG10)-1)),"") -> 178 | AB10: =IFERROR(VALUE(LEFT(AH10,FIND("(",AH10)-1))+($W10-1)*VALUE(MID(AH10,FIND("+",AH10)+1,FIND(")",AH10)-FIND("+",AH10)-1)),"") -> 244 | AC10: =IFERROR(VALUE(LEFT(AI10,FIND("(",AI10)-1))+($W10-1)*VALUE(MID(AI10,FIND("+",AI10)+1,FIND(")",AI10)-FIND("+",AI10)-1)),"") -> 144 | AE10: =IFERROR(VLOOKUP($A10,全人物技能说明!$A$1:$O$99,9,FALSE),"") -> 42(+6) | AF10: =IFERROR(VLOOKUP($A10,全人物技能说明!$A$1:$O$99,10,FALSE),"") -> 48(+7) | AG10: =IFERROR(VLOOKUP($A10,全人物技能说明!$A$1:$O$99,11,FALSE),"") -> 38(+5) | AH10: =IFERROR(VLOOKUP($A10,全人物技能说明!$A$1:$O$99,12,FALSE),"") -> 48(+7) | AI10: =IFERROR(VLOOKUP($A10,全人物技能说明!$A$1:$O$99,13,FALSE),"") -> 32(+4) | AM10: I:4, F:4 | AN10: I:5 | AO10: I:5, A:3 | AP10: 技能/治疗
A11: SONIA | B11: =IFERROR(VLOOKUP($A11,全人物技能说明!$A$1:$O$99,2,FALSE),"") -> 索尼娅 | C11: 29 | D11: =IFERROR(VLOOKUP($A11,全人物技能说明!$A$1:$O$99,3,FALSE),"") -> 3箱子 | E11: =IFERROR(VLOOKUP($A11,全人物技能说明!$A$1:$O$99,4,FALSE),"") -> 稀有 | F11: =IFERROR(VLOOKUP($A11,全人物技能说明!$A$1:$O$99,7,FALSE),"") -> 0 | G11: =IFERROR(VLOOKUP($A11,全人物技能说明!$A$1:$O$99,8,FALSE),"") -> 发动 4 连击，每次攻击造成 [75% DPS] 伤害。 | H11: 发动2次连续攻击，每次造成 [75% DPS] 伤害。 | I11: =IFERROR(VLOOKUP($A11,全人物技能说明!$A$1:$O$99,14,FALSE),"") -> A | J11: =IFERROR(VLOOKUP($A11,全人物技能说明!$A$1:$O$99,15,FALSE),"") -> I, U | K11: I | L11: I | M11: =IFERROR(IF(VLOOKUP($A11,全人物技能说明!$A$1:$O$99,7,FALSE)<>"",VLOOKUP($A11,全人物技能说明!$A$1:$O$99,7,FALSE),""),"") | O11: 矿石 | P11: =RANK(Y11,Y:Y) -> 9 | Q11: =RANK(Z11,Z:Z) -> 6 | R11: =RANK(AA11,AA:AA) -> 17 | S11: =RANK(AB11,AB:AB) -> 7 | T11: =RANK(AC11,AC:AC) -> 17 | U11: =Y11+Z11+AA11+AB11+AC11 -> 1020 | W11: =C11 -> 29 | Y11: =IFERROR(VALUE(LEFT(AE11,FIND("(",AE11)-1))+($W11-1)*VALUE(MID(AE11,FIND("+",AE11)+1,FIND(")",AE11)-FIND("+",AE11)-1)),"") -> 210 | Z11: =IFERROR(VALUE(LEFT(AF11,FIND("(",AF11)-1))+($W11-1)*VALUE(MID(AF11,FIND("+",AF11)+1,FIND(")",AF11)-FIND("+",AF11)-1)),"") -> 244 | AA11: =IFERROR(VALUE(LEFT(AG11,FIND("(",AG11)-1))+($W11-1)*VALUE(MID(AG11,FIND("+",AG11)+1,FIND(")",AG11)-FIND("+",AG11)-1)),"") -> 178 | AB11: =IFERROR(VALUE(LEFT(AH11,FIND("(",AH11)-1))+($W11-1)*VALUE(MID(AH11,FIND("+",AH11)+1,FIND(")",AH11)-FIND("+",AH11)-1)),"") -> 210 | AC11: =IFERROR(VALUE(LEFT(AI11,FIND("(",AI11)-1))+($W11-1)*VALUE(MID(AI11,FIND("+",AI11)+1,FIND(")",AI11)-FIND("+",AI11)-1)),"") -> 178 | AE11: =IFERROR(VLOOKUP($A11,全人物技能说明!$A$1:$O$99,9,FALSE),"") -> 42(+6) | AF11: =IFERROR(VLOOKUP($A11,全人物技能说明!$A$1:$O$99,10,FALSE),"") -> 48(+7) | AG11: =IFERROR(VLOOKUP($A11,全人物技能说明!$A$1:$O$99,11,FALSE),"") -> 38(+5) | AH11: =IFERROR(VLOOKUP($A11,全人物技能说明!$A$1:$O$99,12,FALSE),"") -> 42(+6) | AI11: =IFERROR(VLOOKUP($A11,全人物技能说明!$A$1:$O$99,13,FALSE),"") -> 38(+5) | AL11: 坦克组 (Beatrix, Banka, Martha, Lady Judith, Momoka, Ann, Veneza) | AM11: 巨型扳手 (Giant Wrench) | AN11: 埃莉诺·塞特 (Eleanor Set - 裙) 或 统治 (Dominance) | AO11: 手工棒棒糖 (Handmade Lollipop) | AP11: F/U (生存)
A12: Ann | B12: =IFERROR(VLOOKUP($A12,全人物技能说明!$A$1:$O$99,2,FALSE),"") -> 安 | C12: 29 | D12: =IFERROR(VLOOKUP($A12,全人物技能说明!$A$1:$O$99,3,FALSE),"") -> 3箱子 | E12: =IFERROR(VLOOKUP($A12,全人物技能说明!$A$1:$O$99,4,FALSE),"") -> 稀有 | F12: =IFERROR(VLOOKUP($A12,全人物技能说明!$A$1:$O$99,7,FALSE),"") -> X2武士刀，4次。X4匕首7次 | G12: =IFERROR(VLOOKUP($A12,全人物技能说明!$A$1:$O$99,8,FALSE),"") -> 为最多 2 名血量最低的队友提供美食，回复 [20% AGI] 生命值，并在 4 回合内提升 50% 护甲。 | H12: 为最多 2 名生命值最低的盟友治疗[20% 敏捷]并增加50%护甲，持续4 回合。 | I12: =IFERROR(VLOOKUP($A12,全人物技能说明!$A$1:$O$99,14,FALSE),"") -> U | J12: =IFERROR(VLOOKUP($A12,全人物技能说明!$A$1:$O$99,15,FALSE),"") -> W, I | K12: A | L12: A | M12: =IFERROR(IF(VLOOKUP($A12,全人物技能说明!$A$1:$O$99,7,FALSE)<>"",VLOOKUP($A12,全人物技能说明!$A$1:$O$99,7,FALSE),""),"") -> X2武士刀，4次。X4匕首7次 | O12: F | P12: =RANK(Y12,Y:Y) -> 20 | Q12: =RANK(Z12,Z:Z) -> 11 | R12: =RANK(AA12,AA:AA) -> 17 | S12: =RANK(AB12,AB:AB) -> 7 | T12: =RANK(AC12,AC:AC) -> 5 | U12: =Y12+Z12+AA12+AB12+AC12 -> 1020 | W12: =C12 -> 29 | Y12: =IFERROR(VALUE(LEFT(AE12,FIND("(",AE12)-1))+($W12-1)*VALUE(MID(AE12,FIND("+",AE12)+1,FIND(")",AE12)-FIND("+",AE12)-1)),"") -> 178 | Z12: =IFERROR(VALUE(LEFT(AF12,FIND("(",AF12)-1))+($W12-1)*VALUE(MID(AF12,FIND("+",AF12)+1,FIND(")",AF12)-FIND("+",AF12)-1)),"") -> 210 | AA12: =IFERROR(VALUE(LEFT(AG12,FIND("(",AG12)-1))+($W12-1)*VALUE(MID(AG12,FIND("+",AG12)+1,FIND(")",AG12)-FIND("+",AG12)-1)),"") -> 178 | AB12: =IFERROR(VALUE(LEFT(AH12,FIND("(",AH12)-1))+($W12-1)*VALUE(MID(AH12,FIND("+",AH12)+1,FIND(")",AH12)-FIND("+",AH12)-1)),"") -> 210 | AC12: =IFERROR(VALUE(LEFT(AI12,FIND("(",AI12)-1))+($W12-1)*VALUE(MID(AI12,FIND("+",AI12)+1,FIND(")",AI12)-FIND("+",AI12)-1)),"") -> 244 | AE12: =IFERROR(VLOOKUP($A12,全人物技能说明!$A$1:$O$99,9,FALSE),"") -> 38(+5) | AF12: =IFERROR(VLOOKUP($A12,全人物技能说明!$A$1:$O$99,10,FALSE),"") -> 42(+6) | AG12: =IFERROR(VLOOKUP($A12,全人物技能说明!$A$1:$O$99,11,FALSE),"") -> 38(+5) | AH12: =IFERROR(VLOOKUP($A12,全人物技能说明!$A$1:$O$99,12,FALSE),"") -> 42(+6) | AI12: =IFERROR(VLOOKUP($A12,全人物技能说明!$A$1:$O$99,13,FALSE),"") -> 48(+7)
A13: MARTINA | B13: =IFERROR(VLOOKUP($A13,全人物技能说明!$A$1:$O$99,2,FALSE),"") -> 玛蒂娜 | C13: 28 | D13: =IFERROR(VLOOKUP($A13,全人物技能说明!$A$1:$O$99,3,FALSE),"") -> 1剧情 | E13: =IFERROR(VLOOKUP($A13,全人物技能说明!$A$1:$O$99,4,FALSE),"") -> 普通 | F13: =IFERROR(VLOOKUP($A13,全人物技能说明!$A$1:$O$99,7,FALSE),"") -> 0 | G13: =IFERROR(VLOOKUP($A13,全人物技能说明!$A$1:$O$99,8,FALSE),"") -> 跳向最虚弱的敌人，造成 [200% DPS] 伤害。 | H13: 跳跃到最弱的敌人身上，造成 [150?% DPS] 伤害。 | I13: =IFERROR(VLOOKUP($A13,全人物技能说明!$A$1:$O$99,14,FALSE),"") -> W, I | J13: =IFERROR(VLOOKUP($A13,全人物技能说明!$A$1:$O$99,15,FALSE),"") -> A | K13: W | L13: W | M13: =IFERROR(IF(VLOOKUP($A13,全人物技能说明!$A$1:$O$99,7,FALSE)<>"",VLOOKUP($A13,全人物技能说明!$A$1:$O$99,7,FALSE),""),"") | O13: 广播 | P13: =RANK(Y13,Y:Y) -> 5 | Q13: =RANK(Z13,Z:Z) -> 24 | R13: =RANK(AA13,AA:AA) -> 5 | S13: =RANK(AB13,AB:AB) -> 19 | T13: =RANK(AC13,AC:AC) -> 12 | U13: =Y13+Z13+AA13+AB13+AC13 -> 991 | W13: =C13 -> 28 | Y13: =IFERROR(VALUE(LEFT(AE13,FIND("(",AE13)-1))+($W13-1)*VALUE(MID(AE13,FIND("+",AE13)+1,FIND(")",AE13)-FIND("+",AE13)-1)),"") -> 237 | Z13: =IFERROR(VALUE(LEFT(AF13,FIND("(",AF13)-1))+($W13-1)*VALUE(MID(AF13,FIND("+",AF13)+1,FIND(")",AF13)-FIND("+",AF13)-1)),"") -> 140 | AA13: =IFERROR(VALUE(LEFT(AG13,FIND("(",AG13)-1))+($W13-1)*VALUE(MID(AG13,FIND("+",AG13)+1,FIND(")",AG13)-FIND("+",AG13)-1)),"") -> 237 | AB13: =IFERROR(VALUE(LEFT(AH13,FIND("(",AH13)-1))+($W13-1)*VALUE(MID(AH13,FIND("+",AH13)+1,FIND(")",AH13)-FIND("+",AH13)-1)),"") -> 173 | AC13: =IFERROR(VALUE(LEFT(AI13,FIND("(",AI13)-1))+($W13-1)*VALUE(MID(AI13,FIND("+",AI13)+1,FIND(")",AI13)-FIND("+",AI13)-1)),"") -> 204 | AE13: =IFERROR(VLOOKUP($A13,全人物技能说明!$A$1:$O$99,9,FALSE),"") -> 48(+7) | AF13: =IFERROR(VLOOKUP($A13,全人物技能说明!$A$1:$O$99,10,FALSE),"") -> 32(+4) | AG13: =IFERROR(VLOOKUP($A13,全人物技能说明!$A$1:$O$99,11,FALSE),"") -> 48(+7) | AH13: =IFERROR(VLOOKUP($A13,全人物技能说明!$A$1:$O$99,12,FALSE),"") -> 38(+5) | AI13: =IFERROR(VLOOKUP($A13,全人物技能说明!$A$1:$O$99,13,FALSE),"") -> 42(+6) | AM13: F:5, U:5 | AN13: F:5, U:5 | AO13: U:5, F:4 | AP13: 嘲讽/减伤
A14: LANE | B14: =IFERROR(VLOOKUP($A14,全人物技能说明!$A$1:$O$99,2,FALSE),"") -> 莱恩 | C14: 27 | D14: =IFERROR(VLOOKUP($A14,全人物技能说明!$A$1:$O$99,3,FALSE),"") -> 3剧情 | E14: =IFERROR(VLOOKUP($A14,全人物技能说明!$A$1:$O$99,4,FALSE),"") -> 稀有 | F14: =IFERROR(VLOOKUP($A14,全人物技能说明!$A$1:$O$99,7,FALSE),"") -> 0 | G14: =IFERROR(VLOOKUP($A14,全人物技能说明!$A$1:$O$99,8,FALSE),"") -> 骇入敌人装备，对 4 名敌人造成 [25% INT] 伤害，并在 5 回合内减少其 25% 输出伤害。 | H14: 入侵敌方装备，对2名敌人造成 [25% 智力] 伤害，并减少其 25% 伤害，持续2回合。 | I14: =IFERROR(VLOOKUP($A14,全人物技能说明!$A$1:$O$99,14,FALSE),"") -> W, I | J14: =IFERROR(VLOOKUP($A14,全人物技能说明!$A$1:$O$99,15,FALSE),"") -> F | K14: I | L14: I | M14: =IFERROR(IF(VLOOKUP($A14,全人物技能说明!$A$1:$O$99,7,FALSE)<>"",VLOOKUP($A14,全人物技能说明!$A$1:$O$99,7,FALSE),""),"") | O14: 广播 | P14: =RANK(Y14,Y:Y) -> 7 | Q14: =RANK(Z14,Z:Z) -> 17 | R14: =RANK(AA14,AA:AA) -> 7 | S14: =RANK(AB14,AB:AB) -> 28 | T14: =RANK(AC14,AC:AC) -> 13 | U14: =Y14+Z14+AA14+AB14+AC14 -> 933 | W14: =C14 -> 27 | Y14: =IFERROR(VALUE(LEFT(AE14,FIND("(",AE14)-1))+($W14-1)*VALUE(MID(AE14,FIND("+",AE14)+1,FIND(")",AE14)-FIND("+",AE14)-1)),"") -> 223 | Z14: =IFERROR(VALUE(LEFT(AF14,FIND("(",AF14)-1))+($W14-1)*VALUE(MID(AF14,FIND("+",AF14)+1,FIND(")",AF14)-FIND("+",AF14)-1)),"") -> 163 | AA14: =IFERROR(VALUE(LEFT(AG14,FIND("(",AG14)-1))+($W14-1)*VALUE(MID(AG14,FIND("+",AG14)+1,FIND(")",AG14)-FIND("+",AG14)-1)),"") -> 223 | AB14: =IFERROR(VALUE(LEFT(AH14,FIND("(",AH14)-1))+($W14-1)*VALUE(MID(AH14,FIND("+",AH14)+1,FIND(")",AH14)-FIND("+",AH14)-1)),"") -> 132 | AC14: =IFERROR(VALUE(LEFT(AI14,FIND("(",AI14)-1))+($W14-1)*VALUE(MID(AI14,FIND("+",AI14)+1,FIND(")",AI14)-FIND("+",AI14)-1)),"") -> 192 | AE14: =IFERROR(VLOOKUP($A14,全人物技能说明!$A$1:$O$99,9,FALSE),"") -> 41(+7) | AF14: =IFERROR(VLOOKUP($A14,全人物技能说明!$A$1:$O$99,10,FALSE),"") -> 33(+5) | AG14: =IFERROR(VLOOKUP($A14,全人物技能说明!$A$1:$O$99,11,FALSE),"") -> 41(+7) | AH14: =IFERROR(VLOOKUP($A14,全人物技能说明!$A$1:$O$99,12,FALSE),"") -> 28(+4) | AI14: =IFERROR(VLOOKUP($A14,全人物技能说明!$A$1:$O$99,13,FALSE),"") -> 36(+6) | AL14: 平衡/特殊 (Irma, Foxy, PamOne, PamTwo) | AM14: 爱之弓 (Bow of Love) | AN14: JNT套装 (JNT Set) | AO14: 可爱胸针 (Cute Brooch) | AP14: 均衡成长
A15: KARIN | B15: =IFERROR(VLOOKUP($A15,全人物技能说明!$A$1:$O$99,2,FALSE),"") -> 卡琳 | C15: 24 | D15: =IFERROR(VLOOKUP($A15,全人物技能说明!$A$1:$O$99,3,FALSE),"") -> 1箱子 | E15: =IFERROR(VLOOKUP($A15,全人物技能说明!$A$1:$O$99,4,FALSE),"") -> 稀有 | F15: =IFERROR(VLOOKUP($A15,全人物技能说明!$A$1:$O$99,7,FALSE),"") -> 重管，围绕A因为那条分支上AFU。重管在 A、F和U方面的属性是第二高 | G15: =IFERROR(VLOOKUP($A15,全人物技能说明!$A$1:$O$99,8,FALSE),"") -> 恢复活力，回复 [35% HP] 并在 2 回合内获得 [130% DEF] 防御加成。 | H15: 恢复活力，治疗 [?% HP] 生命值两种防御力增强40%，持续5回合。 | I15: =IFERROR(VLOOKUP($A15,全人物技能说明!$A$1:$O$99,14,FALSE),"") -> W, A | J15: =IFERROR(VLOOKUP($A15,全人物技能说明!$A$1:$O$99,15,FALSE),"") -> I, U | K15: F? | L15: AwF | M15: =IFERROR(IF(VLOOKUP($A15,全人物技能说明!$A$1:$O$99,7,FALSE)<>"",VLOOKUP($A15,全人物技能说明!$A$1:$O$99,7,FALSE),""),"") -> 重管，围绕A因为那条分支上AFU。重管在 A、F和U方面的属性是第二高 | O15: 外WI | P15: =RANK(Y15,Y:Y) -> 4 | Q15: =RANK(Z15,Z:Z) -> 8 | R15: =RANK(AA15,AA:AA) -> 15 | S15: =RANK(AB15,AB:AB) -> 9 | T15: =RANK(AC15,AC:AC) -> 16 | U15: =Y15+Z15+AA15+AB15+AC15 -> 1049 | W15: =C15 -> 24 | X15: 1 | Y15: =IFERROR(VALUE(LEFT(AE15,FIND("(",AE15)-1))+($W15-1)*VALUE(MID(AE15,FIND("+",AE15)+1,FIND(")",AE15)-FIND("+",AE15)-1)),"") -> 238 | Z15: =IFERROR(VALUE(LEFT(AF15,FIND("(",AF15)-1))+($W15-1)*VALUE(MID(AF15,FIND("+",AF15)+1,FIND(")",AF15)-FIND("+",AF15)-1)),"") -> 238 | AA15: =IFERROR(VALUE(LEFT(AG15,FIND("(",AG15)-1))+($W15-1)*VALUE(MID(AG15,FIND("+",AG15)+1,FIND(")",AG15)-FIND("+",AG15)-1)),"") -> 182 | AB15: =IFERROR(VALUE(LEFT(AH15,FIND("(",AH15)-1))+($W15-1)*VALUE(MID(AH15,FIND("+",AH15)+1,FIND(")",AH15)-FIND("+",AH15)-1)),"") -> 209 | AC15: =IFERROR(VALUE(LEFT(AI15,FIND("(",AI15)-1))+($W15-1)*VALUE(MID(AI15,FIND("+",AI15)+1,FIND(")",AI15)-FIND("+",AI15)-1)),"") -> 182 | AE15: =IFERROR(VLOOKUP($A15,全人物技能说明!$A$1:$O$99,9,FALSE),"") -> 54(+8) | AF15: =IFERROR(VLOOKUP($A15,全人物技能说明!$A$1:$O$99,10,FALSE),"") -> 54(+8) | AG15: =IFERROR(VLOOKUP($A15,全人物技能说明!$A$1:$O$99,11,FALSE),"") -> 44(+6) | AH15: =IFERROR(VLOOKUP($A15,全人物技能说明!$A$1:$O$99,12,FALSE),"") -> 48(+7) | AI15: =IFERROR(VLOOKUP($A15,全人物技能说明!$A$1:$O$99,13,FALSE),"") -> 44(+6)
A16: Momoka | B16: =IFERROR(VLOOKUP($A16,全人物技能说明!$A$1:$O$99,2,FALSE),"") -> 桃香 | C16: 24 | D16: =IFERROR(VLOOKUP($A16,全人物技能说明!$A$1:$O$99,3,FALSE),"") -> 2箱子 | E16: =IFERROR(VLOOKUP($A16,全人物技能说明!$A$1:$O$99,4,FALSE),"") -> 传说 | F16: =IFERROR(VLOOKUP($A16,全人物技能说明!$A$1:$O$99,7,FALSE),"") -> 0 | G16: =IFERROR(VLOOKUP($A16,全人物技能说明!$A$1:$O$99,8,FALSE),"") -> 揭发恶徒，指挥 1 名队友立即攻击对方。 | H16: 暴露一个恶棍，命令两个盟友立即攻击他。 | I16: =IFERROR(VLOOKUP($A16,全人物技能说明!$A$1:$O$99,14,FALSE),"") -> F, U | J16: =IFERROR(VLOOKUP($A16,全人物技能说明!$A$1:$O$99,15,FALSE),"") -> W | L16: A | M16: =IFERROR(IF(VLOOKUP($A16,全人物技能说明!$A$1:$O$99,7,FALSE)<>"",VLOOKUP($A16,全人物技能说明!$A$1:$O$99,7,FALSE),""),"") | O16: F | P16: =RANK(Y16,Y:Y) -> 33 | Q16: =RANK(Z16,Z:Z) -> 19 | R16: =RANK(AA16,AA:AA) -> 16 | S16: =RANK(AB16,AB:AB) -> 9 | T16: =RANK(AC16,AC:AC) -> 10 | U16: =Y16+Z16+AA16+AB16+AC16 -> 875 | W16: =C16 -> 24 | Y16: =IFERROR(VALUE(LEFT(AE16,FIND("(",AE16)-1))+($W16-1)*VALUE(MID(AE16,FIND("+",AE16)+1,FIND(")",AE16)-FIND("+",AE16)-1)),"") -> 124 | Z16: =IFERROR(VALUE(LEFT(AF16,FIND("(",AF16)-1))+($W16-1)*VALUE(MID(AF16,FIND("+",AF16)+1,FIND(")",AF16)-FIND("+",AF16)-1)),"") -> 153 | AA16: =IFERROR(VALUE(LEFT(AG16,FIND("(",AG16)-1))+($W16-1)*VALUE(MID(AG16,FIND("+",AG16)+1,FIND(")",AG16)-FIND("+",AG16)-1)),"") -> 180 | AB16: =IFERROR(VALUE(LEFT(AH16,FIND("(",AH16)-1))+($W16-1)*VALUE(MID(AH16,FIND("+",AH16)+1,FIND(")",AH16)-FIND("+",AH16)-1)),"") -> 209 | AC16: =IFERROR(VALUE(LEFT(AI16,FIND("(",AI16)-1))+($W16-1)*VALUE(MID(AI16,FIND("+",AI16)+1,FIND(")",AI16)-FIND("+",AI16)-1)),"") -> 209 | AE16: =IFERROR(VLOOKUP($A16,全人物技能说明!$A$1:$O$99,9,FALSE),"") -> 32(+4) | AF16: =IFERROR(VLOOKUP($A16,全人物技能说明!$A$1:$O$99,10,FALSE),"") -> 38(+5) | AG16: =IFERROR(VLOOKUP($A16,全人物技能说明!$A$1:$O$99,11,FALSE),"") -> 42(+6) | AH16: =IFERROR(VLOOKUP($A16,全人物技能说明!$A$1:$O$99,12,FALSE),"") -> 48(+7) | AI16: =IFERROR(VLOOKUP($A16,全人物技能说明!$A$1:$O$99,13,FALSE),"") -> 48(+7) | AM16: W:3, A:4 | AN16: 全属性:3 | AO16: W:4, F:4
A17: CRAZY | B17: =IFERROR(VLOOKUP($A17,全人物技能说明!$A$1:$O$99,2,FALSE),"") -> 疯狂 | C17: 20 | D17: =IFERROR(VLOOKUP($A17,全人物技能说明!$A$1:$O$99,3,FALSE),"") -> 1箱子 | E17: =IFERROR(VLOOKUP($A17,全人物技能说明!$A$1:$O$99,4,FALSE),"") -> 稀有 | F17: =IFERROR(VLOOKUP($A17,全人物技能说明!$A$1:$O$99,7,FALSE),"") -> 0 | G17: =IFERROR(VLOOKUP($A17,全人物技能说明!$A$1:$O$99,8,FALSE),"") -> 向最多 4 名敌人投掷炸弹，造成 [75% DPS] 伤害。 | H17: 向最多 4 名敌人投掷炸弹，对其造成 [75% DPS] 伤害。 | I17: =IFERROR(VLOOKUP($A17,全人物技能说明!$A$1:$O$99,14,FALSE),"") -> A | J17: =IFERROR(VLOOKUP($A17,全人物技能说明!$A$1:$O$99,15,FALSE),"") -> W, U | K17: A | L17: A | M17: =IFERROR(IF(VLOOKUP($A17,全人物技能说明!$A$1:$O$99,7,FALSE)<>"",VLOOKUP($A17,全人物技能说明!$A$1:$O$99,7,FALSE),""),"") | O17: 矿石 | P17: =RANK(Y17,Y:Y) -> 17 | Q17: =RANK(Z17,Z:Z) -> 3 | R17: =RANK(AA17,AA:AA) -> 8 | S17: =RANK(AB17,AB:AB) -> 11 | T17: =RANK(AC17,AC:AC) -> 15 | U17: =Y17+Z17+AA17+AB17+AC17 -> 1053 | W17: =C17 -> 20 | Y17: =IFERROR(VALUE(LEFT(AE17,FIND("(",AE17)-1))+($W17-1)*VALUE(MID(AE17,FIND("+",AE17)+1,FIND(")",AE17)-FIND("+",AE17)-1)),"") -> 183 | Z17: =IFERROR(VALUE(LEFT(AF17,FIND("(",AF17)-1))+($W17-1)*VALUE(MID(AF17,FIND("+",AF17)+1,FIND(")",AF17)-FIND("+",AF17)-1)),"") -> 275 | AA17: =IFERROR(VALUE(LEFT(AG17,FIND("(",AG17)-1))+($W17-1)*VALUE(MID(AG17,FIND("+",AG17)+1,FIND(")",AG17)-FIND("+",AG17)-1)),"") -> 206 | AB17: =IFERROR(VALUE(LEFT(AH17,FIND("(",AH17)-1))+($W17-1)*VALUE(MID(AH17,FIND("+",AH17)+1,FIND(")",AH17)-FIND("+",AH17)-1)),"") -> 206 | AC17: =IFERROR(VALUE(LEFT(AI17,FIND("(",AI17)-1))+($W17-1)*VALUE(MID(AI17,FIND("+",AI17)+1,FIND(")",AI17)-FIND("+",AI17)-1)),"") -> 183 | AE17: =IFERROR(VLOOKUP($A17,全人物技能说明!$A$1:$O$99,9,FALSE),"") -> 50(+7) | AF17: =IFERROR(VLOOKUP($A17,全人物技能说明!$A$1:$O$99,10,FALSE),"") -> 66(+11) | AG17: =IFERROR(VLOOKUP($A17,全人物技能说明!$A$1:$O$99,11,FALSE),"") -> 54(+8) | AH17: =IFERROR(VLOOKUP($A17,全人物技能说明!$A$1:$O$99,12,FALSE),"") -> 54(+8) | AI17: =IFERROR(VLOOKUP($A17,全人物技能说明!$A$1:$O$99,13,FALSE),"") -> 50(+7) | AL17: 工人类 (YASU, ANGELA, Sakaki) | AM17: 扳手 (Wrench) | AN17: 技工上衣 (Mechanic Top) & 技工裙 (Mechanic Skirt) | AO17: 生日纸杯蛋糕 (Birthday Cupcake) | AP17: 生产效率
A18: TESS | B18: =IFERROR(VLOOKUP($A18,全人物技能说明!$A$1:$O$99,2,FALSE),"") -> 泰丝 | C18: 20 | D18: =IFERROR(VLOOKUP($A18,全人物技能说明!$A$1:$O$99,3,FALSE),"") -> 3剧情 | E18: =IFERROR(VLOOKUP($A18,全人物技能说明!$A$1:$O$99,4,FALSE),"") -> 稀有 | F18: =IFERROR(VLOOKUP($A18,全人物技能说明!$A$1:$O$99,7,FALSE),"") -> Tess嘲讽充能速度最快，用X4要快得多，使用管状武器需要 3 次攻击 | G18: =IFERROR(VLOOKUP($A18,全人物技能说明!$A$1:$O$99,8,FALSE),"") -> 嘲讽敌人 2 回合，减少 60% 所受到的伤害。 | H18: 嘲讽所有敌人1回合，将接下来6次攻击造成伤害减少50%。 | I18: =IFERROR(VLOOKUP($A18,全人物技能说明!$A$1:$O$99,14,FALSE),"") -> A, U | J18: =IFERROR(VLOOKUP($A18,全人物技能说明!$A$1:$O$99,15,FALSE),"") -> W, I | L18: A | M18: =IFERROR(IF(VLOOKUP($A18,全人物技能说明!$A$1:$O$99,7,FALSE)<>"",VLOOKUP($A18,全人物技能说明!$A$1:$O$99,7,FALSE),""),"") -> Tess嘲讽充能速度最快，用X4要快得多，使用管状武器需要 3 次攻击 | P18: =RANK(Y18,Y:Y) -> 22 | Q18: =RANK(Z18,Z:Z) -> 12 | R18: =RANK(AA18,AA:AA) -> 22 | S18: =RANK(AB18,AB:AB) -> 18 | T18: =RANK(AC18,AC:AC) -> 11 | U18: =Y18+Z18+AA18+AB18+AC18 -> 909 | W18: =C18 -> 20 | X18: 1 | Y18: =IFERROR(VALUE(LEFT(AE18,FIND("(",AE18)-1))+($W18-1)*VALUE(MID(AE18,FIND("+",AE18)+1,FIND(")",AE18)-FIND("+",AE18)-1)),"") -> 158 | Z18: =IFERROR(VALUE(LEFT(AF18,FIND("(",AF18)-1))+($W18-1)*VALUE(MID(AF18,FIND("+",AF18)+1,FIND(")",AF18)-FIND("+",AF18)-1)),"") -> 206 | AA18: =IFERROR(VALUE(LEFT(AG18,FIND("(",AG18)-1))+($W18-1)*VALUE(MID(AG18,FIND("+",AG18)+1,FIND(")",AG18)-FIND("+",AG18)-1)),"") -> 158 | AB18: =IFERROR(VALUE(LEFT(AH18,FIND("(",AH18)-1))+($W18-1)*VALUE(MID(AH18,FIND("+",AH18)+1,FIND(")",AH18)-FIND("+",AH18)-1)),"") -> 181 | AC18: =IFERROR(VALUE(LEFT(AI18,FIND("(",AI18)-1))+($W18-1)*VALUE(MID(AI18,FIND("+",AI18)+1,FIND(")",AI18)-FIND("+",AI18)-1)),"") -> 206 | AE18: =IFERROR(VLOOKUP($A18,全人物技能说明!$A$1:$O$99,9,FALSE),"") -> 44(+6) | AF18: =IFERROR(VLOOKUP($A18,全人物技能说明!$A$1:$O$99,10,FALSE),"") -> 54(+8) | AG18: =IFERROR(VLOOKUP($A18,全人物技能说明!$A$1:$O$99,11,FALSE),"") -> 44(+6) | AH18: =IFERROR(VLOOKUP($A18,全人物技能说明!$A$1:$O$99,12,FALSE),"") -> 48(+7) | AI18: =IFERROR(VLOOKUP($A18,全人物技能说明!$A$1:$O$99,13,FALSE),"") -> 54(+8)
A19: SARA | B19: =IFERROR(VLOOKUP($A19,全人物技能说明!$A$1:$O$99,2,FALSE),"") -> 萨拉 | C19: 18 | D19: =IFERROR(VLOOKUP($A19,全人物技能说明!$A$1:$O$99,3,FALSE),"") -> 2剧情 | E19: =IFERROR(VLOOKUP($A19,全人物技能说明!$A$1:$O$99,4,FALSE),"") -> 稀有 | F19: =IFERROR(VLOOKUP($A19,全人物技能说明!$A$1:$O$99,7,FALSE),"") -> 0 | G19: =IFERROR(VLOOKUP($A19,全人物技能说明!$A$1:$O$99,8,FALSE),"") -> 指挥 2 名队友立即攻击一名敌人。 | H19: 命令 2 名盟友立即攻击一名敌人。 | I19: =IFERROR(VLOOKUP($A19,全人物技能说明!$A$1:$O$99,14,FALSE),"") -> I, F | J19: =IFERROR(VLOOKUP($A19,全人物技能说明!$A$1:$O$99,15,FALSE),"") -> A, U | L19: I | M19: =IFERROR(IF(VLOOKUP($A19,全人物技能说明!$A$1:$O$99,7,FALSE)<>"",VLOOKUP($A19,全人物技能说明!$A$1:$O$99,7,FALSE),""),"") | O19: 血瓶 | P19: =RANK(Y19,Y:Y) -> 21 | Q19: =RANK(Z19,Z:Z) -> 23 | R19: =RANK(AA19,AA:AA) -> 13 | S19: =RANK(AB19,AB:AB) -> 16 | T19: =RANK(AC19,AC:AC) -> 21 | U19: =Y19+Z19+AA19+AB19+AC19 -> 839 | W19: =C19 -> 18 | Y19: =IFERROR(VALUE(LEFT(AE19,FIND("(",AE19)-1))+($W19-1)*VALUE(MID(AE19,FIND("+",AE19)+1,FIND(")",AE19)-FIND("+",AE19)-1)),"") -> 167 | Z19: =IFERROR(VALUE(LEFT(AF19,FIND("(",AF19)-1))+($W19-1)*VALUE(MID(AF19,FIND("+",AF19)+1,FIND(")",AF19)-FIND("+",AF19)-1)),"") -> 146 | AA19: =IFERROR(VALUE(LEFT(AG19,FIND("(",AG19)-1))+($W19-1)*VALUE(MID(AG19,FIND("+",AG19)+1,FIND(")",AG19)-FIND("+",AG19)-1)),"") -> 190 | AB19: =IFERROR(VALUE(LEFT(AH19,FIND("(",AH19)-1))+($W19-1)*VALUE(MID(AH19,FIND("+",AH19)+1,FIND(")",AH19)-FIND("+",AH19)-1)),"") -> 190 | AC19: =IFERROR(VALUE(LEFT(AI19,FIND("(",AI19)-1))+($W19-1)*VALUE(MID(AI19,FIND("+",AI19)+1,FIND(")",AI19)-FIND("+",AI19)-1)),"") -> 146 | AE19: =IFERROR(VLOOKUP($A19,全人物技能说明!$A$1:$O$99,9,FALSE),"") -> 48(+7) | AF19: =IFERROR(VLOOKUP($A19,全人物技能说明!$A$1:$O$99,10,FALSE),"") -> 44(+6) | AG19: =IFERROR(VLOOKUP($A19,全人物技能说明!$A$1:$O$99,11,FALSE),"") -> 54(+8) | AH19: =IFERROR(VLOOKUP($A19,全人物技能说明!$A$1:$O$99,12,FALSE),"") -> 54(+8) | AI19: =IFERROR(VLOOKUP($A19,全人物技能说明!$A$1:$O$99,13,FALSE),"") -> 44(+6) | AM19: F:5, U:5 | AN19: F:5, U:5 | AO19: F:5, I:5
A20: KIARA | B20: =IFERROR(VLOOKUP($A20,全人物技能说明!$A$1:$O$99,2,FALSE),"") -> 琪亚拉 | C20: 17 | D20: =IFERROR(VLOOKUP($A20,全人物技能说明!$A$1:$O$99,3,FALSE),"") -> 4箱子 | E20: =IFERROR(VLOOKUP($A20,全人物技能说明!$A$1:$O$99,4,FALSE),"") -> 史诗 | F20: =IFERROR(VLOOKUP($A20,全人物技能说明!$A$1:$O$99,7,FALSE),"") -> 0 | G20: =IFERROR(VLOOKUP($A20,全人物技能说明!$A$1:$O$99,8,FALSE),"") -> 指挥 1 名队友瞬间攻击一名敌人。 | H20: 命令2名盟友立即攻击一名敌人。 | I20: =IFERROR(VLOOKUP($A20,全人物技能说明!$A$1:$O$99,14,FALSE),"") -> W, A, F | J20: =IFERROR(VLOOKUP($A20,全人物技能说明!$A$1:$O$99,15,FALSE),"") -> U | L20: A | M20: =IFERROR(IF(VLOOKUP($A20,全人物技能说明!$A$1:$O$99,7,FALSE)<>"",VLOOKUP($A20,全人物技能说明!$A$1:$O$99,7,FALSE),""),"") | P20: =RANK(Y20,Y:Y) -> 19 | Q20: =RANK(Z20,Z:Z) -> 15 | R20: =RANK(AA20,AA:AA) -> 26 | S20: =RANK(AB20,AB:AB) -> 17 | T20: =RANK(AC20,AC:AC) -> 34 | U20: =Y20+Z20+AA20+AB20+AC20 -> 805 | W20: =C20 -> 17 | Y20: =IFERROR(VALUE(LEFT(AE20,FIND("(",AE20)-1))+($W20-1)*VALUE(MID(AE20,FIND("+",AE20)+1,FIND(")",AE20)-FIND("+",AE20)-1)),"") -> 182 | Z20: =IFERROR(VALUE(LEFT(AF20,FIND("(",AF20)-1))+($W20-1)*VALUE(MID(AF20,FIND("+",AF20)+1,FIND(")",AF20)-FIND("+",AF20)-1)),"") -> 182 | AA20: =IFERROR(VALUE(LEFT(AG20,FIND("(",AG20)-1))+($W20-1)*VALUE(MID(AG20,FIND("+",AG20)+1,FIND(")",AG20)-FIND("+",AG20)-1)),"") -> 141 | AB20: =IFERROR(VALUE(LEFT(AH20,FIND("(",AH20)-1))+($W20-1)*VALUE(MID(AH20,FIND("+",AH20)+1,FIND(")",AH20)-FIND("+",AH20)-1)),"") -> 182 | AC20: =IFERROR(VALUE(LEFT(AI20,FIND("(",AI20)-1))+($W20-1)*VALUE(MID(AI20,FIND("+",AI20)+1,FIND(")",AI20)-FIND("+",AI20)-1)),"") -> 118 | AE20: =IFERROR(VLOOKUP($A20,全人物技能说明!$A$1:$O$99,9,FALSE),"") -> 54(+8) | AF20: =IFERROR(VLOOKUP($A20,全人物技能说明!$A$1:$O$99,10,FALSE),"") -> 54(+8) | AG20: =IFERROR(VLOOKUP($A20,全人物技能说明!$A$1:$O$99,11,FALSE),"") -> 45(+6) | AH20: =IFERROR(VLOOKUP($A20,全人物技能说明!$A$1:$O$99,12,FALSE),"") -> 54(+8) | AI20: =IFERROR(VLOOKUP($A20,全人物技能说明!$A$1:$O$99,13,FALSE),"") -> 38(+5)
A21: SAMANTHA | B21: =IFERROR(VLOOKUP($A21,全人物技能说明!$A$1:$O$99,2,FALSE),"") -> 萨曼莎 | C21: 15 | D21: =IFERROR(VLOOKUP($A21,全人物技能说明!$A$1:$O$99,3,FALSE),"") -> 4箱子 | E21: =IFERROR(VLOOKUP($A21,全人物技能说明!$A$1:$O$99,4,FALSE),"") -> 稀有 | F21: =IFERROR(VLOOKUP($A21,全人物技能说明!$A$1:$O$99,7,FALSE),"") -> 0 | G21: =IFERROR(VLOOKUP($A21,全人物技能说明!$A$1:$O$99,8,FALSE),"") -> 魅惑一名敌人，使其眩晕 2 回合，并使其受到的伤害提升 50%。 | H21: 迷惑一个敌人，使其昏迷1圈，并在接下来的3次攻击中增加15%的伤害。 | I21: =IFERROR(VLOOKUP($A21,全人物技能说明!$A$1:$O$99,14,FALSE),"") -> W | J21: =IFERROR(VLOOKUP($A21,全人物技能说明!$A$1:$O$99,15,FALSE),"") -> U | L21: W | M21: =IFERROR(IF(VLOOKUP($A21,全人物技能说明!$A$1:$O$99,7,FALSE)<>"",VLOOKUP($A21,全人物技能说明!$A$1:$O$99,7,FALSE),""),"") | O21: 广播 | P21: =RANK(Y21,Y:Y) -> 8 | Q21: =RANK(Z21,Z:Z) -> 16 | R21: =RANK(AA21,AA:AA) -> 20 | S21: =RANK(AB21,AB:AB) -> 20 | T21: =RANK(AC21,AC:AC) -> 30 | U21: =Y21+Z21+AA21+AB21+AC21 -> 846 | W21: =C21 -> 15 | Y21: =IFERROR(VALUE(LEFT(AE21,FIND("(",AE21)-1))+($W21-1)*VALUE(MID(AE21,FIND("+",AE21)+1,FIND(")",AE21)-FIND("+",AE21)-1)),"") -> 220 | Z21: =IFERROR(VALUE(LEFT(AF21,FIND("(",AF21)-1))+($W21-1)*VALUE(MID(AF21,FIND("+",AF21)+1,FIND(")",AF21)-FIND("+",AF21)-1)),"") -> 166 | AA21: =IFERROR(VALUE(LEFT(AG21,FIND("(",AG21)-1))+($W21-1)*VALUE(MID(AG21,FIND("+",AG21)+1,FIND(")",AG21)-FIND("+",AG21)-1)),"") -> 166 | AB21: =IFERROR(VALUE(LEFT(AH21,FIND("(",AH21)-1))+($W21-1)*VALUE(MID(AH21,FIND("+",AH21)+1,FIND(")",AH21)-FIND("+",AH21)-1)),"") -> 166 | AC21: =IFERROR(VALUE(LEFT(AI21,FIND("(",AI21)-1))+($W21-1)*VALUE(MID(AI21,FIND("+",AI21)+1,FIND(")",AI21)-FIND("+",AI21)-1)),"") -> 128 | AE21: =IFERROR(VLOOKUP($A21,全人物技能说明!$A$1:$O$99,9,FALSE),"") -> 66(+11) | AF21: =IFERROR(VLOOKUP($A21,全人物技能说明!$A$1:$O$99,10,FALSE),"") -> 54(+8) | AG21: =IFERROR(VLOOKUP($A21,全人物技能说明!$A$1:$O$99,11,FALSE),"") -> 54(+8) | AH21: =IFERROR(VLOOKUP($A21,全人物技能说明!$A$1:$O$99,12,FALSE),"") -> 54(+8) | AI21: =IFERROR(VLOOKUP($A21,全人物技能说明!$A$1:$O$99,13,FALSE),"") -> 44(+6) | AL21: C Rank
A22: Rhode | B22: =IFERROR(VLOOKUP($A22,全人物技能说明!$A$1:$O$99,2,FALSE),"") -> 罗德 | C22: 14 | D22: =IFERROR(VLOOKUP($A22,全人物技能说明!$A$1:$O$99,3,FALSE),"") -> 4剧情 | E22: =IFERROR(VLOOKUP($A22,全人物技能说明!$A$1:$O$99,4,FALSE),"") -> 史诗 | F22: =IFERROR(VLOOKUP($A22,全人物技能说明!$A$1:$O$99,7,FALSE),"") -> 0 | G22: =IFERROR(VLOOKUP($A22,全人物技能说明!$A$1:$O$99,8,FALSE),"") -> 发动 5 连击，每次攻击造成 [75% DPS] 伤害。 | H22: 发动2次连续攻击，每次造成 [75% DPS] 伤害。 | I22: =IFERROR(VLOOKUP($A22,全人物技能说明!$A$1:$O$99,14,FALSE),"") -> W, U | J22: =IFERROR(VLOOKUP($A22,全人物技能说明!$A$1:$O$99,15,FALSE),"") -> A, F | K22: W | L22: W | M22: =IFERROR(IF(VLOOKUP($A22,全人物技能说明!$A$1:$O$99,7,FALSE)<>"",VLOOKUP($A22,全人物技能说明!$A$1:$O$99,7,FALSE),""),"") | P22: =RANK(Y22,Y:Y) -> 22 | Q22: =RANK(Z22,Z:Z) -> 31 | R22: =RANK(AA22,AA:AA) -> 27 | S22: =RANK(AB22,AB:AB) -> 33 | T22: =RANK(AC22,AC:AC) -> 18 | U22: =Y22+Z22+AA22+AB22+AC22 -> 701 | W22: =C22 -> 14 | Y22: =IFERROR(VALUE(LEFT(AE22,FIND("(",AE22)-1))+($W22-1)*VALUE(MID(AE22,FIND("+",AE22)+1,FIND(")",AE22)-FIND("+",AE22)-1)),"") -> 158 | Z22: =IFERROR(VALUE(LEFT(AF22,FIND("(",AF22)-1))+($W22-1)*VALUE(MID(AF22,FIND("+",AF22)+1,FIND(")",AF22)-FIND("+",AF22)-1)),"") -> 123 | AA22: =IFERROR(VALUE(LEFT(AG22,FIND("(",AG22)-1))+($W22-1)*VALUE(MID(AG22,FIND("+",AG22)+1,FIND(")",AG22)-FIND("+",AG22)-1)),"") -> 139 | AB22: =IFERROR(VALUE(LEFT(AH22,FIND("(",AH22)-1))+($W22-1)*VALUE(MID(AH22,FIND("+",AH22)+1,FIND(")",AH22)-FIND("+",AH22)-1)),"") -> 123 | AC22: =IFERROR(VALUE(LEFT(AI22,FIND("(",AI22)-1))+($W22-1)*VALUE(MID(AI22,FIND("+",AI22)+1,FIND(")",AI22)-FIND("+",AI22)-1)),"") -> 158 | AE22: =IFERROR(VLOOKUP($A22,全人物技能说明!$A$1:$O$99,9,FALSE),"") -> 54(+8) | AF22: =IFERROR(VLOOKUP($A22,全人物技能说明!$A$1:$O$99,10,FALSE),"") -> 45(+6) | AG22: =IFERROR(VLOOKUP($A22,全人物技能说明!$A$1:$O$99,11,FALSE),"") -> 48(+7) | AH22: =IFERROR(VLOOKUP($A22,全人物技能说明!$A$1:$O$99,12,FALSE),"") -> 45(+6) | AI22: =IFERROR(VLOOKUP($A22,全人物技能说明!$A$1:$O$99,13,FALSE),"") -> 54(+8) | AM22: B Rank
A23: Foxy | B23: =IFERROR(VLOOKUP($A23,全人物技能说明!$A$1:$O$99,2,FALSE),"") -> 福克希 | C23: 14 | D23: =IFERROR(VLOOKUP($A23,全人物技能说明!$A$1:$O$99,3,FALSE),"") -> 4箱子 | E23: =IFERROR(VLOOKUP($A23,全人物技能说明!$A$1:$O$99,4,FALSE),"") -> 稀有 | F23: =IFERROR(VLOOKUP($A23,全人物技能说明!$A$1:$O$99,7,FALSE),"") -> 0 | G23: =IFERROR(VLOOKUP($A23,全人物技能说明!$A$1:$O$99,8,FALSE),"") -> 为最多 2 名血量最低的队友递出饮品，回复 [20% AGI] 生命值，并在 2 回合内提升其 20% 伤害。 | H23: 向2名生命值最低的盟友治疗 [20% AGI] 生命值并提升其20%伤害，持续2回合。 | I23: =IFERROR(VLOOKUP($A23,全人物技能说明!$A$1:$O$99,14,FALSE),"") -> 全能偏A | J23: =IFERROR(VLOOKUP($A23,全人物技能说明!$A$1:$O$99,15,FALSE),"") -> 0 | K23: A | L23: A | M23: =IFERROR(IF(VLOOKUP($A23,全人物技能说明!$A$1:$O$99,7,FALSE)<>"",VLOOKUP($A23,全人物技能说明!$A$1:$O$99,7,FALSE),""),"") | P23: =RANK(Y23,Y:Y) -> 28 | Q23: =RANK(Z23,Z:Z) -> 25 | R23: =RANK(AA23,AA:AA) -> 27 | S23: =RANK(AB23,AB:AB) -> 25 | T23: =RANK(AC23,AC:AC) -> 25 | U23: =Y23+Z23+AA23+AB23+AC23 -> 695 | W23: =C23 -> 14 | Y23: =IFERROR(VALUE(LEFT(AE23,FIND("(",AE23)-1))+($W23-1)*VALUE(MID(AE23,FIND("+",AE23)+1,FIND(")",AE23)-FIND("+",AE23)-1)),"") -> 139 | Z23: =IFERROR(VALUE(LEFT(AF23,FIND("(",AF23)-1))+($W23-1)*VALUE(MID(AF23,FIND("+",AF23)+1,FIND(")",AF23)-FIND("+",AF23)-1)),"") -> 139 | AA23: =IFERROR(VALUE(LEFT(AG23,FIND("(",AG23)-1))+($W23-1)*VALUE(MID(AG23,FIND("+",AG23)+1,FIND(")",AG23)-FIND("+",AG23)-1)),"") -> 139 | AB23: =IFERROR(VALUE(LEFT(AH23,FIND("(",AH23)-1))+($W23-1)*VALUE(MID(AH23,FIND("+",AH23)+1,FIND(")",AH23)-FIND("+",AH23)-1)),"") -> 139 | AC23: =IFERROR(VALUE(LEFT(AI23,FIND("(",AI23)-1))+($W23-1)*VALUE(MID(AI23,FIND("+",AI23)+1,FIND(")",AI23)-FIND("+",AI23)-1)),"") -> 139 | AE23: =IFERROR(VLOOKUP($A23,全人物技能说明!$A$1:$O$99,9,FALSE),"") -> 48(+7) | AF23: =IFERROR(VLOOKUP($A23,全人物技能说明!$A$1:$O$99,10,FALSE),"") -> 48(+7) | AG23: =IFERROR(VLOOKUP($A23,全人物技能说明!$A$1:$O$99,11,FALSE),"") -> 48(+7) | AH23: =IFERROR(VLOOKUP($A23,全人物技能说明!$A$1:$O$99,12,FALSE),"") -> 48(+7) | AI23: =IFERROR(VLOOKUP($A23,全人物技能说明!$A$1:$O$99,13,FALSE),"") -> 48(+7) | AN23: A Rank
A24: PamTwo | B24: =IFERROR(VLOOKUP($A24,全人物技能说明!$A$1:$O$99,2,FALSE),"") -> 帕姆2 | C24: 14 | D24: =IFERROR(VLOOKUP($A24,全人物技能说明!$A$1:$O$99,3,FALSE),"") -> 6剧情 | E24: =IFERROR(VLOOKUP($A24,全人物技能说明!$A$1:$O$99,4,FALSE),"") -> 史诗 | F24: =IFERROR(VLOOKUP($A24,全人物技能说明!$A$1:$O$99,7,FALSE),"") -> 近战X2武士刀，4次 | G24: =IFERROR(VLOOKUP($A24,全人物技能说明!$A$1:$O$99,8,FALSE),"") -> 发动 2 连击，每次攻击造成 [150% DPS] 伤害。 | H24: 发起一系列3次攻击，每次处理9损坏，忽略所有防御。 | I24: =IFERROR(VLOOKUP($A24,全人物技能说明!$A$1:$O$99,14,FALSE),"") -> 全能I | J24: =IFERROR(VLOOKUP($A24,全人物技能说明!$A$1:$O$99,15,FALSE),"") -> 0 | K24: I | L24: I | M24: =IFERROR(IF(VLOOKUP($A24,全人物技能说明!$A$1:$O$99,7,FALSE)<>"",VLOOKUP($A24,全人物技能说明!$A$1:$O$99,7,FALSE),""),"") -> 近战X2武士刀，4次 | P24: =RANK(Y24,Y:Y) -> 28 | Q24: =RANK(Z24,Z:Z) -> 25 | R24: =RANK(AA24,AA:AA) -> 27 | S24: =RANK(AB24,AB:AB) -> 25 | T24: =RANK(AC24,AC:AC) -> 25 | U24: =Y24+Z24+AA24+AB24+AC24 -> 695 | W24: =C24 -> 14 | Y24: =IFERROR(VALUE(LEFT(AE24,FIND("(",AE24)-1))+($W24-1)*VALUE(MID(AE24,FIND("+",AE24)+1,FIND(")",AE24)-FIND("+",AE24)-1)),"") -> 139 | Z24: =IFERROR(VALUE(LEFT(AF24,FIND("(",AF24)-1))+($W24-1)*VALUE(MID(AF24,FIND("+",AF24)+1,FIND(")",AF24)-FIND("+",AF24)-1)),"") -> 139 | AA24: =IFERROR(VALUE(LEFT(AG24,FIND("(",AG24)-1))+($W24-1)*VALUE(MID(AG24,FIND("+",AG24)+1,FIND(")",AG24)-FIND("+",AG24)-1)),"") -> 139 | AB24: =IFERROR(VALUE(LEFT(AH24,FIND("(",AH24)-1))+($W24-1)*VALUE(MID(AH24,FIND("+",AH24)+1,FIND(")",AH24)-FIND("+",AH24)-1)),"") -> 139 | AC24: =IFERROR(VALUE(LEFT(AI24,FIND("(",AI24)-1))+($W24-1)*VALUE(MID(AI24,FIND("+",AI24)+1,FIND(")",AI24)-FIND("+",AI24)-1)),"") -> 139 | AE24: =IFERROR(VLOOKUP($A24,全人物技能说明!$A$1:$O$99,9,FALSE),"") -> 48(+7) | AF24: =IFERROR(VLOOKUP($A24,全人物技能说明!$A$1:$O$99,10,FALSE),"") -> 48(+7) | AG24: =IFERROR(VLOOKUP($A24,全人物技能说明!$A$1:$O$99,11,FALSE),"") -> 48(+7) | AH24: =IFERROR(VLOOKUP($A24,全人物技能说明!$A$1:$O$99,12,FALSE),"") -> 48(+7) | AI24: =IFERROR(VLOOKUP($A24,全人物技能说明!$A$1:$O$99,13,FALSE),"") -> 48(+7) | AO24: S Rank | AP24: Formula | AQ24: Raw Formula
A25: CLOE | B25: =IFERROR(VLOOKUP($A25,全人物技能说明!$A$1:$O$99,2,FALSE),"") -> 克洛伊 | C25: 13 | D25: =IFERROR(VLOOKUP($A25,全人物技能说明!$A$1:$O$99,3,FALSE),"") -> 1箱子 | E25: =IFERROR(VLOOKUP($A25,全人物技能说明!$A$1:$O$99,4,FALSE),"") -> 史诗 | F25: =IFERROR(VLOOKUP($A25,全人物技能说明!$A$1:$O$99,7,FALSE),"") -> 0 | G25: =IFERROR(VLOOKUP($A25,全人物技能说明!$A$1:$O$99,8,FALSE),"") -> 向 2 名敌人投掷炸药，造成 [75% DPS] 伤害。 | H25: 向3名敌人投掷炸药，对其造成 [75% DPS] 伤害。 | I25: =IFERROR(VLOOKUP($A25,全人物技能说明!$A$1:$O$99,14,FALSE),"") -> I | J25: =IFERROR(VLOOKUP($A25,全人物技能说明!$A$1:$O$99,15,FALSE),"") -> W | K25: I | L25: I | M25: =IFERROR(IF(VLOOKUP($A25,全人物技能说明!$A$1:$O$99,7,FALSE)<>"",VLOOKUP($A25,全人物技能说明!$A$1:$O$99,7,FALSE),""),"") | O25: 金库 | P25: =RANK(Y25,Y:Y) -> 36 | Q25: =RANK(Z25,Z:Z) -> 20 | R25: =RANK(AA25,AA:AA) -> 10 | S25: =RANK(AB25,AB:AB) -> 22 | T25: =RANK(AC25,AC:AC) -> 19 | U25: =Y25+Z25+AA25+AB25+AC25 -> 764 | W25: =C25 -> 13 | Y25: =IFERROR(VALUE(LEFT(AE25,FIND("(",AE25)-1))+($W25-1)*VALUE(MID(AE25,FIND("+",AE25)+1,FIND(")",AE25)-FIND("+",AE25)-1)),"") -> 116 | Z25: =IFERROR(VALUE(LEFT(AF25,FIND("(",AF25)-1))+($W25-1)*VALUE(MID(AF25,FIND("+",AF25)+1,FIND(")",AF25)-FIND("+",AF25)-1)),"") -> 150 | AA25: =IFERROR(VALUE(LEFT(AG25,FIND("(",AG25)-1))+($W25-1)*VALUE(MID(AG25,FIND("+",AG25)+1,FIND(")",AG25)-FIND("+",AG25)-1)),"") -> 198 | AB25: =IFERROR(VALUE(LEFT(AH25,FIND("(",AH25)-1))+($W25-1)*VALUE(MID(AH25,FIND("+",AH25)+1,FIND(")",AH25)-FIND("+",AH25)-1)),"") -> 150 | AC25: =IFERROR(VALUE(LEFT(AI25,FIND("(",AI25)-1))+($W25-1)*VALUE(MID(AI25,FIND("+",AI25)+1,FIND(")",AI25)-FIND("+",AI25)-1)),"") -> 150 | AE25: =IFERROR(VLOOKUP($A25,全人物技能说明!$A$1:$O$99,9,FALSE),"") -> 44(+6) | AF25: =IFERROR(VLOOKUP($A25,全人物技能说明!$A$1:$O$99,10,FALSE),"") -> 54(+8) | AG25: =IFERROR(VLOOKUP($A25,全人物技能说明!$A$1:$O$99,11,FALSE),"") -> 66(+11) | AH25: =IFERROR(VLOOKUP($A25,全人物技能说明!$A$1:$O$99,12,FALSE),"") -> 54(+8) | AI25: =IFERROR(VLOOKUP($A25,全人物技能说明!$A$1:$O$99,13,FALSE),"") -> 54(+8) | AL25: 32 (+4) | AP25: =32+((Champion_Level-1)*4) -> #NAME? | AQ25: 32+((Champion_Level-1)*4)
A26: Gaia | B26: =IFERROR(VLOOKUP($A26,全人物技能说明!$A$1:$O$99,2,FALSE),"") -> 盖亚 | C26: 13 | D26: =IFERROR(VLOOKUP($A26,全人物技能说明!$A$1:$O$99,3,FALSE),"") -> 4箱子 | E26: =IFERROR(VLOOKUP($A26,全人物技能说明!$A$1:$O$99,4,FALSE),"") -> 传说 | F26: =IFERROR(VLOOKUP($A26,全人物技能说明!$A$1:$O$99,7,FALSE),"") -> 0 | G26: =IFERROR(VLOOKUP($A26,全人物技能说明!$A$1:$O$99,8,FALSE),"") -> 立即攻击最虚弱的敌人，造成 [175% DPS] 伤害。 | I26: =IFERROR(VLOOKUP($A26,全人物技能说明!$A$1:$O$99,14,FALSE),"") -> A, F | J26: =IFERROR(VLOOKUP($A26,全人物技能说明!$A$1:$O$99,15,FALSE),"") -> W, I | K26: A | L26: A | M26: =IFERROR(IF(VLOOKUP($A26,全人物技能说明!$A$1:$O$99,7,FALSE)<>"",VLOOKUP($A26,全人物技能说明!$A$1:$O$99,7,FALSE),""),"") | P26: =RANK(Y26,Y:Y) -> 35 | Q26: =RANK(Z26,Z:Z) -> 20 | R26: =RANK(AA26,AA:AA) -> 35 | S26: =RANK(AB26,AB:AB) -> 22 | T26: =RANK(AC26,AC:AC) -> 27 | U26: =Y26+Z26+AA26+AB26+AC26 -> 666 | W26: =C26 -> 13 | Y26: =IFERROR(VALUE(LEFT(AE26,FIND("(",AE26)-1))+($W26-1)*VALUE(MID(AE26,FIND("+",AE26)+1,FIND(")",AE26)-FIND("+",AE26)-1)),"") -> 117 | Z26: =IFERROR(VALUE(LEFT(AF26,FIND("(",AF26)-1))+($W26-1)*VALUE(MID(AF26,FIND("+",AF26)+1,FIND(")",AF26)-FIND("+",AF26)-1)),"") -> 150 | AA26: =IFERROR(VALUE(LEFT(AG26,FIND("(",AG26)-1))+($W26-1)*VALUE(MID(AG26,FIND("+",AG26)+1,FIND(")",AG26)-FIND("+",AG26)-1)),"") -> 117 | AB26: =IFERROR(VALUE(LEFT(AH26,FIND("(",AH26)-1))+($W26-1)*VALUE(MID(AH26,FIND("+",AH26)+1,FIND(")",AH26)-FIND("+",AH26)-1)),"") -> 150 | AC26: =IFERROR(VALUE(LEFT(AI26,FIND("(",AI26)-1))+($W26-1)*VALUE(MID(AI26,FIND("+",AI26)+1,FIND(")",AI26)-FIND("+",AI26)-1)),"") -> 132 | AE26: =IFERROR(VLOOKUP($A26,全人物技能说明!$A$1:$O$99,9,FALSE),"") -> 45(+6) | AF26: =IFERROR(VLOOKUP($A26,全人物技能说明!$A$1:$O$99,10,FALSE),"") -> 54(+8) | AG26: =IFERROR(VLOOKUP($A26,全人物技能说明!$A$1:$O$99,11,FALSE),"") -> 45(+6) | AH26: =IFERROR(VLOOKUP($A26,全人物技能说明!$A$1:$O$99,12,FALSE),"") -> 54(+8) | AI26: =IFERROR(VLOOKUP($A26,全人物技能说明!$A$1:$O$99,13,FALSE),"") -> 48(+7) | AL26: 38 (+5) | AM26: 38 (+5) | AP26: =38+((Champion_Level-1)*5) -> #NAME? | AQ26: 38+((Champion_Level-1)*5)
A27: Amelia | B27: =IFERROR(VLOOKUP($A27,全人物技能说明!$A$1:$O$99,2,FALSE),"") -> 阿米莉亚 | C27: 13 | D27: =IFERROR(VLOOKUP($A27,全人物技能说明!$A$1:$O$99,3,FALSE),"") -> 5剧情 | E27: =IFERROR(VLOOKUP($A27,全人物技能说明!$A$1:$O$99,4,FALSE),"") -> 史诗 | F27: =IFERROR(VLOOKUP($A27,全人物技能说明!$A$1:$O$99,7,FALSE),"") -> 0 | G27: =IFERROR(VLOOKUP($A27,全人物技能说明!$A$1:$O$99,8,FALSE),"") -> 创造一个诱饵分身（继承 [50% HP] 和 [100% DPS] 的防御），嘲讽敌人最多 2 秒。 | H27: 用[50% HP] 和 [100% DPS]创造一个分身诱饵，嘲讽敌人最4人,持续最多4回合。 | I27: =IFERROR(VLOOKUP($A27,全人物技能说明!$A$1:$O$99,14,FALSE),"") -> A, I | J27: =IFERROR(VLOOKUP($A27,全人物技能说明!$A$1:$O$99,15,FALSE),"") -> W | K27: I | L27: I | M27: =IFERROR(IF(VLOOKUP($A27,全人物技能说明!$A$1:$O$99,7,FALSE)<>"",VLOOKUP($A27,全人物技能说明!$A$1:$O$99,7,FALSE),""),"") | P27: =RANK(Y27,Y:Y) -> 38 | Q27: =RANK(Z27,Z:Z) -> 20 | R27: =RANK(AA27,AA:AA) -> 23 | S27: =RANK(AB27,AB:AB) -> 28 | T27: =RANK(AC27,AC:AC) -> 27 | U27: =Y27+Z27+AA27+AB27+AC27 -> 662 | W27: =C27 -> 13 | Y27: =IFERROR(VALUE(LEFT(AE27,FIND("(",AE27)-1))+($W27-1)*VALUE(MID(AE27,FIND("+",AE27)+1,FIND(")",AE27)-FIND("+",AE27)-1)),"") -> 98 | Z27: =IFERROR(VALUE(LEFT(AF27,FIND("(",AF27)-1))+($W27-1)*VALUE(MID(AF27,FIND("+",AF27)+1,FIND(")",AF27)-FIND("+",AF27)-1)),"") -> 150 | AA27: =IFERROR(VALUE(LEFT(AG27,FIND("(",AG27)-1))+($W27-1)*VALUE(MID(AG27,FIND("+",AG27)+1,FIND(")",AG27)-FIND("+",AG27)-1)),"") -> 150 | AB27: =IFERROR(VALUE(LEFT(AH27,FIND("(",AH27)-1))+($W27-1)*VALUE(MID(AH27,FIND("+",AH27)+1,FIND(")",AH27)-FIND("+",AH27)-1)),"") -> 132 | AC27: =IFERROR(VALUE(LEFT(AI27,FIND("(",AI27)-1))+($W27-1)*VALUE(MID(AI27,FIND("+",AI27)+1,FIND(")",AI27)-FIND("+",AI27)-1)),"") -> 132 | AE27: =IFERROR(VLOOKUP($A27,全人物技能说明!$A$1:$O$99,9,FALSE),"") -> 38(+5) | AF27: =IFERROR(VLOOKUP($A27,全人物技能说明!$A$1:$O$99,10,FALSE),"") -> 54(+8) | AG27: =IFERROR(VLOOKUP($A27,全人物技能说明!$A$1:$O$99,11,FALSE),"") -> 54(+8) | AH27: =IFERROR(VLOOKUP($A27,全人物技能说明!$A$1:$O$99,12,FALSE),"") -> 48(+7) | AI27: =IFERROR(VLOOKUP($A27,全人物技能说明!$A$1:$O$99,13,FALSE),"") -> 48(+7) | AN27: 40 (+6) | AP27: =40+((Champion_Level-1)*6) -> #NAME? | AQ27: 40+((Champion_Level-1)*6)
A28: PamOne | B28: =IFERROR(VLOOKUP($A28,全人物技能说明!$A$1:$O$99,2,FALSE),"") -> 帕姆1 | C28: 13 | D28: =IFERROR(VLOOKUP($A28,全人物技能说明!$A$1:$O$99,3,FALSE),"") -> 6剧情 | E28: =IFERROR(VLOOKUP($A28,全人物技能说明!$A$1:$O$99,4,FALSE),"") -> 史诗 | F28: =IFERROR(VLOOKUP($A28,全人物技能说明!$A$1:$O$99,7,FALSE),"") -> 近战X2武士刀，4次 | G28: =IFERROR(VLOOKUP($A28,全人物技能说明!$A$1:$O$99,8,FALSE),"") -> 发动 4 连击，每次攻击造成 [75% DPS] 伤害。 | H28: 发起一系列3次攻击，每次处理9损坏，忽略所有防御。 | I28: =IFERROR(VLOOKUP($A28,全人物技能说明!$A$1:$O$99,14,FALSE),"") -> 全能W | J28: =IFERROR(VLOOKUP($A28,全人物技能说明!$A$1:$O$99,15,FALSE),"") -> 0 | K28: W | L28: W | M28: =IFERROR(IF(VLOOKUP($A28,全人物技能说明!$A$1:$O$99,7,FALSE)<>"",VLOOKUP($A28,全人物技能说明!$A$1:$O$99,7,FALSE),""),"") -> 近战X2武士刀，4次 | P28: =RANK(Y28,Y:Y) -> 30 | Q28: =RANK(Z28,Z:Z) -> 27 | R28: =RANK(AA28,AA:AA) -> 30 | S28: =RANK(AB28,AB:AB) -> 28 | T28: =RANK(AC28,AC:AC) -> 27 | U28: =Y28+Z28+AA28+AB28+AC28 -> 660 | W28: =C28 -> 13 | Y28: =IFERROR(VALUE(LEFT(AE28,FIND("(",AE28)-1))+($W28-1)*VALUE(MID(AE28,FIND("+",AE28)+1,FIND(")",AE28)-FIND("+",AE28)-1)),"") -> 132 | Z28: =IFERROR(VALUE(LEFT(AF28,FIND("(",AF28)-1))+($W28-1)*VALUE(MID(AF28,FIND("+",AF28)+1,FIND(")",AF28)-FIND("+",AF28)-1)),"") -> 132 | AA28: =IFERROR(VALUE(LEFT(AG28,FIND("(",AG28)-1))+($W28-1)*VALUE(MID(AG28,FIND("+",AG28)+1,FIND(")",AG28)-FIND("+",AG28)-1)),"") -> 132 | AB28: =IFERROR(VALUE(LEFT(AH28,FIND("(",AH28)-1))+($W28-1)*VALUE(MID(AH28,FIND("+",AH28)+1,FIND(")",AH28)-FIND("+",AH28)-1)),"") -> 132 | AC28: =IFERROR(VALUE(LEFT(AI28,FIND("(",AI28)-1))+($W28-1)*VALUE(MID(AI28,FIND("+",AI28)+1,FIND(")",AI28)-FIND("+",AI28)-1)),"") -> 132 | AE28: =IFERROR(VLOOKUP($A28,全人物技能说明!$A$1:$O$99,9,FALSE),"") -> 48(+7) | AF28: =IFERROR(VLOOKUP($A28,全人物技能说明!$A$1:$O$99,10,FALSE),"") -> 48(+7) | AG28: =IFERROR(VLOOKUP($A28,全人物技能说明!$A$1:$O$99,11,FALSE),"") -> 48(+7) | AH28: =IFERROR(VLOOKUP($A28,全人物技能说明!$A$1:$O$99,12,FALSE),"") -> 48(+7) | AI28: =IFERROR(VLOOKUP($A28,全人物技能说明!$A$1:$O$99,13,FALSE),"") -> 48(+7) | AL28: 42 (+6) | AP28: =42+((Champion_Level-1)*6) -> #NAME? | AQ28: 42+((Champion_Level-1)*6)
A29: Liza | B29: =IFERROR(VLOOKUP($A29,全人物技能说明!$A$1:$O$99,2,FALSE),"") -> 丽莎 | C29: 13 | D29: =IFERROR(VLOOKUP($A29,全人物技能说明!$A$1:$O$99,3,FALSE),"") -> 7箱子 | E29: =IFERROR(VLOOKUP($A29,全人物技能说明!$A$1:$O$99,4,FALSE),"") -> 稀有 | F29: =IFERROR(VLOOKUP($A29,全人物技能说明!$A$1:$O$99,7,FALSE),"") -> 近战X2武士刀，4次 | G29: =IFERROR(VLOOKUP($A29,全人物技能说明!$A$1:$O$99,8,FALSE),"") -> 发动 4 连击，每次攻击造成 [90% DPS] 伤害。 | I29: =IFERROR(VLOOKUP($A29,全人物技能说明!$A$1:$O$99,14,FALSE),"") -> W | J29: =IFERROR(VLOOKUP($A29,全人物技能说明!$A$1:$O$99,15,FALSE),"") -> A, F | K29: A | L29: A | M29: =IFERROR(IF(VLOOKUP($A29,全人物技能说明!$A$1:$O$99,7,FALSE)<>"",VLOOKUP($A29,全人物技能说明!$A$1:$O$99,7,FALSE),""),"") -> 近战X2武士刀，4次 | P29: =RANK(Y29,Y:Y) -> 30 | Q29: =RANK(Z29,Z:Z) -> 32 | R29: =RANK(AA29,AA:AA) -> 31 | S29: =RANK(AB29,AB:AB) -> 27 | T29: =RANK(AC29,AC:AC) -> 36 | U29: =Y29+Z29+AA29+AB29+AC29 -> 628 | W29: =C29 -> 13 | Y29: =IFERROR(VALUE(LEFT(AE29,FIND("(",AE29)-1))+($W29-1)*VALUE(MID(AE29,FIND("+",AE29)+1,FIND(")",AE29)-FIND("+",AE29)-1)),"") -> 132 | Z29: =IFERROR(VALUE(LEFT(AF29,FIND("(",AF29)-1))+($W29-1)*VALUE(MID(AF29,FIND("+",AF29)+1,FIND(")",AF29)-FIND("+",AF29)-1)),"") -> 122 | AA29: =IFERROR(VALUE(LEFT(AG29,FIND("(",AG29)-1))+($W29-1)*VALUE(MID(AG29,FIND("+",AG29)+1,FIND(")",AG29)-FIND("+",AG29)-1)),"") -> 126 | AB29: =IFERROR(VALUE(LEFT(AH29,FIND("(",AH29)-1))+($W29-1)*VALUE(MID(AH29,FIND("+",AH29)+1,FIND(")",AH29)-FIND("+",AH29)-1)),"") -> 134 | AC29: =IFERROR(VALUE(LEFT(AI29,FIND("(",AI29)-1))+($W29-1)*VALUE(MID(AI29,FIND("+",AI29)+1,FIND(")",AI29)-FIND("+",AI29)-1)),"") -> 114 | AE29: =IFERROR(VLOOKUP($A29,全人物技能说明!$A$1:$O$99,9,FALSE),"") -> 48(+7) | AF29: =IFERROR(VLOOKUP($A29,全人物技能说明!$A$1:$O$99,10,FALSE),"") -> 38(+7) | AG29: =IFERROR(VLOOKUP($A29,全人物技能说明!$A$1:$O$99,11,FALSE),"") -> 42(+7) | AH29: =IFERROR(VLOOKUP($A29,全人物技能说明!$A$1:$O$99,12,FALSE),"") -> 38(+8) | AI29: =IFERROR(VLOOKUP($A29,全人物技能说明!$A$1:$O$99,13,FALSE),"") -> 42(+6) | AM29: 45 (+6) | AP29: =45+((Champion_Level-1)*6) -> #NAME? | AQ29: 45+((Champion_Level-1)*6)
A30: Beatrix | B30: =IFERROR(VLOOKUP($A30,全人物技能说明!$A$1:$O$99,2,FALSE),"") -> 碧翠丝 | C30: 12 | D30: =IFERROR(VLOOKUP($A30,全人物技能说明!$A$1:$O$99,3,FALSE),"") -> 4剧情 | E30: =IFERROR(VLOOKUP($A30,全人物技能说明!$A$1:$O$99,4,FALSE),"") -> 传说 | F30: =IFERROR(VLOOKUP($A30,全人物技能说明!$A$1:$O$99,7,FALSE),"") -> 0 | G30: =IFERROR(VLOOKUP($A30,全人物技能说明!$A$1:$O$99,8,FALSE),"") -> 展露自我，嘲讽敌人 3 回合，减少 50% 所受到的伤害。 | H30: 暴露自己，嘲讽2个敌人4回合，使下一次攻击造成的伤害减少40%。 | I30: =IFERROR(VLOOKUP($A30,全人物技能说明!$A$1:$O$99,14,FALSE),"") -> U | J30: A | L30: A | M30: =IFERROR(IF(VLOOKUP($A30,全人物技能说明!$A$1:$O$99,7,FALSE)<>"",VLOOKUP($A30,全人物技能说明!$A$1:$O$99,7,FALSE),""),"") | P30: =RANK(Y30,Y:Y) -> 32 | Q30: =RANK(Z30,Z:Z) -> 37 | R30: =RANK(AA30,AA:AA) -> 25 | S30: =RANK(AB30,AB:AB) -> 21 | T30: =RANK(AC30,AC:AC) -> 14 | U30: =Y30+Z30+AA30+AB30+AC30 -> 719 | W30: =C30 -> 12 | X30: 1 | Y30: =IFERROR(VALUE(LEFT(AE30,FIND("(",AE30)-1))+($W30-1)*VALUE(MID(AE30,FIND("+",AE30)+1,FIND(")",AE30)-FIND("+",AE30)-1)),"") -> 125 | Z30: =IFERROR(VALUE(LEFT(AF30,FIND("(",AF30)-1))+($W30-1)*VALUE(MID(AF30,FIND("+",AF30)+1,FIND(")",AF30)-FIND("+",AF30)-1)),"") -> 106 | AA30: =IFERROR(VALUE(LEFT(AG30,FIND("(",AG30)-1))+($W30-1)*VALUE(MID(AG30,FIND("+",AG30)+1,FIND(")",AG30)-FIND("+",AG30)-1)),"") -> 142 | AB30: =IFERROR(VALUE(LEFT(AH30,FIND("(",AH30)-1))+($W30-1)*VALUE(MID(AH30,FIND("+",AH30)+1,FIND(")",AH30)-FIND("+",AH30)-1)),"") -> 159 | AC30: =IFERROR(VALUE(LEFT(AI30,FIND("(",AI30)-1))+($W30-1)*VALUE(MID(AI30,FIND("+",AI30)+1,FIND(")",AI30)-FIND("+",AI30)-1)),"") -> 187 | AE30: =IFERROR(VLOOKUP($A30,全人物技能说明!$A$1:$O$99,9,FALSE),"") -> 48(+7) | AF30: =IFERROR(VLOOKUP($A30,全人物技能说明!$A$1:$O$99,10,FALSE),"") -> 40(+6) | AG30: =IFERROR(VLOOKUP($A30,全人物技能说明!$A$1:$O$99,11,FALSE),"") -> 54(+8) | AH30: =IFERROR(VLOOKUP($A30,全人物技能说明!$A$1:$O$99,12,FALSE),"") -> 60(+9) | AI30: =IFERROR(VLOOKUP($A30,全人物技能说明!$A$1:$O$99,13,FALSE),"") -> 66(+11) | AL30: 48 (+7) | AM30: 48 (+7) | AN30: 48 (+7) | AP30: =48+((Champion_Level-1)*7) -> #NAME? | AQ30: 48+((Champion_Level-1)*7)
A31: Diana | B31: =IFERROR(VLOOKUP($A31,全人物技能说明!$A$1:$O$99,2,FALSE),"") -> 黛安娜 | C31: 9 | D31: =IFERROR(VLOOKUP($A31,全人物技能说明!$A$1:$O$99,3,FALSE),"") -> 7箱子 | E31: =IFERROR(VLOOKUP($A31,全人物技能说明!$A$1:$O$99,4,FALSE),"") -> 稀有 | F31: =IFERROR(VLOOKUP($A31,全人物技能说明!$A$1:$O$99,7,FALSE),"") -> 鱼叉枪（W 和 F 属性第二高，U 属性中等，但在 W 属性链中这是最好的防御选择） | G31: =IFERROR(VLOOKUP($A31,全人物技能说明!$A$1:$O$99,8,FALSE),"") -> 恢复活力，回复自身 [25% HP] 并在 2 回合内获得 [125% DEF] 防御加成。 | I31: =IFERROR(VLOOKUP($A31,全人物技能说明!$A$1:$O$99,14,FALSE),"") -> W | J31: =IFERROR(VLOOKUP($A31,全人物技能说明!$A$1:$O$99,15,FALSE),"") -> A, I | K31: I | L31: I | M31: =IFERROR(IF(VLOOKUP($A31,全人物技能说明!$A$1:$O$99,7,FALSE)<>"",VLOOKUP($A31,全人物技能说明!$A$1:$O$99,7,FALSE),""),"") -> 鱼叉枪（W 和 F 属性第二高，U 属性中等，但在 W 属性链中这是最好的防御选择） | P31: =RANK(Y31,Y:Y) -> 24 | Q31: =RANK(Z31,Z:Z) -> 38 | R31: =RANK(AA31,AA:AA) -> 37 | S31: =RANK(AB31,AB:AB) -> 36 | T31: =RANK(AC31,AC:AC) -> 34 | U31: =Y31+Z31+AA31+AB31+AC31 -> 598 | W31: =C31 -> 9 | Y31: =IFERROR(VALUE(LEFT(AE31,FIND("(",AE31)-1))+($W31-1)*VALUE(MID(AE31,FIND("+",AE31)+1,FIND(")",AE31)-FIND("+",AE31)-1)),"") -> 154 | Z31: =IFERROR(VALUE(LEFT(AF31,FIND("(",AF31)-1))+($W31-1)*VALUE(MID(AF31,FIND("+",AF31)+1,FIND(")",AF31)-FIND("+",AF31)-1)),"") -> 104 | AA31: =IFERROR(VALUE(LEFT(AG31,FIND("(",AG31)-1))+($W31-1)*VALUE(MID(AG31,FIND("+",AG31)+1,FIND(")",AG31)-FIND("+",AG31)-1)),"") -> 104 | AB31: =IFERROR(VALUE(LEFT(AH31,FIND("(",AH31)-1))+($W31-1)*VALUE(MID(AH31,FIND("+",AH31)+1,FIND(")",AH31)-FIND("+",AH31)-1)),"") -> 118 | AC31: =IFERROR(VALUE(LEFT(AI31,FIND("(",AI31)-1))+($W31-1)*VALUE(MID(AI31,FIND("+",AI31)+1,FIND(")",AI31)-FIND("+",AI31)-1)),"") -> 118 | AE31: =IFERROR(VLOOKUP($A31,全人物技能说明!$A$1:$O$99,9,FALSE),"") -> 66(+11) | AF31: =IFERROR(VLOOKUP($A31,全人物技能说明!$A$1:$O$99,10,FALSE),"") -> 48(+7) | AG31: =IFERROR(VLOOKUP($A31,全人物技能说明!$A$1:$O$99,11,FALSE),"") -> 48(+7) | AH31: =IFERROR(VLOOKUP($A31,全人物技能说明!$A$1:$O$99,12,FALSE),"") -> 54(+8) | AI31: =IFERROR(VLOOKUP($A31,全人物技能说明!$A$1:$O$99,13,FALSE),"") -> 54(+8) | AN31: 60 (+9) | AO31: 60 (+9) | AP31: =60+((Champion_Level-1)*9) -> #NAME? | AQ31: 60+((Champion_Level-1)*9)
A32: Irma | B32: =IFERROR(VLOOKUP($A32,全人物技能说明!$A$1:$O$99,2,FALSE),"") -> 厄玛 | C32: 5 | D32: =IFERROR(VLOOKUP($A32,全人物技能说明!$A$1:$O$99,3,FALSE),"") -> 1箱子 | E32: =IFERROR(VLOOKUP($A32,全人物技能说明!$A$1:$O$99,4,FALSE),"") -> 传说 | F32: =IFERROR(VLOOKUP($A32,全人物技能说明!$A$1:$O$99,7,FALSE),"") -> UA为核心。X2武士刀，4次。X4匕首8次 | G32: =IFERROR(VLOOKUP($A32,全人物技能说明!$A$1:$O$99,8,FALSE),"") -> 在 3 名敌人脚下投掷捕兽夹，对每人造成 [100% DPS] 伤害。 | H32: 向 4 名敌人脚下投掷捕熊陷阱，对每名敌人造成 [50% DPS] 伤害。 | I32: =IFERROR(VLOOKUP($A32,全人物技能说明!$A$1:$O$99,14,FALSE),"") -> 全能A | J32: =IFERROR(VLOOKUP($A32,全人物技能说明!$A$1:$O$99,15,FALSE),"") -> F | K32: A | L32: A | M32: =IFERROR(IF(VLOOKUP($A32,全人物技能说明!$A$1:$O$99,7,FALSE)<>"",VLOOKUP($A32,全人物技能说明!$A$1:$O$99,7,FALSE),""),"") -> UA为核心。X2武士刀，4次。X4匕首8次 | P32: =RANK(Y32,Y:Y) -> 37 | Q32: =RANK(Z32,Z:Z) -> 36 | R32: =RANK(AA32,AA:AA) -> 36 | S32: =RANK(AB32,AB:AB) -> 38 | T32: =RANK(AC32,AC:AC) -> 37 | U32: =Y32+Z32+AA32+AB32+AC32 -> 536 | W32: =C32 -> 5 | Y32: =IFERROR(VALUE(LEFT(AE32,FIND("(",AE32)-1))+($W32-1)*VALUE(MID(AE32,FIND("+",AE32)+1,FIND(")",AE32)-FIND("+",AE32)-1)),"") -> 110 | Z32: =IFERROR(VALUE(LEFT(AF32,FIND("(",AF32)-1))+($W32-1)*VALUE(MID(AF32,FIND("+",AF32)+1,FIND(")",AF32)-FIND("+",AF32)-1)),"") -> 110 | AA32: =IFERROR(VALUE(LEFT(AG32,FIND("(",AG32)-1))+($W32-1)*VALUE(MID(AG32,FIND("+",AG32)+1,FIND(")",AG32)-FIND("+",AG32)-1)),"") -> 110 | AB32: =IFERROR(VALUE(LEFT(AH32,FIND("(",AH32)-1))+($W32-1)*VALUE(MID(AH32,FIND("+",AH32)+1,FIND(")",AH32)-FIND("+",AH32)-1)),"") -> 96 | AC32: =IFERROR(VALUE(LEFT(AI32,FIND("(",AI32)-1))+($W32-1)*VALUE(MID(AI32,FIND("+",AI32)+1,FIND(")",AI32)-FIND("+",AI32)-1)),"") -> 110 | AE32: =IFERROR(VLOOKUP($A32,全人物技能说明!$A$1:$O$99,9,FALSE),"") -> 66(+11) | AF32: =IFERROR(VLOOKUP($A32,全人物技能说明!$A$1:$O$99,10,FALSE),"") -> 66(+11) | AG32: =IFERROR(VLOOKUP($A32,全人物技能说明!$A$1:$O$99,11,FALSE),"") -> 66(+11) | AH32: =IFERROR(VLOOKUP($A32,全人物技能说明!$A$1:$O$99,12,FALSE),"") -> 60(+9) | AI32: =IFERROR(VLOOKUP($A32,全人物技能说明!$A$1:$O$99,13,FALSE),"") -> 66(+11) | AO32: 72 (+14) | AP32: =72+((Champion_Level-1)*14) -> #NAME? | AQ32: 72+((Champion_Level-1)*14)
A33: Devi | B33: =IFERROR(VLOOKUP($A33,全人物技能说明!$A$1:$O$99,2,FALSE),"") -> 黛维 | C33: 5 | D33: =IFERROR(VLOOKUP($A33,全人物技能说明!$A$1:$O$99,3,FALSE),"") -> 8剧情 | E33: =IFERROR(VLOOKUP($A33,全人物技能说明!$A$1:$O$99,4,FALSE),"") -> 史诗 | F33: =IFERROR(VLOOKUP($A33,全人物技能说明!$A$1:$O$99,7,FALSE),"") -> 攻速倒数第二 | G33: =IFERROR(VLOOKUP($A33,全人物技能说明!$A$1:$O$99,8,FALSE),"") -> 攻击当前目标，造成 [350% DMG] 伤害。 | H33: 攻击当前目标，造成 [350% DMG] 伤害。 | I33: =IFERROR(VLOOKUP($A33,全人物技能说明!$A$1:$O$99,14,FALSE),"") -> W, I, U | J33: =IFERROR(VLOOKUP($A33,全人物技能说明!$A$1:$O$99,15,FALSE),"") -> A | K33: W | L33: W | M33: =IFERROR(IF(VLOOKUP($A33,全人物技能说明!$A$1:$O$99,7,FALSE)<>"",VLOOKUP($A33,全人物技能说明!$A$1:$O$99,7,FALSE),""),"") -> 攻速倒数第二 | P33: =RANK(Y33,Y:Y) -> 39 | Q33: =RANK(Z33,Z:Z) -> 41 | R33: =RANK(AA33,AA:AA) -> 39 | S33: =RANK(AB33,AB:AB) -> 40 | T33: =RANK(AC33,AC:AC) -> 40 | U33: =Y33+Z33+AA33+AB33+AC33 -> 438 | W33: =C33 -> 5 | Y33: =IFERROR(VALUE(LEFT(AE33,FIND("(",AE33)-1))+($W33-1)*VALUE(MID(AE33,FIND("+",AE33)+1,FIND(")",AE33)-FIND("+",AE33)-1)),"") -> 96 | Z33: =IFERROR(VALUE(LEFT(AF33,FIND("(",AF33)-1))+($W33-1)*VALUE(MID(AF33,FIND("+",AF33)+1,FIND(")",AF33)-FIND("+",AF33)-1)),"") -> 64 | AA33: =IFERROR(VALUE(LEFT(AG33,FIND("(",AG33)-1))+($W33-1)*VALUE(MID(AG33,FIND("+",AG33)+1,FIND(")",AG33)-FIND("+",AG33)-1)),"") -> 96 | AB33: =IFERROR(VALUE(LEFT(AH33,FIND("(",AH33)-1))+($W33-1)*VALUE(MID(AH33,FIND("+",AH33)+1,FIND(")",AH33)-FIND("+",AH33)-1)),"") -> 86 | AC33: =IFERROR(VALUE(LEFT(AI33,FIND("(",AI33)-1))+($W33-1)*VALUE(MID(AI33,FIND("+",AI33)+1,FIND(")",AI33)-FIND("+",AI33)-1)),"") -> 96 | AE33: =IFERROR(VLOOKUP($A33,全人物技能说明!$A$1:$O$99,9,FALSE),"") -> 60(+9) | AF33: =IFERROR(VLOOKUP($A33,全人物技能说明!$A$1:$O$99,10,FALSE),"") -> 40(+6) | AG33: =IFERROR(VLOOKUP($A33,全人物技能说明!$A$1:$O$99,11,FALSE),"") -> 60(+9) | AH33: =IFERROR(VLOOKUP($A33,全人物技能说明!$A$1:$O$99,12,FALSE),"") -> 54(+8) | AI33: =IFERROR(VLOOKUP($A33,全人物技能说明!$A$1:$O$99,13,FALSE),"") -> 60(+9)
A34: Maria | B34: =IFERROR(VLOOKUP($A34,全人物技能说明!$A$1:$O$99,2,FALSE),"") -> 玛丽亚 | C34: 5 | D34: =IFERROR(VLOOKUP($A34,全人物技能说明!$A$1:$O$99,3,FALSE),"") -> 8箱子 | E34: =IFERROR(VLOOKUP($A34,全人物技能说明!$A$1:$O$99,4,FALSE),"") -> 稀有 | F34: =IFERROR(VLOOKUP($A34,全人物技能说明!$A$1:$O$99,7,FALSE),"") -> 0 | G34: =IFERROR(VLOOKUP($A34,全人物技能说明!$A$1:$O$99,8,FALSE),"") -> 为 2 名血量最低的队友回复 10% 最大生命值 + [20% INT]。 | H34: 为 2 名血量最低的队友回复 10% 最大生命值 + [20% INT]。 | I34: =IFERROR(VLOOKUP($A34,全人物技能说明!$A$1:$O$99,14,FALSE),"") -> U | J34: I | K34: I | L34: I | M34: =IFERROR(IF(VLOOKUP($A34,全人物技能说明!$A$1:$O$99,7,FALSE)<>"",VLOOKUP($A34,全人物技能说明!$A$1:$O$99,7,FALSE),""),"") | P34: =RANK(Y34,Y:Y) -> 39 | Q34: =RANK(Z34,Z:Z) -> 41 | R34: =RANK(AA34,AA:AA) -> 40 | S34: =RANK(AB34,AB:AB) -> 41 | T34: =RANK(AC34,AC:AC) -> 37 | U34: =Y34+Z34+AA34+AB34+AC34 -> 432 | W34: =C34 -> 5 | Y34: =IFERROR(VALUE(LEFT(AE34,FIND("(",AE34)-1))+($W34-1)*VALUE(MID(AE34,FIND("+",AE34)+1,FIND(")",AE34)-FIND("+",AE34)-1)),"") -> 96 | Z34: =IFERROR(VALUE(LEFT(AF34,FIND("(",AF34)-1))+($W34-1)*VALUE(MID(AF34,FIND("+",AF34)+1,FIND(")",AF34)-FIND("+",AF34)-1)),"") -> 64 | AA34: =IFERROR(VALUE(LEFT(AG34,FIND("(",AG34)-1))+($W34-1)*VALUE(MID(AG34,FIND("+",AG34)+1,FIND(")",AG34)-FIND("+",AG34)-1)),"") -> 86 | AB34: =IFERROR(VALUE(LEFT(AH34,FIND("(",AH34)-1))+($W34-1)*VALUE(MID(AH34,FIND("+",AH34)+1,FIND(")",AH34)-FIND("+",AH34)-1)),"") -> 76 | AC34: =IFERROR(VALUE(LEFT(AI34,FIND("(",AI34)-1))+($W34-1)*VALUE(MID(AI34,FIND("+",AI34)+1,FIND(")",AI34)-FIND("+",AI34)-1)),"") -> 110 | AE34: =IFERROR(VLOOKUP($A34,全人物技能说明!$A$1:$O$99,9,FALSE),"") -> 60(+9) | AF34: =IFERROR(VLOOKUP($A34,全人物技能说明!$A$1:$O$99,10,FALSE),"") -> 40(+6) | AG34: =IFERROR(VLOOKUP($A34,全人物技能说明!$A$1:$O$99,11,FALSE),"") -> 54(+8) | AH34: =IFERROR(VLOOKUP($A34,全人物技能说明!$A$1:$O$99,12,FALSE),"") -> 48(+7) | AI34: =IFERROR(VLOOKUP($A34,全人物技能说明!$A$1:$O$99,13,FALSE),"") -> 66(+11)
A35: PAIN | B35: =IFERROR(VLOOKUP($A35,全人物技能说明!$A$1:$O$99,2,FALSE),"") -> 佩恩 | C35: 3 | D35: =IFERROR(VLOOKUP($A35,全人物技能说明!$A$1:$O$99,3,FALSE),"") -> 5剧情 | E35: =IFERROR(VLOOKUP($A35,全人物技能说明!$A$1:$O$99,4,FALSE),"") -> 传说 | F35: =IFERROR(VLOOKUP($A35,全人物技能说明!$A$1:$O$99,7,FALSE),"") -> 0 | G35: =IFERROR(VLOOKUP($A35,全人物技能说明!$A$1:$O$99,8,FALSE),"") -> 鞭笞最多 4 名敌人，各造成 [30% DPS] 伤害。 | H35: 鞭打最多3名敌人，对每名敌人造成 [30% DPS] 伤害。 | I35: =IFERROR(VLOOKUP($A35,全人物技能说明!$A$1:$O$99,14,FALSE),"") -> A | J35: =IFERROR(VLOOKUP($A35,全人物技能说明!$A$1:$O$99,15,FALSE),"") -> U | K35: A | L35: A | M35: =IFERROR(IF(VLOOKUP($A35,全人物技能说明!$A$1:$O$99,7,FALSE)<>"",VLOOKUP($A35,全人物技能说明!$A$1:$O$99,7,FALSE),""),"") | P35: =RANK(Y35,Y:Y) -> 41 | Q35: =RANK(Z35,Z:Z) -> 39 | R35: =RANK(AA35,AA:AA) -> 41 | S35: =RANK(AB35,AB:AB) -> 39 | T35: =RANK(AC35,AC:AC) -> 42 | U35: =Y35+Z35+AA35+AB35+AC35 -> 424 | W35: =C35 -> 3 | Y35: =IFERROR(VALUE(LEFT(AE35,FIND("(",AE35)-1))+($W35-1)*VALUE(MID(AE35,FIND("+",AE35)+1,FIND(")",AE35)-FIND("+",AE35)-1)),"") -> 88 | Z35: =IFERROR(VALUE(LEFT(AF35,FIND("(",AF35)-1))+($W35-1)*VALUE(MID(AF35,FIND("+",AF35)+1,FIND(")",AF35)-FIND("+",AF35)-1)),"") -> 100 | AA35: =IFERROR(VALUE(LEFT(AG35,FIND("(",AG35)-1))+($W35-1)*VALUE(MID(AG35,FIND("+",AG35)+1,FIND(")",AG35)-FIND("+",AG35)-1)),"") -> 78 | AB35: =IFERROR(VALUE(LEFT(AH35,FIND("(",AH35)-1))+($W35-1)*VALUE(MID(AH35,FIND("+",AH35)+1,FIND(")",AH35)-FIND("+",AH35)-1)),"") -> 88 | AC35: =IFERROR(VALUE(LEFT(AI35,FIND("(",AI35)-1))+($W35-1)*VALUE(MID(AI35,FIND("+",AI35)+1,FIND(")",AI35)-FIND("+",AI35)-1)),"") -> 70 | AE35: =IFERROR(VLOOKUP($A35,全人物技能说明!$A$1:$O$99,9,FALSE),"") -> 66(+11) | AF35: =IFERROR(VLOOKUP($A35,全人物技能说明!$A$1:$O$99,10,FALSE),"") -> 72(+14) | AG35: =IFERROR(VLOOKUP($A35,全人物技能说明!$A$1:$O$99,11,FALSE),"") -> 60(+9) | AH35: =IFERROR(VLOOKUP($A35,全人物技能说明!$A$1:$O$99,12,FALSE),"") -> 66(+11) | AI35: =IFERROR(VLOOKUP($A35,全人物技能说明!$A$1:$O$99,13,FALSE),"") -> 54(+8)
A36: Emily | B36: =IFERROR(VLOOKUP($A36,全人物技能说明!$A$1:$O$99,2,FALSE),"") -> 艾米莉 | C36: 2 | D36: =IFERROR(VLOOKUP($A36,全人物技能说明!$A$1:$O$99,3,FALSE),"") -> 7剧情 | E36: =IFERROR(VLOOKUP($A36,全人物技能说明!$A$1:$O$99,4,FALSE),"") -> 史诗 | F36: =IFERROR(VLOOKUP($A36,全人物技能说明!$A$1:$O$99,7,FALSE),"") -> 0 | G36: =IFERROR(VLOOKUP($A36,全人物技能说明!$A$1:$O$99,8,FALSE),"") -> 跳向最虚弱的敌人，造成 [250% DPS] 伤害。 | H36: 跳向最虚弱的敌人，造成 [250% DPS] 伤害。 | I36: =IFERROR(VLOOKUP($A36,全人物技能说明!$A$1:$O$99,14,FALSE),"") -> W | J36: =IFERROR(VLOOKUP($A36,全人物技能说明!$A$1:$O$99,15,FALSE),"") -> F | K36: W | L36: W | M36: =IFERROR(IF(VLOOKUP($A36,全人物技能说明!$A$1:$O$99,7,FALSE)<>"",VLOOKUP($A36,全人物技能说明!$A$1:$O$99,7,FALSE),""),"") | P36: =RANK(Y36,Y:Y) -> 42 | Q36: =RANK(Z36,Z:Z) -> 40 | R36: =RANK(AA36,AA:AA) -> 42 | S36: =RANK(AB36,AB:AB) -> 42 | T36: =RANK(AC36,AC:AC) -> 41 | U36: =Y36+Z36+AA36+AB36+AC36 -> 371 | W36: =C36 -> 2 | Y36: =IFERROR(VALUE(LEFT(AE36,FIND("(",AE36)-1))+($W36-1)*VALUE(MID(AE36,FIND("+",AE36)+1,FIND(")",AE36)-FIND("+",AE36)-1)),"") -> 86 | Z36: =IFERROR(VALUE(LEFT(AF36,FIND("(",AF36)-1))+($W36-1)*VALUE(MID(AF36,FIND("+",AF36)+1,FIND(")",AF36)-FIND("+",AF36)-1)),"") -> 69 | AA36: =IFERROR(VALUE(LEFT(AG36,FIND("(",AG36)-1))+($W36-1)*VALUE(MID(AG36,FIND("+",AG36)+1,FIND(")",AG36)-FIND("+",AG36)-1)),"") -> 77 | AB36: =IFERROR(VALUE(LEFT(AH36,FIND("(",AH36)-1))+($W36-1)*VALUE(MID(AH36,FIND("+",AH36)+1,FIND(")",AH36)-FIND("+",AH36)-1)),"") -> 62 | AC36: =IFERROR(VALUE(LEFT(AI36,FIND("(",AI36)-1))+($W36-1)*VALUE(MID(AI36,FIND("+",AI36)+1,FIND(")",AI36)-FIND("+",AI36)-1)),"") -> 77 | AE36: =IFERROR(VLOOKUP($A36,全人物技能说明!$A$1:$O$99,9,FALSE),"") -> 72(+14) | AF36: =IFERROR(VLOOKUP($A36,全人物技能说明!$A$1:$O$99,10,FALSE),"") -> 60(+9) | AG36: =IFERROR(VLOOKUP($A36,全人物技能说明!$A$1:$O$99,11,FALSE),"") -> 66(+11) | AH36: =IFERROR(VLOOKUP($A36,全人物技能说明!$A$1:$O$99,12,FALSE),"") -> 54(+8) | AI36: =IFERROR(VLOOKUP($A36,全人物技能说明!$A$1:$O$99,13,FALSE),"") -> 66(+11)
A37: Adelaine | B37: =IFERROR(VLOOKUP($A37,全人物技能说明!$A$1:$O$99,2,FALSE),"") -> 阿德莱恩 | C37: -2 | D37: =IFERROR(VLOOKUP($A37,全人物技能说明!$A$1:$O$99,3,FALSE),"") -> 0 | E37: =IFERROR(VLOOKUP($A37,全人物技能说明!$A$1:$O$99,4,FALSE),"") -> 0 | F37: =IFERROR(VLOOKUP($A37,全人物技能说明!$A$1:$O$99,7,FALSE),"") -> 攻速倒数第一，成长高每级+14的A，使用X2近战武士刀8次 | G37: =IFERROR(VLOOKUP($A37,全人物技能说明!$A$1:$O$99,8,FALSE),"") -> 随机敌人，每个造成36点伤害，忽略所有防御。 | I37: =IFERROR(VLOOKUP($A37,全人物技能说明!$A$1:$O$99,14,FALSE),"") -> 0 | J37: =IFERROR(VLOOKUP($A37,全人物技能说明!$A$1:$O$99,15,FALSE),"") -> 0 | L37: A | M37: =IFERROR(IF(VLOOKUP($A37,全人物技能说明!$A$1:$O$99,7,FALSE)<>"",VLOOKUP($A37,全人物技能说明!$A$1:$O$99,7,FALSE),""),"") -> 攻速倒数第一，成长高每级+14的A，使用X2近战武士刀8次 | P37: =RANK(Y37,Y:Y) -> 44 | Q37: =RANK(Z37,Z:Z) -> 45 | R37: =RANK(AA37,AA:AA) -> 43 | S37: =RANK(AB37,AB:AB) -> 44 | T37: =RANK(AC37,AC:AC) -> 46 | U37: =Y37+Z37+AA37+AB37+AC37 -> 153 | W37: =C37 -> -2 | Y37: =IFERROR(VALUE(LEFT(AE37,FIND("(",AE37)-1))+($W37-1)*VALUE(MID(AE37,FIND("+",AE37)+1,FIND(")",AE37)-FIND("+",AE37)-1)),"") -> 30 | Z37: =IFERROR(VALUE(LEFT(AF37,FIND("(",AF37)-1))+($W37-1)*VALUE(MID(AF37,FIND("+",AF37)+1,FIND(")",AF37)-FIND("+",AF37)-1)),"") -> 30 | AA37: =IFERROR(VALUE(LEFT(AG37,FIND("(",AG37)-1))+($W37-1)*VALUE(MID(AG37,FIND("+",AG37)+1,FIND(")",AG37)-FIND("+",AG37)-1)),"") -> 33 | AB37: =IFERROR(VALUE(LEFT(AH37,FIND("(",AH37)-1))+($W37-1)*VALUE(MID(AH37,FIND("+",AH37)+1,FIND(")",AH37)-FIND("+",AH37)-1)),"") -> 30 | AC37: =IFERROR(VALUE(LEFT(AI37,FIND("(",AI37)-1))+($W37-1)*VALUE(MID(AI37,FIND("+",AI37)+1,FIND(")",AI37)-FIND("+",AI37)-1)),"") -> 30 | AE37: =IFERROR(VLOOKUP($A37,全人物技能说明!$A$1:$O$99,9,FALSE),"") -> 54(+8) | AF37: =IFERROR(VLOOKUP($A37,全人物技能说明!$A$1:$O$99,10,FALSE),"") -> 72(+14) | AG37: =IFERROR(VLOOKUP($A37,全人物技能说明!$A$1:$O$99,11,FALSE),"") -> 60(+9) | AH37: =IFERROR(VLOOKUP($A37,全人物技能说明!$A$1:$O$99,12,FALSE),"") -> 72(+14) | AI37: =IFERROR(VLOOKUP($A37,全人物技能说明!$A$1:$O$99,13,FALSE),"") -> 54(+8)
A38: Veneza | B38: =IFERROR(VLOOKUP($A38,全人物技能说明!$A$1:$O$99,2,FALSE),"") -> 威妮莎 | C38: -2 | D38: =IFERROR(VLOOKUP($A38,全人物技能说明!$A$1:$O$99,3,FALSE),"") -> 5箱子 | E38: =IFERROR(VLOOKUP($A38,全人物技能说明!$A$1:$O$99,4,FALSE),"") -> 稀有 | F38: =IFERROR(VLOOKUP($A38,全人物技能说明!$A$1:$O$99,7,FALSE),"") -> 0 | G38: =IFERROR(VLOOKUP($A38,全人物技能说明!$A$1:$O$99,8,FALSE),"") -> 指挥 2 名队友瞬间攻击一名敌人。 | I38: =IFERROR(VLOOKUP($A38,全人物技能说明!$A$1:$O$99,14,FALSE),"") -> F | J38: =IFERROR(VLOOKUP($A38,全人物技能说明!$A$1:$O$99,15,FALSE),"") -> I | L38: A | M38: =IFERROR(IF(VLOOKUP($A38,全人物技能说明!$A$1:$O$99,7,FALSE)<>"",VLOOKUP($A38,全人物技能说明!$A$1:$O$99,7,FALSE),""),"") | P38: =RANK(Y38,Y:Y) -> 43 | Q38: =RANK(Z38,Z:Z) -> 43 | R38: =RANK(AA38,AA:AA) -> 45 | S38: =RANK(AB38,AB:AB) -> 44 | T38: =RANK(AC38,AC:AC) -> 44 | U38: =Y38+Z38+AA38+AB38+AC38 -> 159 | W38: =C38 -> -2 | Y38: =IFERROR(VALUE(LEFT(AE38,FIND("(",AE38)-1))+($W38-1)*VALUE(MID(AE38,FIND("+",AE38)+1,FIND(")",AE38)-FIND("+",AE38)-1)),"") -> 33 | Z38: =IFERROR(VALUE(LEFT(AF38,FIND("(",AF38)-1))+($W38-1)*VALUE(MID(AF38,FIND("+",AF38)+1,FIND(")",AF38)-FIND("+",AF38)-1)),"") -> 33 | AA38: =IFERROR(VALUE(LEFT(AG38,FIND("(",AG38)-1))+($W38-1)*VALUE(MID(AG38,FIND("+",AG38)+1,FIND(")",AG38)-FIND("+",AG38)-1)),"") -> 30 | AB38: =IFERROR(VALUE(LEFT(AH38,FIND("(",AH38)-1))+($W38-1)*VALUE(MID(AH38,FIND("+",AH38)+1,FIND(")",AH38)-FIND("+",AH38)-1)),"") -> 30 | AC38: =IFERROR(VALUE(LEFT(AI38,FIND("(",AI38)-1))+($W38-1)*VALUE(MID(AI38,FIND("+",AI38)+1,FIND(")",AI38)-FIND("+",AI38)-1)),"") -> 33 | AE38: =IFERROR(VLOOKUP($A38,全人物技能说明!$A$1:$O$99,9,FALSE),"") -> 66(+11) | AF38: =IFERROR(VLOOKUP($A38,全人物技能说明!$A$1:$O$99,10,FALSE),"") -> 66(+11) | AG38: =IFERROR(VLOOKUP($A38,全人物技能说明!$A$1:$O$99,11,FALSE),"") -> 54(+8) | AH38: =IFERROR(VLOOKUP($A38,全人物技能说明!$A$1:$O$99,12,FALSE),"") -> 72(+14) | AI38: =IFERROR(VLOOKUP($A38,全人物技能说明!$A$1:$O$99,13,FALSE),"") -> 60(+9)
A39: pink | B39: =IFERROR(VLOOKUP($A39,全人物技能说明!$A$1:$O$99,2,FALSE),"") -> 粉红 | C39: -2 | D39: =IFERROR(VLOOKUP($A39,全人物技能说明!$A$1:$O$99,3,FALSE),"") -> 8箱子 | E39: =IFERROR(VLOOKUP($A39,全人物技能说明!$A$1:$O$99,4,FALSE),"") -> 史诗 | F39: =IFERROR(VLOOKUP($A39,全人物技能说明!$A$1:$O$99,7,FALSE),"") -> 0 | G39: =IFERROR(VLOOKUP($A39,全人物技能说明!$A$1:$O$99,8,FALSE),"") -> 展露粉嫩，使全体敌人眩晕1回，并使其在接下来的2次受击中降 [15% ?] 防。 | I39: =IFERROR(VLOOKUP($A39,全人物技能说明!$A$1:$O$99,14,FALSE),"") -> F | J39: =IFERROR(VLOOKUP($A39,全人物技能说明!$A$1:$O$99,15,FALSE),"") -> W | L39: A | M39: =IFERROR(IF(VLOOKUP($A39,全人物技能说明!$A$1:$O$99,7,FALSE)<>"",VLOOKUP($A39,全人物技能说明!$A$1:$O$99,7,FALSE),""),"") | P39: =RANK(Y39,Y:Y) -> 44 | Q39: =RANK(Z39,Z:Z) -> 43 | R39: =RANK(AA39,AA:AA) -> 43 | S39: =RANK(AB39,AB:AB) -> 44 | T39: =RANK(AC39,AC:AC) -> 44 | U39: =Y39+Z39+AA39+AB39+AC39 -> 159 | W39: =C39 -> -2 | Y39: =IFERROR(VALUE(LEFT(AE39,FIND("(",AE39)-1))+($W39-1)*VALUE(MID(AE39,FIND("+",AE39)+1,FIND(")",AE39)-FIND("+",AE39)-1)),"") -> 30 | Z39: =IFERROR(VALUE(LEFT(AF39,FIND("(",AF39)-1))+($W39-1)*VALUE(MID(AF39,FIND("+",AF39)+1,FIND(")",AF39)-FIND("+",AF39)-1)),"") -> 33 | AA39: =IFERROR(VALUE(LEFT(AG39,FIND("(",AG39)-1))+($W39-1)*VALUE(MID(AG39,FIND("+",AG39)+1,FIND(")",AG39)-FIND("+",AG39)-1)),"") -> 33 | AB39: =IFERROR(VALUE(LEFT(AH39,FIND("(",AH39)-1))+($W39-1)*VALUE(MID(AH39,FIND("+",AH39)+1,FIND(")",AH39)-FIND("+",AH39)-1)),"") -> 30 | AC39: =IFERROR(VALUE(LEFT(AI39,FIND("(",AI39)-1))+($W39-1)*VALUE(MID(AI39,FIND("+",AI39)+1,FIND(")",AI39)-FIND("+",AI39)-1)),"") -> 33 | AE39: =IFERROR(VLOOKUP($A39,全人物技能说明!$A$1:$O$99,9,FALSE),"") -> 54(+8) | AF39: =IFERROR(VLOOKUP($A39,全人物技能说明!$A$1:$O$99,10,FALSE),"") -> 66(+11) | AG39: =IFERROR(VLOOKUP($A39,全人物技能说明!$A$1:$O$99,11,FALSE),"") -> 66(+11) | AH39: =IFERROR(VLOOKUP($A39,全人物技能说明!$A$1:$O$99,12,FALSE),"") -> 72(+14) | AI39: =IFERROR(VLOOKUP($A39,全人物技能说明!$A$1:$O$99,13,FALSE),"") -> 60(+9)
A40: Z-ANGELA | B40: =IFERROR(VLOOKUP($A40,全人物技能说明!$A$1:$O$99,2,FALSE),"") -> 0 | C40: -9 | D40: =IFERROR(VLOOKUP($A40,全人物技能说明!$A$1:$O$99,3,FALSE),"") -> Z工人 | E40: =IFERROR(VLOOKUP($A40,全人物技能说明!$A$1:$O$99,4,FALSE),"") -> 传说 | F40: =IFERROR(VLOOKUP($A40,全人物技能说明!$A$1:$O$99,7,FALSE),"") -> 工人 | G40: =IFERROR(VLOOKUP($A40,全人物技能说明!$A$1:$O$99,8,FALSE),"") -> 0 | I40: =IFERROR(VLOOKUP($A40,全人物技能说明!$A$1:$O$99,14,FALSE),"") -> W | J40: =IFERROR(VLOOKUP($A40,全人物技能说明!$A$1:$O$99,15,FALSE),"") -> 0 | M40: =IFERROR(IF(VLOOKUP($A40,全人物技能说明!$A$1:$O$99,7,FALSE)<>"",VLOOKUP($A40,全人物技能说明!$A$1:$O$99,7,FALSE),""),"") -> 工人 | O40: 广播 | P40: =RANK(Y40,Y:Y) -> 13 | Q40: =RANK(Z40,Z:Z) -> 28 | R40: =RANK(AA40,AA:AA) -> 24 | S40: =RANK(AB40,AB:AB) -> 31 | T40: =RANK(AC40,AC:AC) -> 31 | U40: =Y40+Z40+AA40+AB40+AC40 -> 712 | W40: 20 | Y40: =IFERROR(VALUE(LEFT(AE40,FIND("(",AE40)-1))+($W40-1)*VALUE(MID(AE40,FIND("+",AE40)+1,FIND(")",AE40)-FIND("+",AE40)-1)),"") -> 193 | Z40: =IFERROR(VALUE(LEFT(AF40,FIND("(",AF40)-1))+($W40-1)*VALUE(MID(AF40,FIND("+",AF40)+1,FIND(")",AF40)-FIND("+",AF40)-1)),"") -> 124 | AA40: =IFERROR(VALUE(LEFT(AG40,FIND("(",AG40)-1))+($W40-1)*VALUE(MID(AG40,FIND("+",AG40)+1,FIND(")",AG40)-FIND("+",AG40)-1)),"") -> 147 | AB40: =IFERROR(VALUE(LEFT(AH40,FIND("(",AH40)-1))+($W40-1)*VALUE(MID(AH40,FIND("+",AH40)+1,FIND(")",AH40)-FIND("+",AH40)-1)),"") -> 124 | AC40: =IFERROR(VALUE(LEFT(AI40,FIND("(",AI40)-1))+($W40-1)*VALUE(MID(AI40,FIND("+",AI40)+1,FIND(")",AI40)-FIND("+",AI40)-1)),"") -> 124 | AE40: =IFERROR(VLOOKUP($A40,全人物技能说明!$A$1:$O$99,9,FALSE),"") -> 41(+8) | AF40: =IFERROR(VLOOKUP($A40,全人物技能说明!$A$1:$O$99,10,FALSE),"") -> 29(+5) | AG40: =IFERROR(VLOOKUP($A40,全人物技能说明!$A$1:$O$99,11,FALSE),"") -> 33(+6) | AH40: =IFERROR(VLOOKUP($A40,全人物技能说明!$A$1:$O$99,12,FALSE),"") -> 29(+5) | AI40: =IFERROR(VLOOKUP($A40,全人物技能说明!$A$1:$O$99,13,FALSE),"") -> 29(+5)
A41: W-U-IA-F | C41: -9 | D41: =IFERROR(VLOOKUP($A41,全人物技能说明!$A$1:$O$99,3,FALSE),"") -> Z工人 | E41: =IFERROR(VLOOKUP($A41,全人物技能说明!$A$1:$O$99,4,FALSE),"") -> 史诗 | M41: =IFERROR(IF(VLOOKUP($A41,全人物技能说明!$A$1:$O$99,7,FALSE)<>"",VLOOKUP($A41,全人物技能说明!$A$1:$O$99,7,FALSE),""),"") -> 工人 | P41: =RANK(Y41,Y:Y) -> 15 | Q41: =RANK(Z41,Z:Z) -> 32 | R41: =RANK(AA41,AA:AA) -> 33 | S41: =RANK(AB41,AB:AB) -> 37 | T41: =RANK(AC41,AC:AC) -> 22 | Y41: 191 | Z41: 122 | AA41: 122 | AB41: 99 | AC41: 145
A42: Z-YASU | B42: =IFERROR(VLOOKUP($A42,全人物技能说明!$A$1:$O$99,2,FALSE),"") -> 0 | C42: -9 | D42: =IFERROR(VLOOKUP($A42,全人物技能说明!$A$1:$O$99,3,FALSE),"") -> Z工人 | E42: =IFERROR(VLOOKUP($A42,全人物技能说明!$A$1:$O$99,4,FALSE),"") -> 传说 | F42: =IFERROR(VLOOKUP($A42,全人物技能说明!$A$1:$O$99,7,FALSE),"") -> 工人 | G42: =IFERROR(VLOOKUP($A42,全人物技能说明!$A$1:$O$99,8,FALSE),"") -> 0 | I42: =IFERROR(VLOOKUP($A42,全人物技能说明!$A$1:$O$99,14,FALSE),"") -> W | J42: =IFERROR(VLOOKUP($A42,全人物技能说明!$A$1:$O$99,15,FALSE),"") -> 0 | M42: =IFERROR(IF(VLOOKUP($A42,全人物技能说明!$A$1:$O$99,7,FALSE)<>"",VLOOKUP($A42,全人物技能说明!$A$1:$O$99,7,FALSE),""),"") -> 工人 | P42: =RANK(Y42,Y:Y) -> 16 | Q42: =RANK(Z42,Z:Z) -> 35 | R42: =RANK(AA42,AA:AA) -> 34 | S42: =RANK(AB42,AB:AB) -> 35 | T42: =RANK(AC42,AC:AC) -> 24 | U42: =Y42+Z42+AA42+AB42+AC42 -> 687 | W42: 20 | Y42: =IFERROR(VALUE(LEFT(AE42,FIND("(",AE42)-1))+($W42-1)*VALUE(MID(AE42,FIND("+",AE42)+1,FIND(")",AE42)-FIND("+",AE42)-1)),"") -> 188 | Z42: =IFERROR(VALUE(LEFT(AF42,FIND("(",AF42)-1))+($W42-1)*VALUE(MID(AF42,FIND("+",AF42)+1,FIND(")",AF42)-FIND("+",AF42)-1)),"") -> 119 | AA42: =IFERROR(VALUE(LEFT(AG42,FIND("(",AG42)-1))+($W42-1)*VALUE(MID(AG42,FIND("+",AG42)+1,FIND(")",AG42)-FIND("+",AG42)-1)),"") -> 119 | AB42: =IFERROR(VALUE(LEFT(AH42,FIND("(",AH42)-1))+($W42-1)*VALUE(MID(AH42,FIND("+",AH42)+1,FIND(")",AH42)-FIND("+",AH42)-1)),"") -> 119 | AC42: =IFERROR(VALUE(LEFT(AI42,FIND("(",AI42)-1))+($W42-1)*VALUE(MID(AI42,FIND("+",AI42)+1,FIND(")",AI42)-FIND("+",AI42)-1)),"") -> 142 | AE42: =IFERROR(VLOOKUP($A42,全人物技能说明!$A$1:$O$99,9,FALSE),"") -> 36(+8) | AF42: =IFERROR(VLOOKUP($A42,全人物技能说明!$A$1:$O$99,10,FALSE),"") -> 24(+5) | AG42: =IFERROR(VLOOKUP($A42,全人物技能说明!$A$1:$O$99,11,FALSE),"") -> 24(+5) | AH42: =IFERROR(VLOOKUP($A42,全人物技能说明!$A$1:$O$99,12,FALSE),"") -> 24(+5) | AI42: =IFERROR(VLOOKUP($A42,全人物技能说明!$A$1:$O$99,13,FALSE),"") -> 28(+6)
A43: Z-MARY | B43: =IFERROR(VLOOKUP($A43,全人物技能说明!$A$1:$O$99,2,FALSE),"") -> 0 | C43: -9 | D43: =IFERROR(VLOOKUP($A43,全人物技能说明!$A$1:$O$99,3,FALSE),"") -> Z工人 | E43: =IFERROR(VLOOKUP($A43,全人物技能说明!$A$1:$O$99,4,FALSE),"") -> 传说 | F43: =IFERROR(VLOOKUP($A43,全人物技能说明!$A$1:$O$99,7,FALSE),"") -> 工人 | G43: =IFERROR(VLOOKUP($A43,全人物技能说明!$A$1:$O$99,8,FALSE),"") -> 0 | I43: =IFERROR(VLOOKUP($A43,全人物技能说明!$A$1:$O$99,14,FALSE),"") -> F | J43: =IFERROR(VLOOKUP($A43,全人物技能说明!$A$1:$O$99,15,FALSE),"") -> 0 | M43: =IFERROR(IF(VLOOKUP($A43,全人物技能说明!$A$1:$O$99,7,FALSE)<>"",VLOOKUP($A43,全人物技能说明!$A$1:$O$99,7,FALSE),""),"") -> 工人 | O43: F | P43: =RANK(Y43,Y:Y) -> 25 | Q43: =RANK(Z43,Z:Z) -> 28 | R43: =RANK(AA43,AA:AA) -> 38 | S43: =RANK(AB43,AB:AB) -> 14 | T43: =RANK(AC43,AC:AC) -> 20 | U43: =Y43+Z43+AA43+AB43+AC43 -> 712 | W43: 20 | Y43: =IFERROR(VALUE(LEFT(AE43,FIND("(",AE43)-1))+($W43-1)*VALUE(MID(AE43,FIND("+",AE43)+1,FIND(")",AE43)-FIND("+",AE43)-1)),"") -> 147 | Z43: =IFERROR(VALUE(LEFT(AF43,FIND("(",AF43)-1))+($W43-1)*VALUE(MID(AF43,FIND("+",AF43)+1,FIND(")",AF43)-FIND("+",AF43)-1)),"") -> 124 | AA43: =IFERROR(VALUE(LEFT(AG43,FIND("(",AG43)-1))+($W43-1)*VALUE(MID(AG43,FIND("+",AG43)+1,FIND(")",AG43)-FIND("+",AG43)-1)),"") -> 101 | AB43: =IFERROR(VALUE(LEFT(AH43,FIND("(",AH43)-1))+($W43-1)*VALUE(MID(AH43,FIND("+",AH43)+1,FIND(")",AH43)-FIND("+",AH43)-1)),"") -> 193 | AC43: =IFERROR(VALUE(LEFT(AI43,FIND("(",AI43)-1))+($W43-1)*VALUE(MID(AI43,FIND("+",AI43)+1,FIND(")",AI43)-FIND("+",AI43)-1)),"") -> 147 | AE43: =IFERROR(VLOOKUP($A43,全人物技能说明!$A$1:$O$99,9,FALSE),"") -> 33(+6) | AF43: =IFERROR(VLOOKUP($A43,全人物技能说明!$A$1:$O$99,10,FALSE),"") -> 29(+5) | AG43: =IFERROR(VLOOKUP($A43,全人物技能说明!$A$1:$O$99,11,FALSE),"") -> 25(+4) | AH43: =IFERROR(VLOOKUP($A43,全人物技能说明!$A$1:$O$99,12,FALSE),"") -> 41(+8) | AI43: =IFERROR(VLOOKUP($A43,全人物技能说明!$A$1:$O$99,13,FALSE),"") -> 33(+6)
A44: Z-Sakaki | B44: =IFERROR(VLOOKUP($A44,全人物技能说明!$A$1:$O$99,2,FALSE),"") -> 0 | C44: -9 | D44: =IFERROR(VLOOKUP($A44,全人物技能说明!$A$1:$O$99,3,FALSE),"") -> Z工人 | E44: =IFERROR(VLOOKUP($A44,全人物技能说明!$A$1:$O$99,4,FALSE),"") -> 传说 | F44: =IFERROR(VLOOKUP($A44,全人物技能说明!$A$1:$O$99,7,FALSE),"") -> 工人 | G44: =IFERROR(VLOOKUP($A44,全人物技能说明!$A$1:$O$99,8,FALSE),"") -> 0 | I44: =IFERROR(VLOOKUP($A44,全人物技能说明!$A$1:$O$99,14,FALSE),"") -> I | J44: =IFERROR(VLOOKUP($A44,全人物技能说明!$A$1:$O$99,15,FALSE),"") -> 0 | M44: =IFERROR(IF(VLOOKUP($A44,全人物技能说明!$A$1:$O$99,7,FALSE)<>"",VLOOKUP($A44,全人物技能说明!$A$1:$O$99,7,FALSE),""),"") -> 工人 | O44: 金库 | P44: =RANK(Y44,Y:Y) -> 25 | Q44: =RANK(Z44,Z:Z) -> 28 | R44: =RANK(AA44,AA:AA) -> 11 | S44: =RANK(AB44,AB:AB) -> 31 | T44: =RANK(AC44,AC:AC) -> 31 | U44: =Y44+Z44+AA44+AB44+AC44 -> 712 | W44: 20 | Y44: =IFERROR(VALUE(LEFT(AE44,FIND("(",AE44)-1))+($W44-1)*VALUE(MID(AE44,FIND("+",AE44)+1,FIND(")",AE44)-FIND("+",AE44)-1)),"") -> 147 | Z44: =IFERROR(VALUE(LEFT(AF44,FIND("(",AF44)-1))+($W44-1)*VALUE(MID(AF44,FIND("+",AF44)+1,FIND(")",AF44)-FIND("+",AF44)-1)),"") -> 124 | AA44: =IFERROR(VALUE(LEFT(AG44,FIND("(",AG44)-1))+($W44-1)*VALUE(MID(AG44,FIND("+",AG44)+1,FIND(")",AG44)-FIND("+",AG44)-1)),"") -> 193 | AB44: =IFERROR(VALUE(LEFT(AH44,FIND("(",AH44)-1))+($W44-1)*VALUE(MID(AH44,FIND("+",AH44)+1,FIND(")",AH44)-FIND("+",AH44)-1)),"") -> 124 | AC44: =IFERROR(VALUE(LEFT(AI44,FIND("(",AI44)-1))+($W44-1)*VALUE(MID(AI44,FIND("+",AI44)+1,FIND(")",AI44)-FIND("+",AI44)-1)),"") -> 124 | AE44: =IFERROR(VLOOKUP($A44,全人物技能说明!$A$1:$O$99,9,FALSE),"") -> 33(+6) | AF44: =IFERROR(VLOOKUP($A44,全人物技能说明!$A$1:$O$99,10,FALSE),"") -> 29(+5) | AG44: =IFERROR(VLOOKUP($A44,全人物技能说明!$A$1:$O$99,11,FALSE),"") -> 41(+8) | AH44: =IFERROR(VLOOKUP($A44,全人物技能说明!$A$1:$O$99,12,FALSE),"") -> 29(+5) | AI44: =IFERROR(VLOOKUP($A44,全人物技能说明!$A$1:$O$99,13,FALSE),"") -> 29(+5)
A45: I-W-AF-U | C45: -9 | D45: =IFERROR(VLOOKUP($A45,全人物技能说明!$A$1:$O$99,3,FALSE),"") -> Z工人 | E45: =IFERROR(VLOOKUP($A45,全人物技能说明!$A$1:$O$99,4,FALSE),"") -> 史诗 | M45: =IFERROR(IF(VLOOKUP($A45,全人物技能说明!$A$1:$O$99,7,FALSE)<>"",VLOOKUP($A45,全人物技能说明!$A$1:$O$99,7,FALSE),""),"") -> 工人 | O45: 血瓶 | P45: =RANK(Y45,Y:Y) -> 27 | Q45: =RANK(Z45,Z:Z) -> 32 | R45: =RANK(AA45,AA:AA) -> 12 | S45: =RANK(AB45,AB:AB) -> 34 | T45: =RANK(AC45,AC:AC) -> 39 | Y45: 145 | Z45: 122 | AA45: 191 | AB45: 122 | AC45: 99
A46: Z-LEILANI | B46: =IFERROR(VLOOKUP($A46,全人物技能说明!$A$1:$O$99,2,FALSE),"") -> 0 | C46: -9 | D46: =IFERROR(VLOOKUP($A46,全人物技能说明!$A$1:$O$99,3,FALSE),"") -> Z工人 | E46: =IFERROR(VLOOKUP($A46,全人物技能说明!$A$1:$O$99,4,FALSE),"") -> 传说 | F46: =IFERROR(VLOOKUP($A46,全人物技能说明!$A$1:$O$99,7,FALSE),"") -> 工人 | G46: =IFERROR(VLOOKUP($A46,全人物技能说明!$A$1:$O$99,8,FALSE),"") -> 0 | I46: =IFERROR(VLOOKUP($A46,全人物技能说明!$A$1:$O$99,14,FALSE),"") -> A | J46: =IFERROR(VLOOKUP($A46,全人物技能说明!$A$1:$O$99,15,FALSE),"") -> 0 | M46: =IFERROR(IF(VLOOKUP($A46,全人物技能说明!$A$1:$O$99,7,FALSE)<>"",VLOOKUP($A46,全人物技能说明!$A$1:$O$99,7,FALSE),""),"") -> 工人 | O46: 矿石 | P46: =RANK(Y46,Y:Y) -> 33 | Q46: =RANK(Z46,Z:Z) -> 14 | R46: =RANK(AA46,AA:AA) -> 32 | S46: =RANK(AB46,AB:AB) -> 24 | T46: =RANK(AC46,AC:AC) -> 31 | U46: =Y46+Z46+AA46+AB46+AC46 -> 712 | W46: 20 | Y46: =IFERROR(VALUE(LEFT(AE46,FIND("(",AE46)-1))+($W46-1)*VALUE(MID(AE46,FIND("+",AE46)+1,FIND(")",AE46)-FIND("+",AE46)-1)),"") -> 124 | Z46: =IFERROR(VALUE(LEFT(AF46,FIND("(",AF46)-1))+($W46-1)*VALUE(MID(AF46,FIND("+",AF46)+1,FIND(")",AF46)-FIND("+",AF46)-1)),"") -> 193 | AA46: =IFERROR(VALUE(LEFT(AG46,FIND("(",AG46)-1))+($W46-1)*VALUE(MID(AG46,FIND("+",AG46)+1,FIND(")",AG46)-FIND("+",AG46)-1)),"") -> 124 | AB46: =IFERROR(VALUE(LEFT(AH46,FIND("(",AH46)-1))+($W46-1)*VALUE(MID(AH46,FIND("+",AH46)+1,FIND(")",AH46)-FIND("+",AH46)-1)),"") -> 147 | AC46: =IFERROR(VALUE(LEFT(AI46,FIND("(",AI46)-1))+($W46-1)*VALUE(MID(AI46,FIND("+",AI46)+1,FIND(")",AI46)-FIND("+",AI46)-1)),"") -> 124 | AE46: =IFERROR(VLOOKUP($A46,全人物技能说明!$A$1:$O$99,9,FALSE),"") -> 29(+5) | AF46: =IFERROR(VLOOKUP($A46,全人物技能说明!$A$1:$O$99,10,FALSE),"") -> 41(+8) | AG46: =IFERROR(VLOOKUP($A46,全人物技能说明!$A$1:$O$99,11,FALSE),"") -> 29(+5) | AH46: =IFERROR(VLOOKUP($A46,全人物技能说明!$A$1:$O$99,12,FALSE),"") -> 33(+6) | AI46: =IFERROR(VLOOKUP($A46,全人物技能说明!$A$1:$O$99,13,FALSE),"") -> 29(+5)
A47: Z-DAISY | B47: =IFERROR(VLOOKUP($A47,全人物技能说明!$A$1:$O$99,2,FALSE),"") -> 0 | C47: -9 | D47: =IFERROR(VLOOKUP($A47,全人物技能说明!$A$1:$O$99,3,FALSE),"") -> Z工人 | E47: =IFERROR(VLOOKUP($A47,全人物技能说明!$A$1:$O$99,4,FALSE),"") -> 传说 | F47: =IFERROR(VLOOKUP($A47,全人物技能说明!$A$1:$O$99,7,FALSE),"") -> 工人 | G47: =IFERROR(VLOOKUP($A47,全人物技能说明!$A$1:$O$99,8,FALSE),"") -> 0 | I47: =IFERROR(VLOOKUP($A47,全人物技能说明!$A$1:$O$99,14,FALSE),"") -> U | J47: =IFERROR(VLOOKUP($A47,全人物技能说明!$A$1:$O$99,15,FALSE),"") -> 0 | M47: =IFERROR(IF(VLOOKUP($A47,全人物技能说明!$A$1:$O$99,7,FALSE)<>"",VLOOKUP($A47,全人物技能说明!$A$1:$O$99,7,FALSE),""),"") -> 工人 | P47: =RANK(Y47,Y:Y) -> 46 | Q47: =RANK(Z47,Z:Z) -> 46 | R47: =RANK(AA47,AA:AA) -> 46 | S47: =RANK(AB47,AB:AB) -> 43 | T47: =RANK(AC47,AC:AC) -> 43 | U47: =Y47+Z47+AA47+AB47+AC47 -> 161 | W47: 1 | Y47: =IFERROR(VALUE(LEFT(AE47,FIND("(",AE47)-1))+($W47-1)*VALUE(MID(AE47,FIND("+",AE47)+1,FIND(")",AE47)-FIND("+",AE47)-1)),"") -> 29 | Z47: =IFERROR(VALUE(LEFT(AF47,FIND("(",AF47)-1))+($W47-1)*VALUE(MID(AF47,FIND("+",AF47)+1,FIND(")",AF47)-FIND("+",AF47)-1)),"") -> 29 | AA47: =IFERROR(VALUE(LEFT(AG47,FIND("(",AG47)-1))+($W47-1)*VALUE(MID(AG47,FIND("+",AG47)+1,FIND(")",AG47)-FIND("+",AG47)-1)),"") -> 29 | AB47: =IFERROR(VALUE(LEFT(AH47,FIND("(",AH47)-1))+($W47-1)*VALUE(MID(AH47,FIND("+",AH47)+1,FIND(")",AH47)-FIND("+",AH47)-1)),"") -> 33 | AC47: =IFERROR(VALUE(LEFT(AI47,FIND("(",AI47)-1))+($W47-1)*VALUE(MID(AI47,FIND("+",AI47)+1,FIND(")",AI47)-FIND("+",AI47)-1)),"") -> 41 | AE47: =IFERROR(VLOOKUP($A47,全人物技能说明!$A$1:$O$99,9,FALSE),"") -> 29(+5) | AF47: =IFERROR(VLOOKUP($A47,全人物技能说明!$A$1:$O$99,10,FALSE),"") -> 29(+5) | AG47: =IFERROR(VLOOKUP($A47,全人物技能说明!$A$1:$O$99,11,FALSE),"") -> 29(+6) | AH47: =IFERROR(VLOOKUP($A47,全人物技能说明!$A$1:$O$99,12,FALSE),"") -> 33(+7) | AI47: =IFERROR(VLOOKUP($A47,全人物技能说明!$A$1:$O$99,13,FALSE),"") -> 41(+8)
A48: _+++ | B48: =IFERROR(VLOOKUP($A48,全人物技能说明!$A$1:$O$99,2,FALSE),"") -> _+++ | C48: -99 | D48: =IFERROR(VLOOKUP($A48,全人物技能说明!$A$1:$O$99,4,FALSE),"") -> _+++ | E48: =IFERROR(VLOOKUP($A48,全人物技能说明!$A$1:$O$99,4,FALSE),"") -> _+++ | F48: =IFERROR(VLOOKUP($A48,全人物技能说明!$A$1:$O$99,7,FALSE),"") -> _+++ | G48: =IFERROR(VLOOKUP($A48,全人物技能说明!$A$1:$O$99,8,FALSE),"") -> _+++ | I48: =IFERROR(VLOOKUP($A48,全人物技能说明!$A$1:$O$99,14,FALSE),"") -> _+++ | J48: =IFERROR(VLOOKUP($A48,全人物技能说明!$A$1:$O$99,15,FALSE),"") -> _+++ | M48: =IFERROR(IF(VLOOKUP($A48,全人物技能说明!$A$1:$O$99,7,FALSE)<>"",VLOOKUP($A48,全人物技能说明!$A$1:$O$99,7,FALSE),""),"") -> _+++ | P48: =RANK(Y48,Y:Y) -> 47 | Q48: =RANK(Z48,Z:Z) -> 47 | R48: =RANK(AA48,AA:AA) -> 47 | S48: =RANK(AB48,AB:AB) -> 47 | T48: =RANK(AC48,AC:AC) -> 47 | U48: =Y48+Z48+AA48+AB48+AC48 -> 0 | W48: 0 | Y48: =IFERROR(VALUE(LEFT(AE48,FIND("(",AE48)-1))+($W48-1)*VALUE(MID(AE48,FIND("+",AE48)+1,FIND(")",AE48)-FIND("+",AE48)-1)),"") -> 0 | Z48: =IFERROR(VALUE(LEFT(AF48,FIND("(",AF48)-1))+($W48-1)*VALUE(MID(AF48,FIND("+",AF48)+1,FIND(")",AF48)-FIND("+",AF48)-1)),"") -> 0 | AA48: =IFERROR(VALUE(LEFT(AG48,FIND("(",AG48)-1))+($W48-1)*VALUE(MID(AG48,FIND("+",AG48)+1,FIND(")",AG48)-FIND("+",AG48)-1)),"") -> 0 | AB48: =IFERROR(VALUE(LEFT(AH48,FIND("(",AH48)-1))+($W48-1)*VALUE(MID(AH48,FIND("+",AH48)+1,FIND(")",AH48)-FIND("+",AH48)-1)),"") -> 0 | AC48: =IFERROR(VALUE(LEFT(AI48,FIND("(",AI48)-1))+($W48-1)*VALUE(MID(AI48,FIND("+",AI48)+1,FIND(")",AI48)-FIND("+",AI48)-1)),"") -> 0 | AE48: =IFERROR(VLOOKUP($A48,全人物技能说明!$A$1:$O$99,9,FALSE),"") -> 0(+0) | AF48: =IFERROR(VLOOKUP($A48,全人物技能说明!$A$1:$O$99,10,FALSE),"") -> 0(+0) | AG48: =IFERROR(VLOOKUP($A48,全人物技能说明!$A$1:$O$99,11,FALSE),"") -> 0(+0) | AH48: =IFERROR(VLOOKUP($A48,全人物技能说明!$A$1:$O$99,12,FALSE),"") -> 0(+0) | AI48: =IFERROR(VLOOKUP($A48,全人物技能说明!$A$1:$O$99,13,FALSE),"") -> 0(+0)
M49: =IFERROR(IF(VLOOKUP($A49,全人物技能说明!$A$1:$O$99,7,FALSE)<>"",VLOOKUP($A49,全人物技能说明!$A$1:$O$99,7,FALSE),""),"")
M50: =IFERROR(IF(VLOOKUP($A50,全人物技能说明!$A$1:$O$99,7,FALSE)<>"",VLOOKUP($A50,全人物技能说明!$A$1:$O$99,7,FALSE),""),"")
M51: =IFERROR(IF(VLOOKUP($A51,全人物技能说明!$A$1:$O$99,7,FALSE)<>"",VLOOKUP($A51,全人物技能说明!$A$1:$O$99,7,FALSE),""),"")
M52: =IFERROR(IF(VLOOKUP($A52,全人物技能说明!$A$1:$O$99,7,FALSE)<>"",VLOOKUP($A52,全人物技能说明!$A$1:$O$99,7,FALSE),""),"")
M53: =IFERROR(IF(VLOOKUP($A53,全人物技能说明!$A$1:$O$99,7,FALSE)<>"",VLOOKUP($A53,全人物技能说明!$A$1:$O$99,7,FALSE),""),"")
M54: =IFERROR(IF(VLOOKUP($A54,全人物技能说明!$A$1:$O$99,7,FALSE)<>"",VLOOKUP($A54,全人物技能说明!$A$1:$O$99,7,FALSE),""),"")
M55: =IFERROR(IF(VLOOKUP($A55,全人物技能说明!$A$1:$O$99,7,FALSE)<>"",VLOOKUP($A55,全人物技能说明!$A$1:$O$99,7,FALSE),""),"")
M56: =IFERROR(IF(VLOOKUP($A56,全人物技能说明!$A$1:$O$99,7,FALSE)<>"",VLOOKUP($A56,全人物技能说明!$A$1:$O$99,7,FALSE),""),"")
M57: =IFERROR(IF(VLOOKUP($A57,全人物技能说明!$A$1:$O$99,7,FALSE)<>"",VLOOKUP($A57,全人物技能说明!$A$1:$O$99,7,FALSE),""),"")
M58: =IFERROR(IF(VLOOKUP($A58,全人物技能说明!$A$1:$O$99,7,FALSE)<>"",VLOOKUP($A58,全人物技能说明!$A$1:$O$99,7,FALSE),""),"")
M59: =IFERROR(IF(VLOOKUP($A59,全人物技能说明!$A$1:$O$99,7,FALSE)<>"",VLOOKUP($A59,全人物技能说明!$A$1:$O$99,7,FALSE),""),"")
H79: 使用 Kim+Judith+Pink 搭配喷火器
H80: 锁死姐妹 = Kim, Judith, Pink, Sibyl
H81: 锁死姐妹（金姆、朱迪斯夫人、粉红、西比尔）即锁死敌人
H82: 金姆和朱迪斯有 flamers，粉红有斧头因为她工作在财政部
H83: 锁死姐妹队是 kim，judith，pink，使用火焰喷射器以最快技能使用速度
H85: 尖刺队是帕姆爆发流和 liza 或 notlaracroft，使用武士刀以最大化深度
H86: 帕姆爆发流（帕姆一，帕姆二，一个随机）
H88: 步骤 1：使用帕姆爆发流和一个眩晕技能（粉色最肉，但任何都可以）并获胜
H89: 步骤 2：如果你不小心没赢，重新加载游戏，用最低速度和金卡+朱迪斯+粉色对战同一个对手并获胜
H99: 4 攻击敏捷（辅助技能）：锋利砍刀
H100: 2 攻击敏捷（DPS 技能）：武士刀
H101: 4 攻击意志（辅助技能）：精准激光手枪
... H206: 正确。伊尔玛的顶部和底部 A 和 I 都出奇地高，所以她很适合这个

Sheet 全人物技能说明
A1: 姓名 (Name) | B1: 姓名 (中文) | C1: 出场/获取 | D1: 稀有度(中文) | E1: 主动技能名称 | F1: Skill Description (原文) | G1: 装备备注 | H1: 技能描述 (修正) | I1: W | J1: A | K1: I | L1: F | M1: U | N1: 最佳属性 | O1: 最差属性 | P1: 备注 | S1: W | T1: A | U1: I | V1: F | W1: U | X1: 最佳属性 | Y1: 最差属性
A2: ______ | C2: Y隔断 | I2: 0(+0) | J2: 0(+0) | K2: 0(+0) | L2: 0(+0) | M2: 0(+0) | N2: ______ | O2: ______ | U2: Green | V2: Red | W2: Green | X2: {=_xlfn.TEXTJOIN(", ",TRUE,IF(VALUE(LEFT(I2:M2,2))=MAX(VALUE(LEFT(I2:M2,2))),$I$1:$M$1,""))} -> #VALUE! | Y2: {=_xlfn.TEXTJOIN(", ",TRUE,IF(VALUE(LEFT(I2:M2,2))=MIN(VALUE(LEFT(I2:M2,2))),$I$1:$M$1,""))} -> #VALUE!
A3: _+++ | B3: _+++ | C3: za | D3: _+++ | E3: _+++ | F3: _+++ | G3: _+++ | H3: _+++ | I3: 0(+0) | J3: 0(+0) | K3: 0(+0) | L3: 0(+0) | M3: 0(+0) | N3: _+++ | O3: _+++ | P3: _+++ | S3: Green | T3: Yellow | U3: Green | V3: Red | W3: Red | X3: =_xlfn.TEXTJOIN(", ",TRUE,IF(VALUE(LEFT(I3:M3,2))=MAX(VALUE(LEFT(I3:M3,2))),$I$1:$M$1,"")) -> #VALUE! | Y3: {=_xlfn.TEXTJOIN(", ",TRUE,IF(VALUE(LEFT(I3:M3,2))=MIN(VALUE(LEFT(I3:M3,2))),$I$1:$M$1,""))} -> #VALUE!
A4: Adah | B4: 阿达 | S4: Red | T4: Green | U4: Yellow | V4: Red | W4: Yellow | X4: {=_xlfn.TEXTJOIN(", ",TRUE,IF(VALUE(LEFT(I4:M4,2))=MAX(VALUE(LEFT(I4:M4,2))),$I$1:$M$1,""))} -> #VALUE! | Y4: {=_xlfn.TEXTJOIN(", ",TRUE,IF(VALUE(LEFT(I4:M4,2))=MIN(VALUE(LEFT(I4:M4,2))),$I$1:$M$1,""))} -> #VALUE!
A5: Adelaine | B5: 阿德莱恩 | G5: 攻速倒数第一，成长高每级+14的A，使用X2近战武士刀8次 | H5: 随机敌人，每个造成36点伤害，忽略所有防御。 | I5: 54(+8) | J5: 72(+14) | K5: 60(+9) | L5: 72(+14) | M5: 54(+8) | P5: 无视护甲 | S5: Red | T5: Yellow | U5: Red | V5: Yellow | W5: Yellow | X5: {=_xlfn.TEXTJOIN(", ",TRUE,IF(VALUE(LEFT(I5:M5,2))=MAX(VALUE(LEFT(I5:M5,2))),$I$1:$M$1,""))} -> A, F | Y5: {=_xlfn.TEXTJOIN(", ",TRUE,IF(VALUE(LEFT(I5:M5,2))=MIN(VALUE(LEFT(I5:M5,2))),$I$1:$M$1,""))} -> W, U
A6: Allura | B6: 阿露拉 | C6: 6箱子 | D6: 传说 | E6: Cosmic Precognition | F6: Increases the damage of the next 2 attacks by 300%. Ready at the start of combat. | H6: 使下 2 次攻击的伤害提升 300%。战斗开始时即就绪。 | I6: 72(+14) | J6: 66(+11) | K6: 72(+14) | L6: 54(+8) | M6: 48(+7) | N6: W, I | O6: U | U6: Green | V6: Yellow | W6: Yellow | X6: {=_xlfn.TEXTJOIN(", ",TRUE,IF(VALUE(LEFT(I6:M6,2))=MAX(VALUE(LEFT(I6:M6,2))),$I$1:$M$1,""))} -> W, I | Y6: {=_xlfn.TEXTJOIN(", ",TRUE,IF(VALUE(LEFT(I6:M6,2))=MIN(VALUE(LEFT(I6:M6,2))),$I$1:$M$1,""))} -> U
A7: Amelia | B7: 阿米莉亚 | C7: 5剧情 | D7: 史诗 | E7: A(lmost)melia | F7: Creates a decoy version of herself with [50% HP] health and [100% DPS] defense that taunts enemies up to 2 seconds. | H7: 创造一个诱饵分身（继承 [50% HP] 和 [100% DPS] 的防御），嘲讽敌人最多 2 秒。 | I7: 38(+5) | J7: 54(+8) | K7: 54(+8) | L7: 48(+7) | M7: 48(+7) | N7: A, I | O7: W | S7: Red | T7: Yellow | U7: Yellow | V7: Green | W7: Red | X7: {=_xlfn.TEXTJOIN(", ",TRUE,IF(VALUE(LEFT(I7:M7,2))=MAX(VALUE(LEFT(I7:M7,2))),$I$1:$M$1,""))} -> A, I | Y7: {=_xlfn.TEXTJOIN(", ",TRUE,IF(VALUE(LEFT(I7:M7,2))=MIN(VALUE(LEFT(I7:M7,2))),$I$1:$M$1,""))} -> W
A8: Andrea | B8: 安德烈亚 | C8: 1剧情 | D8: 稀有 | E8: ELDI Infusion | F8: Heal 2 lowest health allies by 10% of their Max HP + [15% INT]. | G8: 高电压电击枪（I 类武器伤害最高） | H8: 为 2 名血量最低的队友回复 10% 最大生命值 + [15% INT]。 | I8: 38(+5) | J8: 42(+6) | K8: 48(+7) | L8: 38(+5) | M8: 42(+6) | N8: I | O8: W, F | S8: Red | T8: Green | U8: Green | V8: Yellow | W8: Green | X8: {=_xlfn.TEXTJOIN(", ",TRUE,IF(VALUE(LEFT(I8:M8,2))=MAX(VALUE(LEFT(I8:M8,2))),$I$1:$M$1,""))} -> I | Y8: {=_xlfn.TEXTJOIN(", ",TRUE,IF(VALUE(LEFT(I8:M8,2))=MIN(VALUE(LEFT(I8:M8,2))),$I$1:$M$1,""))} -> W, F
A9: Ann | B9: 安 | C9: 3箱子 | D9: 稀有 | E9: 3-Star Chef | F9: Give a delicious meal to up to 2 lowest health allies, healing them by [20% AGI] and increasing armor 50% for 4 turns. | G9: X2武士刀，4次。X4匕首7次 | H9: 为最多 2 名血量最低的队友提供美食，回复 [20% AGI] 生命值，并在 4 回合内提升 50% 护甲。 | I9: 38(+5) | J9: 42(+6) | K9: 38(+5) | L9: 42(+6) | M9: 48(+7) | N9: U | O9: W, I | S9: Red | T9: Yellow | U9: Red | V9: Yellow | W9: Red | X9: {=_xlfn.TEXTJOIN(", ",TRUE,IF(VALUE(LEFT(I9:M9,2))=MAX(VALUE(LEFT(I9:M9,2))),$I$1:$M$1,""))} -> U | Y9: {=_xlfn.TEXTJOIN(", ",TRUE,IF(VALUE(LEFT(I9:M9,2))=MIN(VALUE(LEFT(I9:M9,2))),$I$1:$M$1,""))} -> W, I
A10: Ashley | B10: 艾希莉 | C10: 5箱子 | D10: 传说 | E10: Amp It Up | F10: Increases damage of next 2 attacks by 200%. Ready at the start of combat. | G10: 无论是近战还是远程攻击，都需要 4 次攻击 | H10: 使下 2 次攻击的伤害提升 200%。战斗开始时即就绪。 | I10: 38(+5) | J10: 48(+7) | K10: 32(+4) | L10: 42(+6) | M10: 48(+7) | N10: A, U | O10: I | S10: Red | T10: Yellow | U10: Yellow | V10: Green | W10: Green | X10: {=_xlfn.TEXTJOIN(", ",TRUE,IF(VALUE(LEFT(I10:M10,2))=MAX(VALUE(LEFT(I10:M10,2))),$I$1:$M$1,""))} -> A, U | Y10: {=_xlfn.TEXTJOIN(", ",TRUE,IF(VALUE(LEFT(I10:M10,2))=MIN(VALUE(LEFT(I10:M10,2))),$I$1:$M$1,""))} -> I
A11: Autumn | B11: 奥特姆 | C11: 8专属 | D11: 传说 | E11: Season Shift | F11: Reducing Damage of up to 4 enemies by 30% while increasing the damage of all allies by 30% for 2 turns. | H11: 在 2 回合内降低最多 4 名敌人 30% 的伤害，同时提升全体队友 30% 的伤害。 | I11: 60(+9) | J11: 60(+9) | K11: 72(+14) | L11: 60(+9) | M11: 66(+11) | N11: I | O11: W, A, F | S11: Red | T11: Yellow | U11: Green | V11: Green | W11: Red | X11: {=_xlfn.TEXTJOIN(", ",TRUE,IF(VALUE(LEFT(I11:M11,2))=MAX(VALUE(LEFT(I11:M11,2))),$I$1:$M$1,""))} -> I | Y11: {=_xlfn.TEXTJOIN(", ",TRUE,IF(VALUE(LEFT(I11:M11,2))=MIN(VALUE(LEFT(I11:M11,2))),$I$1:$M$1,""))} -> W, A, F
A12: Banka | B12: 班卡 | C12: 8专属 | D12: 传说 | E12: Teasing Bubbling | F12: Taunts enemies for 3 turns, reducing damage taken from their attacks by 40%. | H12: 嘲讽敌人 3 回合，减少 40% 所受到的伤害。 | I12: 54(+8) | J12: 66(+11) | K12: 60(+9) | L12: 66(+11) | M12: 72(+14) | N12: U | O12: W | S12: Red | T12: Yellow | U12: Yellow | V12: Yellow | W12: Yellow | X12: {=_xlfn.TEXTJOIN(", ",TRUE,IF(VALUE(LEFT(I12:M12,2))=MAX(VALUE(LEFT(I12:M12,2))),$I$1:$M$1,""))} -> U | Y12: {=_xlfn.TEXTJOIN(", ",TRUE,IF(VALUE(LEFT(I12:M12,2))=MIN(VALUE(LEFT(I12:M12,2))),$I$1:$M$1,""))} -> W
A13: Beatrix | B13: 碧翠丝 | C13: 4剧情 | D13: 传说 | E13: Due Punishment | F13: Exposes herself, taunting for 3 turns, reducing damage taken by 50%. | H13: 展露自我，嘲讽敌人 3 回合，减少 50% 所受到的伤害。 | I13: 48(+7) | J13: 40(+6) | K13: 54(+8) | L13: 60(+9) | M13: 66(+11) | N13: U | O13: A | S13: Red | T13: Yellow | U13: Green | V13: Green | W13: Green | X13: {=_xlfn.TEXTJOIN(", ",TRUE,IF(VALUE(LEFT(I13:M13,2))=MAX(VALUE(LEFT(I13:M13,2))),$I$1:$M$1,""))} -> U | Y13: {=_xlfn.TEXTJOIN(", ",TRUE,IF(VALUE(LEFT(I13:M13,2))=MIN(VALUE(LEFT(I13:M13,2))),$I$1:$M$1,""))} -> A
A14: Carmilla | B14: 卡米拉 | I14: 66(+11) | J14: 72(+14) | K14: 60(+9) | L14: 60(+9) | M14: 60(+9) | S14: Red | T14: Yellow | U14: Green | V14: Green | W14: Yellow | X14: {=_xlfn.TEXTJOIN(", ",TRUE,IF(VALUE(LEFT(I14:M14,2))=MAX(VALUE(LEFT(I14:M14,2))),$I$1:$M$1,""))} -> A | Y14: {=_xlfn.TEXTJOIN(", ",TRUE,IF(VALUE(LEFT(I14:M14,2))=MIN(VALUE(LEFT(I14:M14,2))),$I$1:$M$1,""))} -> I, F, U
A15: Catherine | B15: 凯瑟琳 | I15: 60(+9) | J15: 72(+14) | K15: 60(+9) | L15: 72(+14) | M15: 48(+7) | S15: Green | T15: Red | U15: Red | V15: Yellow | W15: Yellow | X15: {=_xlfn.TEXTJOIN(", ",TRUE,IF(VALUE(LEFT(I15:M15,2))=MAX(VALUE(LEFT(I15:M15,2))),$I$1:$M$1,""))} -> A, F | Y15: {=_xlfn.TEXTJOIN(", ",TRUE,IF(VALUE(LEFT(I15:M15,2))=MIN(VALUE(LEFT(I15:M15,2))),$I$1:$M$1,""))} -> U
A16: CB-69 | B16: CB-69（技能快 | I16: 66(+11) | J16: 66(+11) | K16: 60(+9) | L16: 66(+11) | M16: 66(+11) | S16: Green | T16: Red | U16: Green | V16: Red | W16: Red | X16: {=_xlfn.TEXTJOIN(", ",TRUE,IF(VALUE(LEFT(I16:M16,2))=MAX(VALUE(LEFT(I16:M16,2))),$I$1:$M$1,""))} -> W, A, F, U | Y16: {=_xlfn.TEXTJOIN(", ",TRUE,IF(VALUE(LEFT(I16:M16,2))=MIN(VALUE(LEFT(I16:M16,2))),$I$1:$M$1,""))} -> I
A17: Chelsea | B17: 切尔西 | C17: 8专属 | D17: 传说 | E17: Suffocating Hips | F17: Instantly attack weakest enemy, dealing [30% DPS] damage. | H17: 立即攻击最虚弱的敌人，造成 [30% DPS] 伤害。 | I17: 54(+8) | J17: 72(+14) | K17: 66(+11) | L17: 60(+9) | M17: 66(+11) | N17: A | O17: W | S17: Yellow | T17: Red | U17: Red | V17: Yellow | W17: Green | X17: {=_xlfn.TEXTJOIN(", ",TRUE,IF(VALUE(LEFT(I17:M17,2))=MAX(VALUE(LEFT(I17:M17,2))),$I$1:$M$1,""))} -> A | Y17: {=_xlfn.TEXTJOIN(", ",TRUE,IF(VALUE(LEFT(I17:M17,2))=MIN(VALUE(LEFT(I17:M17,2))),$I$1:$M$1,""))} -> W
A18: Cloe | B18: 克洛伊 | C18: 1箱子 | D18: 史诗 | E18: Short Fuse | F18: Throws dynamite at 2 enemies, dealing [75% DPS] damage to them. | H18: 向 2 名敌人投掷炸药，造成 [75% DPS] 伤害。 | I18: 44(+6) | J18: 54(+8) | K18: 66(+11) | L18: 54(+8) | M18: 54(+8) | N18: I | O18: W | S18: Green | T18: Red | U18: Yellow | V18: Red | W18: Green | X18: {=_xlfn.TEXTJOIN(", ",TRUE,IF(VALUE(LEFT(I18:M18,2))=MAX(VALUE(LEFT(I18:M18,2))),$I$1:$M$1,""))} -> I | Y18: {=_xlfn.TEXTJOIN(", ",TRUE,IF(VALUE(LEFT(I18:M18,2))=MIN(VALUE(LEFT(I18:M18,2))),$I$1:$M$1,""))} -> W
A19: Crazy | B19: 疯狂 | C19: 1箱子 | D19: 稀有 | E19: Bombs for Everyone | F19: Throws bombs at up to 4 enemies, dealing [75% DPS] damage to them. | H19: 向最多 4 名敌人投掷炸弹，造成 [75% DPS] 伤害。 | I19: 50(+7) | J19: 66(+11) | K19: 54(+8) | L19: 54(+8) | M19: 50(+7) | N19: A | O19: W, U | S19: Green | T19: Green | U19: Red | V19: Red | W19: Red | X19: {=_xlfn.TEXTJOIN(", ",TRUE,IF(VALUE(LEFT(I19:M19,2))=MAX(VALUE(LEFT(I19:M19,2))),$I$1:$M$1,""))} -> A | Y19: {=_xlfn.TEXTJOIN(", ",TRUE,IF(VALUE(LEFT(I19:M19,2))=MIN(VALUE(LEFT(I19:M19,2))),$I$1:$M$1,""))} -> W, U
A20: Dahia | B20: 达希亚 | I20: 48(+7) | J20: 48(+7) | K20: 60(+9) | L20: 60(+9) | M20: 60(+9) | P20: 团队增益 | S20: Green | T20: Yellow | U20: Yellow | V20: Green | W20: Green | X20: {=_xlfn.TEXTJOIN(", ",TRUE,IF(VALUE(LEFT(I20:M20,2))=MAX(VALUE(LEFT(I20:M20,2))),$I$1:$M$1,""))} -> I, F, U | Y20: {=_xlfn.TEXTJOIN(", ",TRUE,IF(VALUE(LEFT(I20:M20,2))=MIN(VALUE(LEFT(I20:M20,2))),$I$1:$M$1,""))} -> W, A
A21: Desiderata | B21: 德西德拉塔 | I21: 60(+9) | J21: 72(+14) | K21: 60(+9) | L21: 66(+11) | M21: 60(+9) | S21: Yellow | T21: Green | U21: Yellow | V21: Red | W21: Green | X21: {=_xlfn.TEXTJOIN(", ",TRUE,IF(VALUE(LEFT(I21:M21,2))=MAX(VALUE(LEFT(I21:M21,2))),$I$1:$M$1,""))} -> A | Y21: {=_xlfn.TEXTJOIN(", ",TRUE,IF(VALUE(LEFT(I21:M21,2))=MIN(VALUE(LEFT(I21:M21,2))),$I$1:$M$1,""))} -> W, I, U
A22: Devi | B22: 黛维 | C22: 8剧情 | D22: 史诗 | E22: Snipe | F22: Attacks her current target, dealing [350% DMG] damage. | G22: 攻速倒数第二 | H22: 攻击当前目标，造成 [350% DMG] 伤害。 | I22: 60(+9) | J22: 40(+6) | K22: 60(+9) | L22: 54(+8) | M22: 60(+9) | N22: W, I, U | O22: A | S22: Green | T22: Yellow | U22: Green | V22: Green | W22: Green | X22: {=_xlfn.TEXTJOIN(", ",TRUE,IF(VALUE(LEFT(I22:M22,2))=MAX(VALUE(LEFT(I22:M22,2))),$I$1:$M$1,""))} -> W, I, U | Y22: {=_xlfn.TEXTJOIN(", ",TRUE,IF(VALUE(LEFT(I22:M22,2))=MIN(VALUE(LEFT(I22:M22,2))),$I$1:$M$1,""))} -> A
A23: Diana | B23: 黛安娜 | C23: 7箱子 | D23: 稀有 | E23: Last Stand | F23: Regain vigor, healing herself [25% HP] and gaining [125% DEF] defense for 2 turns. | G23: 鱼叉枪（W 和 F 属性第二高，U 属性中等，但在 W 属性链中这是最好的防御选择） | H23: 恢复活力，回复自身 [25% HP] 并在 2 回合内获得 [125% DEF] 防御加成。 | I23: 66(+11) | J23: 48(+7) | K23: 48(+7) | L23: 54(+8) | M23: 54(+8) | N23: W | O23: A, I | S23: Yellow | T23: Green | U23: Yellow | V23: Green | W23: Green | X23: {=_xlfn.TEXTJOIN(", ",TRUE,IF(VALUE(LEFT(I23:M23,2))=MAX(VALUE(LEFT(I23:M23,2))),$I$1:$M$1,""))} -> W | Y23: {=_xlfn.TEXTJOIN(", ",TRUE,IF(VALUE(LEFT(I23:M23,2))=MIN(VALUE(LEFT(I23:M23,2))),$I$1:$M$1,""))} -> A, I
A24: Eleanor | B24: 埃莉诺 | C24: 8专属 | D24: 传说 | E24: Scandinavian Defence | F24: For 3 turns reduces all enemies damage and defences by 20% while boosting all allies damage by 30%. | H24: 在 3 回合内降低全体敌人 20% 的伤害和防御，同时提升全体队友 30% 的伤害。 | I24: 60(+9) | J24: 48(+7) | K24: 72(+14) | L24: 60(+9) | M24: 72(+14) | N24: I, U | O24: A | S24: Green | T24: Green | U24: Yellow | V24: Green | W24: Red | X24: {=_xlfn.TEXTJOIN(", ",TRUE,IF(VALUE(LEFT(I24:M24,2))=MAX(VALUE(LEFT(I24:M24,2))),$I$1:$M$1,""))} -> I, U | Y24: {=_xlfn.TEXTJOIN(", ",TRUE,IF(VALUE(LEFT(I24:M24,2))=MIN(VALUE(LEFT(I24:M24,2))),$I$1:$M$1,""))} -> A
A25: Emily | B25: 艾米莉 | C25: 7剧情 | D25: 史诗 | E25: Cull The Weak | F25: Jump on the weakest enemy, dealing [250% DPS] damage. | H25: 跳向最虚弱的敌人，造成 [250% DPS] 伤害。 | I25: 72(+14) | J25: 60(+9) | K25: 66(+11) | L25: 54(+8) | M25: 66(+11) | N25: W | O25: F | S25: Green | T25: Green | U25: Green | V25: Red | W25: Red | X25: {=_xlfn.TEXTJOIN(", ",TRUE,IF(VALUE(LEFT(I25:M25,2))=MAX(VALUE(LEFT(I25:M25,2))),$I$1:$M$1,""))} -> W | Y25: {=_xlfn.TEXTJOIN(", ",TRUE,IF(VALUE(LEFT(I25:M25,2))=MIN(VALUE(LEFT(I25:M25,2))),$I$1:$M$1,""))} -> F
A26: Foxy | B26: 福克希 | C26: 4箱子 | D26: 稀有 | E26: Penetrator | F26: Pass a drink to up to 2 lowest health allies, healing them by [20% AGI] and increasing their damage 20% for 2 turns. | H26: 为最多 2 名血量最低的队友递出饮品，回复 [20% AGI] 生命值，并在 2 回合内提升其 20% 伤害。 | I26: 48(+7) | J26: 48(+7) | K26: 48(+7) | L26: 48(+7) | M26: 48(+7) | N26: 全能偏A | S26: Red | T26: Yellow | U26: Yellow | V26: Yellow | W26: Red | X26: {=_xlfn.TEXTJOIN(", ",TRUE,IF(VALUE(LEFT(I26:M26,2))=MAX(VALUE(LEFT(I26:M26,2))),$I$1:$M$1,""))} -> W, A, I, F, U | Y26: {=_xlfn.TEXTJOIN(", ",TRUE,IF(VALUE(LEFT(I26:M26,2))=MIN(VALUE(LEFT(I26:M26,2))),$I$1:$M$1,""))} -> W, A, I, F, U
A27: Frozen | B27: 弗罗赞 | C27: 8专属 | D27: 传说 | E27: Snow Queen | F27: Freeze one enemy with her deadly glare, stunning them for 3 turns and increasing their damage taken by 50% | H27: 用致命凝视冻结一名敌人，使其眩晕 3 回合，并使其受到的伤害提升 50%。 | I27: 72(+14) | J27: 54(+8) | K27: 60(+9) | L27: 72(+14) | M27: 54(+8) | N27: W, F | O27: A, U | S27: Green | T27: Yellow | U27: Green | V27: Yellow | W27: Yellow | X27: {=_xlfn.TEXTJOIN(", ",TRUE,IF(VALUE(LEFT(I27:M27,2))=MAX(VALUE(LEFT(I27:M27,2))),$I$1:$M$1,""))} -> W, F | Y27: {=_xlfn.TEXTJOIN(", ",TRUE,IF(VALUE(LEFT(I27:M27,2))=MIN(VALUE(LEFT(I27:M27,2))),$I$1:$M$1,""))} -> A, U
A28: Gaia | B28: 盖亚 | C28: 4箱子 | D28: 传说 | E28: Natural Selection | F28: Instantly attacks the weakest enemy, dealing [175% DPS] damage. | H28: 立即攻击最虚弱的敌人，造成 [175% DPS] 伤害。 | I28: 45(+6) | J28: 54(+8) | K28: 45(+6) | L28: 54(+8) | M28: 48(+7) | N28: A, F | O28: W, I | S28: Green | T28: Yellow | U28: Red | V28: Yellow | W28: Red | X28: {=_xlfn.TEXTJOIN(", ",TRUE,IF(VALUE(LEFT(I28:M28,2))=MAX(VALUE(LEFT(I28:M28,2))),$I$1:$M$1,""))} -> A, F | Y28: {=_xlfn.TEXTJOIN(", ",TRUE,IF(VALUE(LEFT(I28:M28,2))=MIN(VALUE(LEFT(I28:M28,2))),$I$1:$M$1,""))} -> W, I
A29: Guinevere | B29: 桂妮薇儿 | H29: 攻击1名敌人并造成伤害。恢复19健康。同时，在3回合内，将他们的近战和远程防御降低3%。 | I29: 48(+7) | J29: 60(+9) | K29: 60(+9) | L29: 60(+9) | M29: 48(+7) | S29: Yellow | T29: Yellow | U29: Yellow | V29: Red | W29: Green | X29: {=_xlfn.TEXTJOIN(", ",TRUE,IF(VALUE(LEFT(I29:M29,2))=MAX(VALUE(LEFT(I29:M29,2))),$I$1:$M$1,""))} -> A, I, F | Y29: {=_xlfn.TEXTJOIN(", ",TRUE,IF(VALUE(LEFT(I29:M29,2))=MIN(VALUE(LEFT(I29:M29,2))),$I$1:$M$1,""))} -> W, U
A30: Harriet | B30: 哈里特 | G30: 攻速倒数第三 | I30: 66(+11) | J30: 66(+11) | K30: 54(+8) | L30: 72(+14) | M30: 60(+9) | S30: Green | T30: Red | U30: Yellow | V30: Yellow | W30: Yellow | X30: {=_xlfn.TEXTJOIN(", ",TRUE,IF(VALUE(LEFT(I30:M30,2))=MAX(VALUE(LEFT(I30:M30,2))),$I$1:$M$1,""))} -> F | Y30: {=_xlfn.TEXTJOIN(", ",TRUE,IF(VALUE(LEFT(I30:M30,2))=MIN(VALUE(LEFT(I30:M30,2))),$I$1:$M$1,""))} -> I
A31: Irma | B31: 厄玛 | C31: 1箱子 | D31: 传说 | E31: Bear With Me | F31: Throws bear traps under the legs of 3 enemies, dealing [100% DPS] damage to each. | G31: UA为核心。X2武士刀，4次。X4匕首8次 | H31: 在 3 名敌人脚下投掷捕兽夹，对每人造成 [100% DPS] 伤害。 | I31: 66(+11) | J31: 66(+11) | K31: 66(+11) | L31: 60(+9) | M31: 66(+11) | N31: 全能A | O31: F | S31: Red | T31: Yellow | U31: Red | V31: Green | W31: Red | X31: {=_xlfn.TEXTJOIN(", ",TRUE,IF(VALUE(LEFT(I31:M31,2))=MAX(VALUE(LEFT(I31:M31,2))),$I$1:$M$1,""))} -> W, A, I, U | Y31: {=_xlfn.TEXTJOIN(", ",TRUE,IF(VALUE(LEFT(I31:M31,2))=MIN(VALUE(LEFT(I31:M31,2))),$I$1:$M$1,""))} -> F
A32: Jane | B32: 简 | C32: 1剧情 | D32: 史诗 | E32: Fired Up | F32: Increases damage of next 2 attacks by 200%. Ready at the start of combat. | G32: 无论是近战还是远程攻击，都需要 4 次攻击 | H32: 使下 2 次攻击的伤害提升 200%。战斗开始时即就绪。 | I32: 42(+6) | J32: 48(+7) | K32: 38(+5) | L32: 48(+7) | M32: 32(+4) | N32: A, F | O32: U | S32: Green | T32: Yellow | U32: Green | V32: Green | W32: Green | X32: {=_xlfn.TEXTJOIN(", ",TRUE,IF(VALUE(LEFT(I32:M32,2))=MAX(VALUE(LEFT(I32:M32,2))),$I$1:$M$1,""))} -> A, F | Y32: {=_xlfn.TEXTJOIN(", ",TRUE,IF(VALUE(LEFT(I32:M32,2))=MIN(VALUE(LEFT(I32:M32,2))),$I$1:$M$1,""))} -> U
A33: Jasmine | B33: 茉莉 | I33: 72(+14) | J33: 66(+11) | K33: 60(+9) | L33: 66(+11) | M33: 60(+9) | S33: Red | T33: Yellow | U33: Green | V33: Green | W33: Green | X33: {=_xlfn.TEXTJOIN(", ",TRUE,IF(VALUE(LEFT(I33:M33,2))=MAX(VALUE(LEFT(I33:M33,2))),$I$1:$M$1,""))} -> W | Y33: {=_xlfn.TEXTJOIN(", ",TRUE,IF(VALUE(LEFT(I33:M33,2))=MIN(VALUE(LEFT(I33:M33,2))),$I$1:$M$1,""))} -> I, U
A34: Karin | B34: 卡琳 | C34: 1箱子 | D34: 稀有 | E34: Wonder Who? | F34: Regain vigor, healing [35% HP] and gaining [130% DEF] defense for 2 turns. | G34: 重管，围绕A因为那条分支上AFU。重管在 A、F和U方面的属性是第二高 | H34: 恢复活力，回复 [35% HP] 并在 2 回合内获得 [130% DEF] 防御加成。 | I34: 54(+8) | J34: 54(+8) | K34: 44(+6) | L34: 48(+7) | M34: 44(+6) | N34: W, A | O34: I, U | S34: Green | T34: Red | U34: Green | V34: Red | W34: Red | X34: {=_xlfn.TEXTJOIN(", ",TRUE,IF(VALUE(LEFT(I34:M34,2))=MAX(VALUE(LEFT(I34:M34,2))),$I$1:$M$1,""))} -> W, A | Y34: {=_xlfn.TEXTJOIN(", ",TRUE,IF(VALUE(LEFT(I34:M34,2))=MIN(VALUE(LEFT(I34:M34,2))),$I$1:$M$1,""))} -> I, U
A35: Kiara | B35: 琪亚拉 | C35: 4箱子 | D35: 史诗 | E35: Lioness' Order | F35: Command 1 ally to attack one enemy instantaneously. | H35: 指挥 1 名队友瞬间攻击一名敌人。 | I35: 54(+8) | J35: 54(+8) | K35: 45(+6) | L35: 54(+8) | M35: 38(+5) | N35: W, A, F | O35: U | S35: Yellow | T35: Green | U35: Yellow | V35: Red | W35: Yellow | X35: {=_xlfn.TEXTJOIN(", ",TRUE,IF(VALUE(LEFT(I35:M35,2))=MAX(VALUE(LEFT(I35:M35,2))),$I$1:$M$1,""))} -> W, A, F | Y35: {=_xlfn.TEXTJOIN(", ",TRUE,IF(VALUE(LEFT(I35:M35,2))=MIN(VALUE(LEFT(I35:M35,2))),$I$1:$M$1,""))} -> U
A36: Kim | B36: 金 | C36: 2箱子 | D36: 稀有 | E36: Fatalistic Prophocies | F36: Read from a depressing masterpiece, stunning up to 4 enemies for 2 turns. | G36: X4或X2武器7次，远X4八次。喷火8次。X4近锋利砍刀单次伤最高，穿甲 | H36: 阅读忧郁杰作，使最多 4 名敌人眩晕 2 回合。 | I36: 44(+6) | J36: 54(+8) | K36: 60(+9) | L36: 60(+9) | M36: 60(+9) | N36: I, F, U | O36: W | S36: Green | T36: Green | U36: Yellow | V36: Yellow | W36: Yellow | X36: {=_xlfn.TEXTJOIN(", ",TRUE,IF(VALUE(LEFT(I36:M36,2))=MAX(VALUE(LEFT(I36:M36,2))),$I$1:$M$1,""))} -> I, F, U | Y36: {=_xlfn.TEXTJOIN(", ",TRUE,IF(VALUE(LEFT(I36:M36,2))=MIN(VALUE(LEFT(I36:M36,2))),$I$1:$M$1,""))} -> W
A37: Kriss | B37: 克丽丝 | I37: 60(+9) | J37: 48(+7) | K37: 66(+11) | L37: 54(+8) | M37: 40(+6) | S37: Green | T37: Green | U37: Green | V37: Green | W37: Red | X37: {=_xlfn.TEXTJOIN(", ",TRUE,IF(VALUE(LEFT(I37:M37,2))=MAX(VALUE(LEFT(I37:M37,2))),$I$1:$M$1,""))} -> I | Y37: {=_xlfn.TEXTJOIN(", ",TRUE,IF(VALUE(LEFT(I37:M37,2))=MIN(VALUE(LEFT(I37:M37,2))),$I$1:$M$1,""))} -> U
A38: Lady Judith | B38: 朱迪丝 | C38: 4箱子 | D38: 史诗 | E38: Guards! Guards! | F38: Calls bodyguard with [75% HP] and [75% DEF] taunting enemies for up to 2 turns. | G38: 近战X4武器8次攻击，X2稍快，远程x4武器就需要9次 | H38: 召唤保镖（继承 [75% HP] 和 [75% DEF]），嘲讽敌人最多 2 回合。 | I38: 66(+11) | J38: 48(+7) | K38: 66(+11) | L38: 40(+6) | M38: 40(+6) | N38: W, I | O38: F, U | S38: Red | T38: Yellow | U38: Green | V38: Yellow | W38: Yellow | X38: {=_xlfn.TEXTJOIN(", ",TRUE,IF(VALUE(LEFT(I38:M38,2))=MAX(VALUE(LEFT(I38:M38,2))),$I$1:$M$1,""))} -> W, I | Y38: {=_xlfn.TEXTJOIN(", ",TRUE,IF(VALUE(LEFT(I38:M38,2))=MIN(VALUE(LEFT(I38:M38,2))),$I$1:$M$1,""))} -> F, U
A39: Lane | B39: 莱恩 | C39: 3剧情 | D39: 稀有 | E39: Own3d by L33t H4x | F39: Hack enemy equipment, dealing [25% INT] damage to 4 enemies, and reducing damage they deal by 25% for 5 turns. | H39: 骇入敌人装备，对 4 名敌人造成 [25% INT] 伤害，并在 5 回合内减少其 25% 输出伤害。 | I39: 41(+7) | J39: 33(+5) | K39: 41(+7) | L39: 28(+4) | M39: 36(+6) | N39: W, I | O39: F | S39: Green | T39: Red | U39: Yellow | V39: Red | W39: Green | X39: {=_xlfn.TEXTJOIN(", ",TRUE,IF(VALUE(LEFT(I39:M39,2))=MAX(VALUE(LEFT(I39:M39,2))),$I$1:$M$1,""))} -> W, I | Y39: {=_xlfn.TEXTJOIN(", ",TRUE,IF(VALUE(LEFT(I39:M39,2))=MIN(VALUE(LEFT(I39:M39,2))),$I$1:$M$1,""))} -> F
A40: Liza | B40: 丽莎 | C40: 7箱子 | D40: 稀有 | E40: Bug Buzz | F40: Launch a series of 4 attacks, each dealing [90% DPS] damage. | G40: 近战X2武士刀，4次 | H40: 发动 4 连击，每次攻击造成 [90% DPS] 伤害。 | I40: 48(+7) | J40: 38(+7) | K40: 42(+7) | L40: 38(+8) | M40: 42(+6) | N40: W | O40: A, F | U40: Green | V40: Yellow | W40: Red | X40: {=_xlfn.TEXTJOIN(", ",TRUE,IF(VALUE(LEFT(I40:M40,2))=MAX(VALUE(LEFT(I40:M40,2))),$I$1:$M$1,""))} -> W | Y40: {=_xlfn.TEXTJOIN(", ",TRUE,IF(VALUE(LEFT(I40:M40,2))=MIN(VALUE(LEFT(I40:M40,2))),$I$1:$M$1,""))} -> A, F
A41: Makeda | B41: 马基达 | I41: 72(+14) | J41: 48(+7) | K41: 60(+9) | L41: 60(+9) | M41: 72(+14) | S41: Green | T41: Yellow | U41: Green | V41: Green | W41: Yellow | X41: {=_xlfn.TEXTJOIN(", ",TRUE,IF(VALUE(LEFT(I41:M41,2))=MAX(VALUE(LEFT(I41:M41,2))),$I$1:$M$1,""))} -> W, U | Y41: {=_xlfn.TEXTJOIN(", ",TRUE,IF(VALUE(LEFT(I41:M41,2))=MIN(VALUE(LEFT(I41:M41,2))),$I$1:$M$1,""))} -> A
A42: Maria | B42: 玛丽亚 | C42: 8箱子 | D42: 稀有 | E42: Soothing Hands | F42: Heal 2 lowest health allies by 10% of their Max HP + [20% INT]. | H42: 为 2 名血量最低的队友回复 10% 最大生命值 + [20% INT]。 | I42: 60(+9) | J42: 40(+6) | K42: 54(+8) | L42: 48(+7) | M42: 66(+11) | N42: U | O42: A | S42: Yellow | T42: Red | U42: Yellow | V42: Red | W42: Green | X42: {=_xlfn.TEXTJOIN(", ",TRUE,IF(VALUE(LEFT(I42:M42,2))=MAX(VALUE(LEFT(I42:M42,2))),$I$1:$M$1,""))} -> U | Y42: {=_xlfn.TEXTJOIN(", ",TRUE,IF(VALUE(LEFT(I42:M42,2))=MIN(VALUE(LEFT(I42:M42,2))),$I$1:$M$1,""))} -> A
A43: Martha | B43: 玛莎 | C43: 1箱子 | D43: 稀有 | E43: Sweet Nothings | F43: Taunts enemies for 2 turns, showering them with gossip. Reduce damage taken from their attacks by 70%. | G43: 使用管武器需要5次攻击 | H43: 嘲讽敌人 2 回合；减少 70% 所受到的伤害。 | I43: 38(+5) | J43: 42(+6) | K43: 38(+5) | L43: 42(+6) | M43: 48(+7) | N43: U | O43: W, I | S43: Red | T43: Green | U43: Yellow | V43: Red | W43: Yellow | X43: {=_xlfn.TEXTJOIN(", ",TRUE,IF(VALUE(LEFT(I43:M43,2))=MAX(VALUE(LEFT(I43:M43,2))),$I$1:$M$1,""))} -> U | Y43: {=_xlfn.TEXTJOIN(", ",TRUE,IF(VALUE(LEFT(I43:M43,2))=MIN(VALUE(LEFT(I43:M43,2))),$I$1:$M$1,""))} -> W, I
A44: Martina | B44: 玛蒂娜 | C44: 1剧情 | D44: 普通 | E44: Taste Their Fear | F44: Jump on the weakest enemy, dealing [200% DPS] damage. | H44: 跳向最虚弱的敌人，造成 [200% DPS] 伤害。 | I44: 48(+7) | J44: 32(+4) | K44: 48(+7) | L44: 38(+5) | M44: 42(+6) | N44: W, I | O44: A | S44: Yellow | T44: Red | U44: Green | V44: Red | W44: Green | X44: {=_xlfn.TEXTJOIN(", ",TRUE,IF(VALUE(LEFT(I44:M44,2))=MAX(VALUE(LEFT(I44:M44,2))),$I$1:$M$1,""))} -> W, I | Y44: {=_xlfn.TEXTJOIN(", ",TRUE,IF(VALUE(LEFT(I44:M44,2))=MIN(VALUE(LEFT(I44:M44,2))),$I$1:$M$1,""))} -> A
A45: Milena | B45: 米莲娜 | I45: 60(+9) | J45: 40(+6) | K45: 40(+120) | L45: 60(+9) | M45: 66(+11) | S45: Red | T45: Green | U45: Red | V45: Green | W45: Yellow | X45: {=_xlfn.TEXTJOIN(", ",TRUE,IF(VALUE(LEFT(I45:M45,2))=MAX(VALUE(LEFT(I45:M45,2))),$I$1:$M$1,""))} -> U | Y45: {=_xlfn.TEXTJOIN(", ",TRUE,IF(VALUE(LEFT(I45:M45,2))=MIN(VALUE(LEFT(I45:M45,2))),$I$1:$M$1,""))} -> A, I
A46: Momoka | B46: 桃香 | C46: 2箱子 | D46: 传说 | E46: Elementary, My Dear | F46: Expose a villain commanding 1 ally to attack them instantly. | H46: 揭发恶徒，指挥 1 名队友立即攻击对方。 | I46: 32(+4) | J46: 38(+5) | K46: 42(+6) | L46: 48(+7) | M46: 48(+7) | N46: F, U | O46: W | S46: Green | T46: Red
A47: Olivia | B47: 奥利维亚 | C47: 5箱子 | D47: 稀有 | E47: Nobody Expects… | F47: Regain [35% HP] health and taunt enemies for 3 turns. | H47: 回复 [35% HP] 生命值并嘲讽敌人 3 回合。 | I47: 72(+14) | J47: 54(+8) | K47: 60(+9) | L47: 66(+11) | M47: 66(+11) | N47: W | O47: A | P47: 最佳嘲讽 | S47: Yellow | T47: Yellow
A48: PAIN | B48: 佩恩 | C48: 5剧情 | D48: 传说 | E48: Whip Into Shape | F48: Whip up to 4 enemies, dealing [30% DPS] damage to each of them. | H48: 鞭笞最多 4 名敌人，各造成 [30% DPS] 伤害。 | I48: 66(+11) | J48: 72(+14) | K48: 60(+9) | L48: 66(+11) | M48: 54(+8) | N48: A | O48: U | S48: Red | T48: Green
A49: PamOne | B49: 帕姆1 | C49: 6剧情 | D49: 史诗 | E49: Synapsis Overload | F49: Launch a series of 4 attacks, each dealing [75% DPS] damage. | G49: 近战X2武士刀，4次 | H49: 发动 4 连击，每次攻击造成 [75% DPS] 伤害。 | I49: 48(+7) | J49: 48(+7) | K49: 48(+7) | L49: 48(+7) | M49: 48(+7) | N49: 全能W
A50: PamTwo | B50: 帕姆2 | C50: 6剧情 | D50: 史诗 | E50: Synapsis Outburst | F50: Launch a series of 2 attacks, each dealing [150% DPS] damage. | G50: 近战X2武士刀，4次 | H50: 发动 2 连击，每次攻击造成 [150% DPS] 伤害。 | I50: 48(+7) | J50: 48(+7) | K50: 48(+7) | L50: 48(+7) | M50: 48(+7) | N50: 全能I
A51: Pearl | B51: 珀尔珍珠 | I51: 60(+9) | J51: 72(+14) | K51: 60(+9) | L51: 66(+11) | M51: 60(+9)
A52: Pink | B52: 粉红 | C52: 8箱子 | D52: 史诗 | E52: Commando Flash | F52: Flashes her pink, stunning all enemies for 1 turn, reducing their defenses by [15% ?] for next 2 incoming attacks. | H52: 展露粉嫩，使全体敌人眩晕1回，并使其在接下来的2次受击中降 [15% ?] 防。 | I52: 54(+8) | J52: 66(+11) | K52: 66(+11) | L52: 72(+14) | M52: 60(+9) | N52: F | O52: W
A53: Reznor | B53: 雷兹诺 | G53: 攻速倒数第三，近战需要 6 次挥击，远程需要 7 次射击 | H53: 她接下来的两次攻击造成 200%的伤害 | I53: 54(+8) | J53: 66(+11) | K53: 60(+9) | L53: 72(+14) | M53: 66(+11)
A54: Rhode | B54: 罗德 | C54: 4剧情 | D54: 史诗 | E54: Rhode-Volver | F54: Launch a series of 5 attacks, each dealing [75% DPS] damage. | H54: 发动 5 连击，每次攻击造成 [75% DPS] 伤害。 | I54: 54(+8) | J54: 45(+6) | K54: 48(+7) | L54: 45(+6) | M54: 54(+8) | N54: W, U | O54: A, F
A55: Samantha | B55: 萨曼莎 | C55: 4箱子 | D55: 稀有 | E55: Trojan Horse | F55: Charm an enemy, stunning them for 2 turns and increasing damage taken by 50% | H55: 魅惑一名敌人，使其眩晕 2 回合，并使其受到的伤害提升 50%。 | I55: 66(+11) | J55: 54(+8) | K55: 54(+8) | L55: 54(+8) | M55: 44(+6) | N55: W | O55: U
A56: Sara | B56: 萨拉 | C56: 2剧情 | D56: 稀有 | E56: Fist of the Free Market | F56: Command 2 allies to instantly attack an enemy. | H56: 指挥 2 名队友立即攻击一名敌人。 | I56: 48(+7) | J56: 44(+6) | K56: 54(+8) | L56: 54(+8) | M56: 44(+6) | N56: I, F | O56: A, U
A57: Sonia | B57: 索尼娅 | C57: 3箱子 | D57: 稀有 | E57: Quick Trigger | F57: Launch a series of 4 attacks, each dealing [75% DPS] damage. | H57: 发动 4 连击，每次攻击造成 [75% DPS] 伤害。 | I57: 42(+6) | J57: 48(+7) | K57: 38(+5) | L57: 42(+6) | M57: 38(+5) | N57: A | O57: I, U
A58: Sophie | B58: 苏菲 | C58: 3剧情 | D58: 史诗 | E58: Love Nectar | F58: Pass a vial to up to 2 lowest health allies, healing them by [20% INT], and increasing their damage by 20% for 2 turns. | H58: 向最多 2 名血量最低的队友递出药剂，回复 [20% INT] 生命值，并在 2 回合内提升其 20% 伤害。 | I58: 42(+6) | J58: 32(+4) | K58: 48(+7) | L58: 38(+5) | M58: 48(+7) | N58: I, U | O58: A
A59: Stella | B59: 斯特拉 | I59: 54(+8) | J59: 60(+9) | K59: 54(+184) | L59: 60(+9) | M59: 48(+7) | P59: 最佳嘲讽
A60: Sybil | B60: 西比尔 | H60: 无法取代朱迪。眩晕所有敌人2回合，并将她接下来3次攻击的伤害增加25%。 | I60: 66(+11) | J60: 72(+14) | K60: 48(+15) | L60: 72(+14) | M60: 54(+8) | N60: A, F | O60: I | P60: 限定最佳 | S60: A工人
A61: Tess | B61: 泰丝 | C61: 3剧情 | D61: 稀有 | E61: One for All | F61: Taunts enemies for 2 turns, reducing damage taken from their attacks by 60%. | G61: Tess嘲讽充能速度最快，用X4要快得多，使用管状武器需要 3 次攻击 | H61: 嘲讽敌人 2 回合，减少 60% 所受到的伤害。 | I61: 44(+6) | J61: 54(+8) | K61: 44(+6) | L61: 48(+7) | M61: 54(+8) | N61: A, U | O61: W, I | P61: 最佳嘲讽最快 | S61: 20(+4)
A62: Trixie | B62: 翠克希 | C62: 2剧情 | D62: 稀有 | E62: Focus Attacks | F62: Command 2 allies to attack one enemy instantaneously. | H62: 指挥 2 名队友瞬间攻击一名敌人。 | I62: 48(+7) | J62: 38(+5) | K62: 42(+6) | L62: 38(+5) | M62: 42(+6) | N62: W | O62: A, F | S62: 24(+5)
A63: Veneza | B63: 威妮莎 | C63: 5箱子 | D63: 稀有 | E63: Grand Slam | F63: Command 2 allies to attack one enemy instantaneously. | H63: 指挥 2 名队友瞬间攻击一名敌人。 | I63: 66(+11) | J63: 66(+11) | K63: 54(+8) | L63: 72(+14) | M63: 60(+9) | N63: F | O63: I | S63: 28(+6)
A64: XX | B64: XX | C64: 1剧情 | D64: 普通 | E64: Path of Love | F64: Charm one enemy, stunning them for 2 turns, and increasing their damage taken by 50%. | G64: X4武器6次攻击放技能，X2会更快 | H64: 魅惑一名敌人，使其眩晕 2 回合，并使其受到的伤害提升 50%。 | I64: 38(+5) | J64: 48(+7) | K64: 38(+5) | L64: 42(+6) | M64: 42(+6) | N64: A | O64: W, I | S64: 36(+8)
A65: Z-ANGELA | C65: Z工人 | D65: 传说 | G65: 工人 | I65: 41(+8) | J65: 29(+5) | K65: 33(+6) | L65: 29(+5) | M65: 29(+5) | N65: W
A66: Z-Sakaki | C66: Z工人 | D66: 传说 | G66: 工人 | I66: 33(+6) | J66: 29(+5) | K66: 41(+8) | L66: 29(+5) | M66: 29(+5) | N66: I
A67: Z-YASU | C67: Z工人 | D67: 传说 | G67: 工人 | I67: 36(+8) | J67: 24(+5) | K67: 24(+5) | L67: 24(+5) | M67: 28(+6) | N67: W | S67: S工人
P68: BUG不打第一个？ | R68: 20 | S68: 25(+4)
A69: Z-MARY | C69: Z工人 | D69: 传说 | G69: 工人 | I69: 33(+6) | J69: 29(+5) | K69: 25(+4) | L69: 41(+8) | M69: 33(+6) | N69: F | R69: 24 | S69: 29(+5) | T69: 29(+5)
A70: Z-LEILANI | C70: Z工人 | D70: 传说 | G70: 工人 | I70: 29(+5) | J70: 41(+8) | K70: 29(+5) | L70: 33(+6) | M70: 29(+5) | N70: A | R70: 28 | S70: 33(+6) | T70: 33(+6)
A71: Z-DAISY | C71: Z工人 | D71: 传说 | G71: 工人 | I71: 29(+5) | J71: 29(+5) | K71: 29(+6) | L71: 33(+7) | M71: 41(+8) | N71: U | R71: 36 | S71: 39(+8) | T71: 41(+8)
A72: W-U-IA-F | C72: Z工人 | D72: 史诗 | G72: 工人
A73: I-W-AF-U | C73: Z工人 | D73: 史诗 | G73: 工人
A86: vera

Sheet 全装
A1: 拥有 | B1: 购买 | C1: 筛选 | D1: 最适配 | E1: 衣服搭配 | F1: 级别 | G1: 装备名称 (English) | H1: 中文参考 | K1: 类型 (Type) | L1: f+u | M1: W红 | N1: A绿 | O1: I蓝 | P1: F橘 | Q1: U紫 | R1: 综合 | S1: W+FU | T1: A+FU | U1: I+FU | V1: W+F | W1: A+F | X1: I+F | Y1: 推荐 | Z1: 最终 | AA1: 1 | AB1: 原先版
B2: 1 | E2: 1W.ZD | F2: 1 | G2: Army Bottom | H2: 军队下装 | I2: ①.1_WFU-军用下装-51144 | K2: Bottom | L2: =P2+Q2 -> 8 | M2: 5 | N2: 1 | O2: 1 | P2: 4 | Q2: 4 | R2: =SUM(M2:Q2) -> 15 | S2: =V2+Q2 -> 13 | T2: =W2+Q2 -> 9 | U2: =X2+Q2 -> 9 | V2: =M2+P2 -> 9 | W2: =N2+P2 -> 5 | X2: =O2+P2 -> 5 | Y2: 1 | Z2: WFU-军用下装-51144_1=① | AA2: WFU-军用下装-51144_1 | AB2: ①1W51144陆军下装 | AC2: AIF-#阿达的Cos服-15451 | AD2: AIF-#阿达的Cos服-15451
B3: 1 | E3: 1W.ZD | F3: 1 | G3: Army Top | H3: 军队上衣 | I3: ①.1_WFU-军用上衣-51144 | K3: Top | L3: =P3+Q3 -> 8 | M3: 5 | N3: 1 | O3: 1 | P3: 4 | Q3: 4 | R3: =SUM(M3:Q3) -> 15 | S3: =V3+Q3 -> 13 | T3: =W3+Q3 -> 9 | U3: =X3+Q3 -> 9 | V3: =M3+P3 -> 9 | W3: =N3+P3 -> 5 | X3: =O3+P3 -> 5 | Y3: 1 | Z3: WFU-军用上衣-51144_1=① | AA3: WFU-军用上衣-51144_1 | AB3: ①1W51144陆军上装 | AC3: IUF-#阿德莱德的慰藉-11545.② | AD3: ②.IUF-#阿德莱德的慰藉-11545
E4: 2A.ZD | F4: 2 | G4: Gaia's Bottom | H4: 盖亚的下装 | I4: 2_AUF-盖亚的下装-14145 | K4: Bottom | L4: =P4+Q4 -> 9 | M4: 1 | N4: 4 | O4: 1 | P4: 4 | Q4: 5 | R4: =SUM(M4:Q4) -> 15 | S4: =V4+Q4 -> 10 | T4: =W4+Q4 -> 13 | U4: =X4+Q4 -> 10 | V4: =M4+P4 -> 5 | W4: =N4+P4 -> 8 | X4: =O4+P4 -> 5 | Y4: 2 | Z4: FAU-盖亚的下装-14145_2 | AA4: IFU-盖亚的下装-14145_2 | AB4: ②2A14145盖亚下 | AC4: AI-空气胸罩-14433 | AD4: AI-空气胸罩-14433
A5: Y | C5: 2 | E5: 2A.ZD | F5: 2 | G5: Veneza’s Top | H5: 威妮莎的上衣 | I5: 2_AUF-维内莎的上衣-14145 | K5: Top | L5: =P5+Q5 -> 9 | M5: 1 | N5: 4 | O5: 1 | P5: 4 | Q5: 5 | R5: =SUM(M5:Q5) -> 15 | S5: =V5+Q5 -> 10 | T5: =W5+Q5 -> 13 | U5: =X5+Q5 -> 10 | V5: =M5+P5 -> 5 | W5: =N5+P5 -> 8 | X5: =O5+P5 -> 5 | Y5: 2 | Z5: FAU-维内莎的上衣-14145_2 | AA5: AFU-维内莎的上衣-14145_2 | AB5: ②2A14145威尼斯顶 | AC5: A-多情蝴蝶结-34332 | AD5: A-多情蝴蝶结-34332
A6: Y | C6: 2 | E6: 3A.ZD | F6: 3 | G6: Space Leggings | H6: 太空紧身裤 | I6: ③.3_AFU-太空紧身裤-14244 | K6: Bottom | L6: =P6+Q6 -> 8 | M6: 1 | N6: 4 | O6: 2 | P6: 4 | Q6: 4 | R6: =SUM(M6:Q6) -> 15 | S6: =V6+Q6 -> 9 | T6: =W6+Q6 -> 12 | U6: =X6+Q6 -> 10 | V6: =M6+P6 -> 5 | W6: =N6+P6 -> 8 | X6: =O6+P6 -> 6 | Y6: 3 | Z6: AFI-太空紧身裤-14244_3=③ | AA6: AFI-太空紧身裤-14244_3 | AB6: ③3A14244太空紧身裤 | AC6: I-安德莉亚的秘密-23433 | AD6: I-安德莉亚的秘密-23433
A7: Y | C7: 2 | E7: 3A.ZD | F7: 3 | G7: Liza’s Wings | H7: 丽莎的翅膀 | I7: ③.3_AFU-丽莎的翅翼-14244 | K7: Top | L7: =P7+Q7 -> 8 | M7: 1 | N7: 4 | O7: 2 | P7: 4 | Q7: 4 | R7: =SUM(M7:Q7) -> 15 | S7: =V7+Q7 -> 9 | T7: =W7+Q7 -> 12 | U7: =X7+Q7 -> 10 | V7: =M7+P7 -> 5 | W7: =N7+P7 -> 8 | X7: =O7+P7 -> 6 | Y7: 3 | Z7: AFI-丽莎的翅翼-14244_3=③ | AA7: AFI-丽莎的翅翼-14244_3 | AB7: ③3A14244丽莎翅膀 | AC7: W-无袖衬衫-52233 | AD7: W-无袖衬衫-52233
A8: Y | C8: 2 | E8: 3A.ZD | F8: 3 | G8: Flaming Leggings | H8: 燃烧紧身裤 | I8: ③.3_AFU-燃烧紧身裤-14244 | K8: Bottom | L8: =P8+Q8 -> 8 | M8: 1 | N8: 4 | O8: 2 | P8: 4 | Q8: 4 | R8: =SUM(M8:Q8) -> 15 | S8: =V8+Q8 -> 9 | T8: =W8+Q8 -> 12 | U8: =X8+Q8 -> 10 | V8: =M8+P8 -> 5 | W8: =N8+P8 -> 8 | X8: =O8+P8 -> 6 | Y8: 3 | Z8: AIF-燃烧紧身裤-14244_3=③ | AA8: AIF-燃烧紧身裤-14244_3 | AB8: ③3A14244火焰紧身裤 | AC8: WFU-军用下装-51144_1.① | AD8: ①.WFU-军用下装-51144_1
A9: Y | C9: 2 | E9: 3A.ZD | F9: 3 | G9: Ashley’s Top | H9: 艾希莉的上衣 | I9: ③.3_AFU-艾希莉的上衣-14244 | K9: Top | L9: =P9+Q9 -> 8 | M9: 1 | N9: 4 | O9: 2 | P9: 4 | Q9: 4 | R9: =SUM(M9:Q9) -> 15 | S9: =V9+Q9 -> 9 | T9: =W9+Q9 -> 12 | U9: =X9+Q9 -> 10 | V9: =M9+P9 -> 5 | W9: =N9+P9 -> 8 | X9: =O9+P9 -> 6 | Y9: 3 | Z9: AFU-艾希莉的上衣-14244_3=③ | AA9: AFU-艾希莉的上衣-14244_3 | AB9: ③3A14244阿什利上衣 | AC9: WFU-军用上衣-51144_1.① | AD9: ①.WFU-军用上衣-51144_1
A10: Y | C10: 1 | E10: 4I.ZD | F10: 1 | G10: Momoka's Bottom | H10: 桃香的下装 | I10: ②.4_IFU-桃香的下装-11454 | K10: Bottom | L10: =P10+Q10 -> 9 | M10: 1 | N10: 1 | O10: 4 | P10: 5 | Q10: 4 | R10: =SUM(M10:Q10) -> 15 | S10: =V10+Q10 -> 10 | T10: =W10+Q10 -> 10 | U10: =X10+Q10 -> 13 | V10: =M10+P10 -> 6 | W10: =N10+P10 -> 6 | X10: =O10+P10 -> 9 | Y10: 4 | Z10: IFU-桃香的下装-11454_4=② | AA10: IFU-桃香的下装-11454_4 | AB10: ②4I11454桃花下 | AC10: AFU-艾希莉的上衣-14244_3.③ | AD10: ③.AFU-艾希莉的上衣-14244_3
A11: Y | C11: 1 | E11: 4I.ZD | F11: 3 | G11: Black-red Bra | H11: 黑红文胸 | I11: ②.4_IFU-黑红胸罩-21444 | K11: Top | L11: =P11+Q11 -> 8 | M11: 2 | N11: 1 | O11: 4 | P11: 4 | Q11: 4 | R11: =SUM(M11:Q11) -> 15 | S11: =V11+Q11 -> 10 | T11: =W11+Q11 -> 9 | U11: =X11+Q11 -> 12 | V11: =M11+P11 -> 6 | W11: =N11+P11 -> 5 | X11: =O11+P11 -> 8 | Y11: 4 | Z11: IFU-黑红胸罩-21444_4=② | AA11: IFU-黑红胸罩-21444_4 | AB11: ②4I21444黑红奶罩 | AC11: FU-艾希莉的下装-13344 | AD11: FU-艾希莉的下装-13344
A12: Y | C12: 1 | E12: 4I.ZD | F12: 2 | G12: Mechanic's Skirt | H12: 机械师短裙 | I12: ②.4_IUF-技工短裙-11445 | K12: Bottom | L12: =P12+Q12 -> 9 | M12: 1 | N12: 1 | O12: 4 | P12: 4 | Q12: 5 | R12: =SUM(M12:Q12) -> 15 | S12: =V12+Q12 -> 10 | T12: =W12+Q12 -> 10 | U12: =X12+Q12 -> 13 | V12: =M12+P12 -> 5 | W12: =N12+P12 -> 5 | X12: =O12+P12 -> 8 | Y12: 4 | Z12: IUF-技工短裙-11445_4=② | AA12: IFU-技工短裙-11445_4 | AB12: ②4I11445技裙 | AC12: AF-刺客的短匕-15342 | AD12: AF-刺客的短匕-15342
B13: 1 | E13: 14I.ZD | F13: 1 | G13: Neon Lights (bottom) | H13: 霓虹灯光（下装） | I13: ①.14_IFU-霓虹灯（下装）-11544 | K13: Bottom | L13: =P13+Q13 -> 8 | M13: 1 | N13: 1 | O13: 5 | P13: 4 | Q13: 4 | R13: =SUM(M13:Q13) -> 15 | S13: =V13+Q13 -> 9 | T13: =W13+Q13 -> 9 | U13: =X13+Q13 -> 13 | V13: =M13+P13 -> 5 | W13: =N13+P13 -> 5 | X13: =O13+P13 -> 9 | Y13: 4.1 | Z13: IFU-霓虹灯（下装）-11544_14=① | AA13: IFU-霓虹灯（下装）-11544_14 | AB13: ①14I11544霓虹散件 | AC13: UF-秋日套装-11345 | AD13: UF-秋日套装-11345
A14: y | B14: 1 | E14: 14I.ZD | F14: 1 | G14: Neon Lights (top) | H14: 霓虹灯光（上装） | I14: ①.14_IFU-霓虹灯(散件)-11544 | K14: Top | L14: =P14+Q14 -> 8 | M14: 1 | N14: 1 | O14: 5 | P14: 4 | Q14: 4 | R14: =SUM(M14:Q14) -> 15 | S14: =V14+Q14 -> 9 | T14: =W14+Q14 -> 9 | U14: =X14+Q14 -> 13 | V14: =M14+P14 -> 5 | W14: =N14+P14 -> 5 | X14: =O14+P14 -> 9 | Y14: 4.1 | Z14: IFU-霓虹灯（上衣）-11544_14=① | AA14: IFU-霓虹灯（上衣）-11544_14 | AB14: ①14I11544霓虹上 | AC14: UF-班卡的泡沫-23145 | AD14: UF-班卡的泡沫-23145
A15: Y | C15: X | E15: 5FU.FJ | G15: Mechanic’s Top | H15: 机械师上衣 | I15: 5_FU-技工上衣-11355 | K15: Top | L15: =P15+Q15 -> 10 | M15: 1 | N15: 1 | O15: 3 | P15: 5 | Q15: 5 | R15: =SUM(M15:Q15) -> 15 | S15: =V15+Q15 -> 11 | T15: =W15+Q15 -> 11 | U15: =X15+Q15 -> 13 | V15: =M15+P15 -> 6 | W15: =N15+P15 -> 6 | X15: =O15+P15 -> 8 | Y15: 5 | Z15: FUI-技工上衣-11355_5 | AA15: IFU-技工上衣-11355_5 | AB15: 5FU11355技衣 | AC15: AF-野蛮人短裙-15153_7.① | AD15: ①.AF-野蛮人短裙-15153_7
A16: Y | C16: X | E16: 5FU.FJ | G16: Veneza's Bottom | H16: 威妮莎的下装 | I16: 5_FU-维内莎的下装-13155 | K16: Bottom | L16: =P16+Q16 -> 10 | M16: 1 | N16: 3 | O16: 1 | P16: 5 | Q16: 5 | R16: =SUM(M16:Q16) -> 15 | S16: =V16+Q16 -> 11 | T16: =W16+Q16 -> 13 | U16: =X16+Q16 -> 11 | V16: =M16+P16 -> 6 | W16: =N16+P16 -> 8 | X16: =O16+P16 -> 6 | Y16: 5 | Z16: FUA-维内莎的下装-13155_5 | AA16: IFU-维内莎的下装-13155_5 | AB16: 5FU13155威尼斯下 | AC16: AF-野蛮人上衣-15153_7.① | AD16: ①.AF-野蛮人上衣-15153_7
A17: Y | B17: 1 | C17: X | E17: 6WA.FJ | G17: Open Top | H17: 开襟上衣 | I17: ⑥.WAI-#敞口上衣-55411 | K17: Top | L17: =P17+Q17 -> 2 | M17: 5 | N17: 5 | O17: 4 | P17: 1 | Q17: 1 | R17: =SUM(M17:Q17) -> 16 | S17: =V17+Q17 -> 7 | T17: =W17+Q17 -> 7 | U17: =X17+Q17 -> 6 | V17: =M17+P17 -> 6 | W17: =N17+P17 -> 6 | X17: =O17+P17 -> 5 | Y17: 6 | Z17: WAI-敞口上衣-55411_6 | AA17: WAI-敞口上衣-55411_6 | AB17: 6WA55411@敞篷 | AC17: FU-棒球明星（下装）-13254_11 | AD17: FU-棒球明星（下装）-13254_11
A18: y | B18: 1 | E18: 6WA.FJ | G18: Wide Bottom | H18: 宽下装 | I18: ⑥.WAI-#宽阔下装-55411 | K18: Bottom | L18: =P18+Q18 -> 2 | M18: 5 | N18: 5 | O18: 4 | P18: 1 | Q18: 1 | R18: =SUM(M18:Q18) -> 16 | S18: =V18+Q18 -> 7 | T18: =W18+Q18 -> 7 | U18: =X18+Q18 -> 6 | V18: =M18+P18 -> 6 | W18: =N18+P18 -> 6 | X18: =O18+P18 -> 5 | Y18: 6 | Z18: WAI-宽阔下装-55411_6 | AA18: WAI-宽阔下装-55411_6 | AB18: 6WA55411@宽裤 | AC18: FU-棒球明星(散件)-13254_11 | AD18: FU-棒球明星(散件)-13254_11
A19: y | B19: 1 | E19: 7AF.FJ | F19: 1 | G19: Barbarian Skirt | H19: 野蛮人裙 | I19: ①.7_AF-野蛮人短裙-15153 | K19: Bottom | L19: =P19+Q19 -> 8 | M19: 1 | N19: 5 | O19: 1 | P19: 5 | Q19: 3 | R19: =SUM(M19:Q19) -> 15 | S19: =V19+Q19 -> 9 | T19: =W19+Q19 -> 13 | U19: =X19+Q19 -> 9 | V19: =M19+P19 -> 6 | W19: =N19+P19 -> 10 | X19: =O19+P19 -> 6 | Y19: 7 | Z19: AFU-野蛮人短裙-15153_7=① | AA19: AFU-野蛮人短裙-15153_7 | AB19: ①7AF15153野蛮人裙 | AC19: IF-甲虫胸针-13443 | AD19: IF-甲虫胸针-13443
A20: y | B20: 1 | E20: 7AF.FJ | F20: 1 | G20: Barbarian Top | H20: 野蛮人上衣 | I20: ①.7_AF-野蛮人上衣-15153 | K20: Top | L20: =P20+Q20 -> 8 | M20: 1 | N20: 5 | O20: 1 | P20: 5 | Q20: 3 | R20: =SUM(M20:Q20) -> 15 | S20: =V20+Q20 -> 9 | T20: =W20+Q20 -> 13 | U20: =X20+Q20 -> 9 | V20: =M20+P20 -> 6 | W20: =N20+P20 -> 10 | X20: =O20+P20 -> 6 | Y20: 7 | Z20: AFU-野蛮人上衣-15153_7=① | AA20: AFU-野蛮人上衣-15153_7 | AB20: ①7AF15153野蛮人上衣 | AC20: IF-生日小蛋糕-11553 | AD20: IF-生日小蛋糕-11553
A21: Y | C21: 1 | E21: 8AF.FJ | G21: Chelsea’s Favor | H21: 切尔西的青睐 | I21: ②.8_AF-切尔西的恩惠-15243 | K21: Top | L21: =P21+Q21 -> 7 | M21: 1 | N21: 5 | O21: 2 | P21: 4 | Q21: 3 | R21: =SUM(M21:Q21) -> 15 | S21: =V21+Q21 -> 8 | T21: =W21+Q21 -> 12 | U21: =X21+Q21 -> 9 | V21: =M21+P21 -> 5 | W21: =N21+P21 -> 9 | X21: =O21+P21 -> 6 | Y21: 8 | Z21: AFI-切尔西的恩惠-15243_8=② | AA21: AFI-切尔西的恩惠-15243_8 | AB21: ②8AF152343切尔西的恩惠 | AC21: IFU-黑红胸罩-21444_4.② | AD21: ②.IFU-黑红胸罩-21444_4
C22: 1 | E22: 8AF.FJ | F22: 1 | G22: Chelsea's Blessing | H22: 切尔西的祝福 | I22: ②.8_AF-切尔西的赐福-15243 | K22: Bottom | L22: =P22+Q22 -> 7 | M22: 1 | N22: 5 | O22: 2 | P22: 4 | Q22: 3 | R22: =SUM(M22:Q22) -> 15 | S22: =V22+Q22 -> 8 | T22: =W22+Q22 -> 12 | U22: =X22+Q22 -> 9 | V22: =M22+P22 -> 5 | W22: =N22+P22 -> 9 | X22: =O22+P22 -> 6 | Y22: 8 | Z22: AFI-切尔西的赐福-15243_8=② | AA22: AFI-切尔西的赐福-15243_8 | AB22: ②8AF152343切尔西的祝福 | AC22: W-爆能枪-43332 | AD22: W-爆能枪-43332
A23: Y | C23: 1 | E23: 9AF.FJ | F23: 1 | G23: Prisoners Panties | H23: 囚犯内裤 | I23: ②.9_AF-囚犯内裤-15342 | K23: Bottom | L23: =P23+Q23 -> 6 | M23: 1 | N23: 5 | O23: 3 | P23: 4 | Q23: 2 | R23: =SUM(M23:Q23) -> 15 | S23: =V23+Q23 -> 7 | T23: =W23+Q23 -> 11 | U23: =X23+Q23 -> 9 | V23: =M23+P23 -> 5 | W23: =N23+P23 -> 9 | X23: =O23+P23 -> 7 | Y23: 9 | Z23: AFI-囚犯内裤-15342_9=② | AA23: AFI-囚犯内裤-15342_9 | AB23: 9AF15342囚犯内裤 | AC23: FU-爆破锤-13344 | AD23: FU-爆破锤-13344
A24: Y | C24: 1 | E24: 9AF.FJ | F24: 1 | G24: Dissolved Top | H24: 溶解上衣 | I24: ②.9_AF-溶解上衣-15243 | K24: Top | L24: =P24+Q24 -> 7 | M24: 1 | N24: 5 | O24: 2 | P24: 4 | Q24: 3 | R24: =SUM(M24:Q24) -> 15 | S24: =V24+Q24 -> 8 | T24: =W24+Q24 -> 12 | U24: =X24+Q24 -> 9 | V24: =M24+P24 -> 5 | W24: =N24+P24 -> 9 | X24: =O24+P24 -> 6 | Y24: 9 | Z24: AFI-溶解上衣-15243_9=② | AA24: AFI-溶解上衣-15243_9 | AB24: 9AF15243溶解顶部 | AC24: W-束缚长裤-42333 | AD24: W-束缚长裤-42333
E25: 11FU.FJ | G25: Baseball Star (bottom) | H25: 棒球明星（下装） | I25: 11_FU-棒球明星（下装）-13254 | K25: Bottom | L25: =P25+Q25 -> 9 | M25: 1 | N25: 3 | O25: 2 | P25: 5 | Q25: 4 | R25: =SUM(M25:Q25) -> 15 | S25: =V25+Q25 -> 10 | T25: =W25+Q25 -> 12 | U25: =X25+Q25 -> 11 | V25: =M25+P25 -> 6 | W25: =N25+P25 -> 8 | X25: =O25+P25 -> 7 | Y25: 11 | Z25: FU-棒球明星（下装）-13254_11 | AA25: AFU-棒球明星（下装）-13254_11 | AB25: 11FU13254棒球明星散件 | AC25: AF-烙印钥匙链-34143 | AD25: AF-烙印钥匙链-34143
E26: 11FU.FJ | G26: Baseball Star (top) | H26: 棒球明星（上装） | I26: 11_FU-棒球明星(散件)-13254 | K26: Top | L26: =P26+Q26 -> 9 | M26: 1 | N26: 3 | O26: 2 | P26: 5 | Q26: 4 | R26: =SUM(M26:Q26) -> 15 | S26: =V26+Q26 -> 10 | T26: =W26+Q26 -> 12 | U26: =X26+Q26 -> 11 | V26: =M26+P26 -> 6 | W26: =N26+P26 -> 8 | X26: =O26+P26 -> 7 | Y26: 11 | Z26: FU-棒球明星（上衣）-13254_11 | AA26: AFU-棒球明星（上衣）-13254_11 | AB26: 11FU棒球明星上衣 | AC26: WI-胸针-41433 | AD26: WI-胸针-41433
A27: y | B27: 1 | E27: 12.SB | G27: Waifu's Special (bottom) | H27: 老婆特别下装 | I27: 12_老婆特供（下装）-33333 | K27: Bottom | L27: =P27+Q27 -> 6 | M27: 3 | N27: 3 | O27: 3 | P27: 3 | Q27: 3 | R27: =SUM(M27:Q27) -> 15 | S27: =V27+Q27 -> 9 | T27: =W27+Q27 -> 9 | U27: =X27+Q27 -> 9 | V27: =M27+P27 -> 6 | W27: =N27+P27 -> 6 | X27: =O27+P27 -> 6 | Y27: 12 | Z27: 老婆特供（下装）-33333_12 | AA27: 老婆特供（下装）-33333_12 | AB27: 12特辑下装 | AC27: IU-商务下装-31434 | AD27: IU-商务下装-31434
B28: 1 | E28: 12.SB | G28: Waifu’s Special (top) | H28: 老婆特别上衣 | I28: 12_老婆特供(散件)-33333 | K28: Top | L28: =P28+Q28 -> 6 | M28: 3 | N28: 3 | O28: 3 | P28: 3 | Q28: 3 | R28: =SUM(M28:Q28) -> 15 | S28: =V28+Q28 -> 9 | T28: =W28+Q28 -> 9 | U28: =X28+Q28 -> 9 | V28: =M28+P28 -> 6 | W28: =N28+P28 -> 6 | X28: =O28+P28 -> 6 | Y28: 12 | Z28: 老婆特供（上衣）-33333_12 | AA28: 老婆特供（上衣）-33333_12 | AB28: 12特辑散件5T | AC28: IU-商务上衣-31434 | AD28: IU-商务上衣-31434
A29: y | B29: 1 | E29: 13.FJ | G29: XX's Prayer | H29: XX的祈祷 | I29: ②.13_WU-XX的祈祷-51135 | K29: Bottom | L29: =P29+Q29 -> 8 | M29: 5 | N29: 1 | O29: 1 | P29: 3 | Q29: 5 | R29: =SUM(M29:Q29) -> 15 | S29: =V29+Q29 -> 13 | T29: =W29+Q29 -> 9 | U29: =X29+Q29 -> 9 | V29: =M29+P29 -> 8 | W29: =N29+P29 -> 4 | X29: =O29+P29 -> 4 | Y29: 13 | Z29: WFU-XX的祈祷-51135_13=② | AA29: WFU-XX的祈祷-51135_13 | AB29: U13WU51135 XX祈祷 | AC29: AFU-屠夫的斩肉刀-14244 | AD29: AFU-屠夫的斩肉刀-14244
B30: 1 | E30: 13.FJ | G30: XX’s Blessing | H30: XX的祝福 | I30: ②.13_WU-XX的赐福-51135 | K30: Top | L30: =P30+Q30 -> 8 | M30: 5 | N30: 1 | O30: 1 | P30: 3 | Q30: 5 | R30: =SUM(M30:Q30) -> 15 | S30: =V30+Q30 -> 13 | T30: =W30+Q30 -> 9 | U30: =X30+Q30 -> 9 | V30: =M30+P30 -> 8 | W30: =N30+P30 -> 4 | X30: =O30+P30 -> 4 | Y30: 13 | Z30: WFU-XX的赐福-51135_13=② | AA30: WFU-XX的赐福-51135_13 | AB30: 13WU51135 XX祝福 | AC30: 休闲连衣裙-33333 | AD30: 休闲连衣裙-33333
A31: Y | B31: 1 | E31: 15.FJ | G31: Pain Bringers (bottom) | H31: 佩恩使者（下装） | I31: ⑮.WAI-#痛苦使者（下装）-54511 | K31: Bottom | L31: =P31+Q31 -> 2 | M31: 5 | N31: 4 | O31: 5 | P31: 1 | Q31: 1 | R31: =SUM(M31:Q31) -> 16 | S31: =V31+Q31 -> 7 | T31: =W31+Q31 -> 6 | U31: =X31+Q31 -> 7 | V31: =M31+P31 -> 6 | W31: =N31+P31 -> 5 | X31: =O31+P31 -> 6 | Y31: 15 | Z31: WAI-痛苦使者（下装）-54511_15 | AA31: WAI-痛苦使者（下装）-54511_15 | AB31: 15WI51511@痛苦使者下装 | AC31: IFU-休闲套装-21444.④ | AD31: ④.IFU-休闲套装-21444
A32: y | B32: 1 | E32: 15.FJ | G32: Pain Bringers (top) | H32: 佩恩使者（上装） | I32: ⑮.WAI-#痛苦使者(散件)-54511 | K32: Top | L32: =P32+Q32 -> 2 | M32: 5 | N32: 4 | O32: 5 | P32: 1 | Q32: 1 | R32: =SUM(M32:Q32) -> 16 | S32: =V32+Q32 -> 7 | T32: =W32+Q32 -> 6 | U32: =X32+Q32 -> 7 | V32: =M32+P32 -> 6 | W32: =N32+P32 -> 5 | X32: =O32+P32 -> 6 | Y32: 15 | Z32: WAI-痛苦使者（上衣）-54511_15 | AA32: WAI-痛苦使者（上衣）-54511_15 | AB32: 15WI54511@痛苦使者上衣 | AC32: AF-猫耳发饰-14343 | AD32: AF-猫耳发饰-14343
A33: y | B33: 1 | E33: 16.FJ | F33: 1 | G33: Road Warrior (bottom) | H33: 公路勇士（下装） | I33: ①.16_AF-公路战士（下装）-15153 | K33: Bottom | L33: =P33+Q33 -> 8 | M33: 1 | N33: 5 | O33: 1 | P33: 5 | Q33: 3 | R33: =SUM(M33:Q33) -> 15 | S33: =V33+Q33 -> 9 | T33: =W33+Q33 -> 13 | U33: =X33+Q33 -> 9 | V33: =M33+P33 -> 6 | W33: =N33+P33 -> 10 | X33: =O33+P33 -> 6 | Y33: 16 | Z33: AFU-公路战士（下装）-15153_16=① | AA33: AFU-公路战士（下装）-15153_16 | AB33: ①16AF15153公路战士 | AC33: 凯瑟琳的绷带装(X)-00000 | AD33: 凯瑟琳的绷带装(X)-00000
B34: 1 | E34: 16.FJ | F34: 1 | G34: Road Warrior (top) | H34: 公路勇士（上装） | I34: ①.16_AF-公路战士(散件)-15153 | K34: Top | L34: =P34+Q34 -> 8 | M34: 1 | N34: 5 | O34: 1 | P34: 5 | Q34: 3 | R34: =SUM(M34:Q34) -> 15 | S34: =V34+Q34 -> 9 | T34: =W34+Q34 -> 13 | U34: =X34+Q34 -> 9 | V34: =M34+P34 -> 6 | W34: =N34+P34 -> 10 | X34: =O34+P34 -> 6 | Y34: 16 | Z34: AFU-公路战士（上衣）-15153_16=① | AA34: AFU-公路战士（上衣）-15153_16 | AB34: ①16A15153公路战士上衣 | AC34: CB-69的护甲(X)-00000 | AD34: CB-69的护甲(X)-00000
A35: y | B35: 1 | E35: 17.FJ | G35: Pearl's Treasury | H35: 珀尔的财宝 | I35: 17_FU-珍珠的珍藏-11155 | K35: Bottom | L35: =P35+Q35 -> 10 | M35: 1 | N35: 1 | O35: 1 | P35: 5 | Q35: 5 | R35: =SUM(M35:Q35) -> 13 | S35: =V35+Q35 -> 11 | T35: =W35+Q35 -> 11 | U35: =X35+Q35 -> 11 | V35: =M35+P35 -> 6 | W35: =N35+P35 -> 6 | X35: =O35+P35 -> 6 | Y35: 17 | Z35: FU-珍珠的珍藏-11155_17 | AA35: FUW-珍珠的珍藏-11155_17 | AB35: 17FU11155珍珠宝库 | AC35: AF-切尔西的连体紧身衣-15243.② | AD35: ②.AF-切尔西的连体紧身衣-15243
B36: 1 | E36: 17.FJ | G36: Pearl's Shell | H36: 珀尔的贝壳 | I36: 17_FU-珍珠的贝壳-11155 | K36: Top | L36: =P36+Q36 -> 10 | M36: 1 | N36: 1 | O36: 1 | P36: 5 | Q36: 5 | R36: =SUM(M36:Q36) -> 13 | S36: =V36+Q36 -> 11 | T36: =W36+Q36 -> 11 | U36: =X36+Q36 -> 11 | V36: =M36+P36 -> 6 | W36: =N36+P36 -> 6 | X36: =O36+P36 -> 6 | Y36: 17 | Z36: FU-珍珠的贝壳-11155_17 | AA36: FUW-珍珠的贝壳-11155_17 | AB36: 17FU11155珍珠贝壳 | AC36: AF-切尔西的恩惠-15243_8.② | AD36: ②.AF-切尔西的恩惠-15243_8
B37: 1 | E37: =_xlfn.XLOOKUP(G37,Combos!AB:AB,Combos!AA:AA,"",0,1) | F37: 1 | G37: Adah’s Cosplays | H37: 阿达的Cos服 | I37: AIF-#阿达的Cos服-15451 | K37: Dress | L37: =P37+Q37 -> 6 | M37: 1 | N37: 5 | O37: 4 | P37: 5 | Q37: 1 | R37: =SUM(M37:Q37) -> 16 | S37: =V37+Q37 -> 7 | T37: =W37+Q37 -> 11 | U37: =X37+Q37 -> 10 | V37: =M37+P37 -> 6 | W37: =N37+P37 -> 10 | X37: =O37+P37 -> 9 | Y37: =_xlfn.XLOOKUP(AA37,Combos!AU:AU,Combos!AT:AT,"",0,1) | Z37: FAI-阿达的角色扮演服-15451 | AA37: AFI-阿达的角色扮演服-15451 | AB37: AIF15451@阿达Cos服 | AC37: AF-切尔西的赐福-15243_8.② | AD37: ②.AF-切尔西的赐福-15243_8
B38: 1 | E38: =_xlfn.XLOOKUP(G38,Combos!AB:AB,Combos!AA:AA,"",0,1) | F38: 1 | G38: Adelaide’s Comfort | H38: 阿德莱恩的舒适 | I38: ②.IUF-#阿德莱德的慰藉-11545 | K38: Dress | L38: =P38+Q38 -> 9 | M38: 1 | N38: 1 | O38: 5 | P38: 4 | Q38: 5 | R38: =SUM(M38:Q38) -> 16 | S38: =V38+Q38 -> 10 | T38: =W38+Q38 -> 10 | U38: =X38+Q38 -> 14 | V38: =M38+P38 -> 5 | W38: =N38+P38 -> 5 | X38: =O38+P38 -> 9 | Y38: =_xlfn.XLOOKUP(AA38,Combos!AU:AU,Combos!AT:AT,"",0,1) | Z38: IUF-阿德莱德的慰藉-11545=② | AA38: IUF-阿德莱德的慰藉-11545 | AB38: ②IU11545@阿黛拉伊德的舒适 | AC38: WUF-骑士精神-41145.③ | AD38: ③.WUF-骑士精神-41145
A39: Y | C39: 2 | E39: =_xlfn.XLOOKUP(G39,Combos!AB:AB,Combos!AA:AA,"",0,1) | G39: Andrea’s Secrets | H39: 安德烈亚的秘密 | I39: I-安德莉亚的秘密-23433 | K39: Dress | L39: =P39+Q39 -> 6 | M39: 2 | N39: 3 | O39: 4 | P39: 3 | Q39: 3 | R39: =SUM(M39:Q39) -> 15 | S39: =V39+Q39 -> 8 | T39: =W39+Q39 -> 9 | U39: =X39+Q39 -> 10 | V39: =M39+P39 -> 5 | W39: =N39+P39 -> 6 | X39: =O39+P39 -> 7 | Y39: =_xlfn.XLOOKUP(AA39,Combos!AU:AU,Combos!AT:AT,"",0,1) | Z39: IFU-安德莉亚的秘密-23433 | AA39: IFU-安德莉亚的秘密-23433 | AB39: 安德里亚的秘密 | AC39: FU-巧克力棒-13344 | AD39: FU-巧克力棒-13344
A40: Y | C40: X | E40: =_xlfn.XLOOKUP(G40,Combos!AB:AB,Combos!AA:AA,"",0,1) | G40: Autumn Set | H40: 奥特姆套装 | I40: UF-秋日套装-11345 | K40: Dress | L40: =P40+Q40 -> 9 | M40: 1 | N40: 1 | O40: 3 | P40: 4 | Q40: 5 | R40: =SUM(M40:Q40) -> 14 | S40: =V40+Q40 -> 10 | T40: =W40+Q40 -> 10 | U40: =X40+Q40 -> 12 | V40: =M40+P40 -> 5 | W40: =N40+P40 -> 5 | X40: =O40+P40 -> 7 | Y40: =_xlfn.XLOOKUP(AA40,Combos!AU:AU,Combos!AT:AT,"",0,1) | Z40: UF-秋日套装-11345 | AA40: IFU-秋日套装-11345 | AB40: U11345秋季套装 | AC40: AF-斩肉刀-24243 | AD40: AF-斩肉刀-24243
B41: 1 | E41: =_xlfn.XLOOKUP(G41,Combos!AB:AB,Combos!AA:AA,"",0,1) | G41: Beetle Brooch | H41: 甲虫胸针 | I41: IF-甲虫胸针-13443 | K41: Trinket | L41: =P41+Q41 -> 7 | M41: 1 | N41: 3 | O41: 4 | P41: 4 | Q41: 3 | R41: =SUM(M41:Q41) -> 15 | S41: =V41+Q41 -> 8 | T41: =W41+Q41 -> 10 | U41: =X41+Q41 -> 11 | V41: =M41+P41 -> 5 | W41: =N41+P41 -> 7 | X41: =O41+P41 -> 8 | Y41: =_xlfn.XLOOKUP(AA41,Combos!AU:AU,Combos!AT:AT,"",0,1) | Z41: IFU-甲虫胸针-13443 | AA41: IFU-甲虫胸针-13443 | AB41: IF13443甲虫胸针 | AC41: W-民用自动手枪-43332 | AD41: W-民用自动手枪-43332
E42: =_xlfn.XLOOKUP(G42,Combos!AB:AB,Combos!AA:AA,"",0,1) | F42: 1 | G42: Birthday Cupcakes | H42: 生日纸杯蛋糕 | I42: IF-生日小蛋糕-11553 | K42: Trinket | L42: =P42+Q42 -> 8 | M42: 1 | N42: 1 | O42: 5 | P42: 5 | Q42: 3 | R42: =SUM(M42:Q42) -> 15 | S42: =V42+Q42 -> 9 | T42: =W42+Q42 -> 9 | U42: =X42+Q42 -> 13 | V42: =M42+P42 -> 6 | W42: =N42+P42 -> 6 | X42: =O42+P42 -> 10 | Y42: =_xlfn.XLOOKUP(AA42,Combos!AU:AU,Combos!AT:AT,"",0,1) | Z42: IFU-生日小蛋糕-11553 | AA42: IFU-生日小蛋糕-11553 | AB42: IF11553纸杯蛋糕 | AC42: IU-上流色彩-22434 | AD42: IU-上流色彩-22434
C43: 1 | E43: =_xlfn.XLOOKUP(G43,Combos!AB:AB,Combos!AA:AA,"",0,1) | G43: Subtle Top | H43: 精致上衣 | I43: I-微妙的上衣-31533 | K43: Top | L43: =P43+Q43 -> 6 | M43: 3 | N43: 1 | O43: 5 | P43: 3 | Q43: 3 | R43: =SUM(M43:Q43) -> 15 | S43: =V43+Q43 -> 9 | T43: =W43+Q43 -> 7 | U43: =X43+Q43 -> 11 | V43: =M43+P43 -> 6 | W43: =N43+P43 -> 4 | X43: =O43+P43 -> 8 | Y43: =_xlfn.XLOOKUP(AA43,Combos!AU:AU,Combos!AT:AT,"",0,1) | Z43: WIF-微妙的上衣-31533 | AA43: WIF-微妙的上衣-31533 | AB43: I精致上衣 | AC43: IF-克洛伊的套装-13542.③ | AD43: ③.IF-克洛伊的套装-13542
A44: Y | C44: X | E44: =_xlfn.XLOOKUP(G44,Combos!AB:AB,Combos!AA:AA,"",0,1) | G44: Banka’s Bubbles | H44: 班卡的气泡 | I44: UF-班卡的泡沫-23145 | K44: Dress | L44: =P44+Q44 -> 9 | M44: 2 | N44: 3 | O44: 1 | P44: 4 | Q44: 5 | R44: =SUM(M44:Q44) -> 15 | S44: =V44+Q44 -> 11 | T44: =W44+Q44 -> 12 | U44: =X44+Q44 -> 10 | V44: =M44+P44 -> 6 | W44: =N44+P44 -> 7 | X44: =O44+P44 -> 5 | Y44: =_xlfn.XLOOKUP(AA44,Combos!AU:AU,Combos!AT:AT,"",0,1) | Z44: UF-班卡的泡沫-23145 | AA44: IFU-班卡的泡沫-23145 | AB44: U23145班卡的泡泡 | AC44: WF-战斗霰弹枪-41352 | AD44: WF-战斗霰弹枪-41352
A45: Y | B45: 1 | C45: 1 | E45: =_xlfn.XLOOKUP(G45,Combos!AB:AB,Combos!AA:AA,"",0,1) | G45: Branded Key Chain | H45: 烙印钥匙链 | I45: AF-烙印钥匙链-34143 | K45: Trinket | L45: =P45+Q45 -> 7 | M45: 3 | N45: 4 | O45: 1 | P45: 4 | Q45: 3 | R45: =SUM(M45:Q45) -> 15 | S45: =V45+Q45 -> 10 | T45: =W45+Q45 -> 11 | U45: =X45+Q45 -> 8 | V45: =M45+P45 -> 7 | W45: =N45+P45 -> 8 | X45: =O45+P45 -> 5 | Y45: =_xlfn.XLOOKUP(AA45,Combos!AU:AU,Combos!AT:AT,"",0,1) | Z45: WIF-烙印钥匙链-34143 | AA45: WIF-烙印钥匙链-34143 | AB45: AF34143钥匙扣 | AC45: WI-宇宙装束-51513 | AD45: WI-宇宙装束-51513
B46: 1 | E46: =_xlfn.XLOOKUP(G46,Combos!AB:AB,Combos!AA:AA,"",0,1) | G46: Casual Dress | H46: 休闲连衣裙 | I46: 休闲连衣裙-33333 | K46: Dress | L46: =P46+Q46 -> 6 | M46: 3 | N46: 3 | O46: 3 | P46: 3 | Q46: 3 | R46: =SUM(M46:Q46) -> 15 | S46: =V46+Q46 -> 9 | T46: =W46+Q46 -> 9 | U46: =X46+Q46 -> 9 | V46: =M46+P46 -> 6 | W46: =N46+P46 -> 6 | X46: =O46+P46 -> 6 | Y46: =_xlfn.XLOOKUP(AA46,Combos!AU:AU,Combos!AT:AT,"",0,1) | Z46: 休闲连衣裙-33333 | AA46: 休闲连衣裙-33333 | AB46: 休闲连衣裙 | AC46: WI-宇宙装束（上衣）-43422 | AD46: WI-宇宙装束（上衣）-43422
A47: Y | C47: 1 | E47: =_xlfn.XLOOKUP(G47,Combos!AB:AB,Combos!AA:AA,"",0,1) | F47: 3 | G47: Casual Suit | H47: 休闲套装 | I47: ④.IFU-休闲套装-21444 | K47: Dress | L47: =P47+Q47 -> 8 | M47: 2 | N47: 1 | O47: 4 | P47: 4 | Q47: 4 | R47: =SUM(M47:Q47) -> 15 | S47: =V47+Q47 -> 10 | T47: =W47+Q47 -> 9 | U47: =X47+Q47 -> 12 | V47: =M47+P47 -> 6 | W47: =N47+P47 -> 5 | X47: =O47+P47 -> 8 | Y47: =_xlfn.XLOOKUP(AA47,Combos!AU:AU,Combos!AT:AT,"",0,1) | Z47: IFU-休闲套装-21444=④ | AA47: IFU-休闲套装-21444 | AB47: ④I21444休闲套装 | AC47: AF-疯狂套装-24342.⑥ | AD47: ⑥.AF-疯狂套装-24342
B48: 1 | G48: Catherine's Bandages | H48: 凯瑟琳的绷带 | I48: 凯瑟琳的绷带装(X)-00000 | K48: Dress | L48: =P48+Q48 -> 0 | M48: 0 | N48: 0 | O48: 0 | P48: 0 | Q48: 0 | R48: =SUM(M48:Q48) -> 0 | S48: =V48+Q48 -> 0 | T48: =W48+Q48 -> 0 | U48: =X48+Q48 -> 0 | V48: =M48+P48 -> 0 | W48: =N48+P48 -> 0 | X48: =O48+P48 -> 0 | Z48: 凯瑟琳的绷带装(X)-00000 | AA48: 凯瑟琳的绷带装(X)-00000 | AB48: (?)凯瑟琳的绷带 | AC48: WF-可爱胸针-42342 | AD48: WF-可爱胸针-42342
B49: 1 | G49: CB-69's Armour | H49: CB-69的护甲 | I49: CB-69的护甲(X)-00000 | K49: Dress | L49: =P49+Q49 -> 0 | M49: 0 | N49: 0 | O49: 0 | P49: 0 | Q49: 0 | R49: =SUM(M49:Q49) -> 0 | S49: =V49+Q49 -> 0 | T49: =W49+Q49 -> 0 | U49: =X49+Q49 -> 0 | V49: =M49+P49 -> 0 | W49: =N49+P49 -> 0 | X49: =O49+P49 -> 0 | Z49: CB-69的护甲(X)-00000 | AA49: CB-69的护甲(X)-00000 | AB49: (?)CB-69的护甲 | AC49: IFU-可爱连衣裙-12444.④ | AD49: ④.IFU-可爱连衣裙-12444
A50: Y | C50: X | E50: =_xlfn.XLOOKUP(G50,Combos!AB:AB,Combos!AA:AA,"",0,1) | G50: Brooch | H50: 胸针 | I50: WI-胸针-41433 | K50: Trinket | L50: =P50+Q50 -> 6 | M50: 4 | N50: 1 | O50: 4 | P50: 3 | Q50: 3 | R50: =SUM(M50:Q50) -> 15 | S50: =V50+Q50 -> 10 | T50: =W50+Q50 -> 7 | U50: =X50+Q50 -> 10 | V50: =M50+P50 -> 7 | W50: =N50+P50 -> 4 | X50: =O50+P50 -> 7 | Y50: =_xlfn.XLOOKUP(AA50,Combos!AU:AU,Combos!AT:AT,"",0,1) | Z50: WAI-胸针-41433 | AA50: WAI-胸针-41433 | AB50: WI41433胸针 | AC50: AF-匕首-24342 | AD50: AF-匕首-24342
A51: Y | C51: 1 | E51: =_xlfn.XLOOKUP(G51,Combos!AB:AB,Combos!AA:AA,"",0,1) | F51: 1 | G51: Chelsea’s Bodysuit | H51: 切尔西的连体衣 | I51: ②.AF-切尔西的连体紧身衣-15243 | K51: Dress | L51: =P51+Q51 -> 7 | M51: 1 | N51: 5 | O51: 2 | P51: 4 | Q51: 3 | R51: =SUM(M51:Q51) -> 15 | S51: =V51+Q51 -> 8 | T51: =W51+Q51 -> 12 | U51: =X51+Q51 -> 9 | V51: =M51+P51 -> 5 | W51: =N51+P51 -> 9 | X51: =O51+P51 -> 6 | Y51: =_xlfn.XLOOKUP(AA51,Combos!AU:AU,Combos!AT:AT,"",0,1) | Z51: AFI-切尔西的连体紧身衣-15243=② | AA51: AFI-切尔西的连体紧身衣-15243 | AB51: ②A切尔西连体衣15243 | AC51: 达希亚的仪式(X)-00000 | AD51: 达希亚的仪式(X)-00000
B52: 1 | E52: =_xlfn.XLOOKUP(G52,Combos!AB:AB,Combos!AA:AA,"",0,1) | F52: 2 | G52: Chivalry | H52: 骑士精神 | I52: ③.WUF-骑士精神-41145 | K52: Dress | L52: =P52+Q52 -> 9 | M52: 4 | N52: 1 | O52: 1 | P52: 4 | Q52: 5 | R52: =SUM(M52:Q52) -> 15 | S52: =V52+Q52 -> 13 | T52: =W52+Q52 -> 10 | U52: =X52+Q52 -> 10 | V52: =M52+P52 -> 8 | W52: =N52+P52 -> 5 | X52: =O52+P52 -> 5 | Y52: =_xlfn.XLOOKUP(AA52,Combos!AU:AU,Combos!AT:AT,"",0,1) | Z52: WFU-骑士精神-41145=③ | AA52: WFU-骑士精神-41145 | AB52: ②UW41145骑士精神 | AC52: AF-危险套装-24243.⑤ | AD52: ⑤.AF-危险套装-24243
B53: 1 | E53: =_xlfn.XLOOKUP(G53,Combos!AB:AB,Combos!AA:AA,"",0,1) | G53: Cat Ears | H53: 猫耳 | I53: AF-猫耳发饰-14343 | K53: Trinket | L53: =P53+Q53 -> 7 | M53: 1 | N53: 4 | O53: 3 | P53: 4 | Q53: 3 | R53: =SUM(M53:Q53) -> 15 | S53: =V53+Q53 -> 8 | T53: =W53+Q53 -> 11 | U53: =X53+Q53 -> 10 | V53: =M53+P53 -> 5 | W53: =N53+P53 -> 8 | X53: =O53+P53 -> 7 | Y53: =_xlfn.XLOOKUP(AA53,Combos!AU:AU,Combos!AT:AT,"",0,1) | Z53: AFI-猫耳发饰-14343 | AA53: AFI-猫耳发饰-14343 | AB53: AF14343猫耳 | AC53: F-深V短裙-23343 | AD53: F-深V短裙-23343
A54: Y | B54: 1 | E54: =_xlfn.XLOOKUP(G54,Combos!AB:AB,Combos!AA:AA,"",0,1) | G54: Chocolate Bar | H54: 巧克力棒 | I54: FU-巧克力棒-13344 | K54: Trinket | L54: =P54+Q54 -> 8 | M54: 1 | N54: 3 | O54: 3 | P54: 4 | Q54: 4 | R54: =SUM(M54:Q54) -> 15 | S54: =V54+Q54 -> 9 | T54: =W54+Q54 -> 11 | U54: =X54+Q54 -> 11 | V54: =M54+P54 -> 5 | W54: =N54+P54 -> 7 | X54: =O54+P54 -> 7 | Y54: =_xlfn.XLOOKUP(AA54,Combos!AU:AU,Combos!AT:AT,"",0,1) | Z54: IFU-巧克力棒-13344 | AA54: IFU-巧克力棒-13344 | AB54: FU巧克力棒 13344 | AC54: F-深V上衣-23352 | AD54: F-深V上衣-23352
E55: =_xlfn.XLOOKUP(G55,Combos!AB:AB,Combos!AA:AA,"",0,1) | G55: Airy Bra | H55: 透气文胸 | I55: AI-空气胸罩-14433 | K55: Top | L55: =P55+Q55 -> 6 | M55: 1 | N55: 4 | O55: 4 | P55: 3 | Q55: 3 | R55: =SUM(M55:Q55) -> 15 | S55: =V55+Q55 -> 7 | T55: =W55+Q55 -> 10 | U55: =X55+Q55 -> 10 | V55: =M55+P55 -> 4 | W55: =N55+P55 -> 7 | X55: =O55+P55 -> 7 | Y55: =_xlfn.XLOOKUP(AA55,Combos!AU:AU,Combos!AT:AT,"",0,1) | Z55: AFI-空气胸罩-14433 | AA55: AFI-空气胸罩-14433 | AB55: AI14433轻盈文胸 | AC55: AF-溶解下装-14343 | AD55: AF-溶解下装-14343
A56: Y | C56: X | E56: =_xlfn.XLOOKUP(G56,Combos!AB:AB,Combos!AA:AA,"",0,1) | G56: Irma's Bottom | H56: 厄玛的下装 | I56: AI-艾尔玛的下装-24432 | K56: Bottom | L56: =P56+Q56 -> 5 | M56: 2 | N56: 4 | O56: 4 | P56: 3 | Q56: 2 | R56: =SUM(M56:Q56) -> 15 | S56: =V56+Q56 -> 7 | T56: =W56+Q56 -> 9 | U56: =X56+Q56 -> 9 | V56: =M56+P56 -> 5 | W56: =N56+P56 -> 7 | X56: =O56+P56 -> 7 | Y56: =_xlfn.XLOOKUP(AA56,Combos!AU:AU,Combos!AT:AT,"",0,1) | Z56: AIF-艾尔玛的下装-24432 | AA56: AIF-艾尔玛的下装-24432 | AB56: AI24432伊尔玛下装 | AC56: AF-溶解上衣-15243_9.② | AD56: ②.AF-溶解上衣-15243_9
A57: Y | C57: X | E57: =_xlfn.XLOOKUP(G57,Combos!AB:AB,Combos!AA:AA,"",0,1) | G57: Irma’s Top | H57: 厄玛的上衣 | I57: AI-艾尔玛的上衣-24432 | K57: Top | L57: =P57+Q57 -> 5 | M57: 2 | N57: 4 | O57: 4 | P57: 3 | Q57: 2 | R57: =SUM(M57:Q57) -> 15 | S57: =V57+Q57 -> 7 | T57: =W57+Q57 -> 9 | U57: =X57+Q57 -> 9 | V57: =M57+P57 -> 5 | W57: =N57+P57 -> 7 | X57: =O57+P57 -> 7 | Y57: =_xlfn.XLOOKUP(AA57,Combos!AU:AU,Combos!AT:AT,"",0,1) | Z57: AIF-艾尔玛的上衣-24432 | AA57: AIF-艾尔玛的上衣-24432 | AB57: AI24432伊尔玛的顶 | AC57: IF-狗狗零食-13443 | AD57: IF-狗狗零食-13443
A58: Y | C58: 2 | E58: =_xlfn.XLOOKUP(G58,Combos!AB:AB,Combos!AA:AA,"",0,1) | G58: Cute Brooch | H58: 可爱胸针 | I58: WF-可爱胸针-42342 | K58: Trinket | L58: =P58+Q58 -> 6 | M58: 4 | N58: 2 | O58: 3 | P58: 4 | Q58: 2 | R58: =SUM(M58:Q58) -> 15 | S58: =V58+Q58 -> 10 | T58: =W58+Q58 -> 8 | U58: =X58+Q58 -> 9 | V58: =M58+P58 -> 8 | W58: =N58+P58 -> 6 | X58: =O58+P58 -> 7 | Y58: =_xlfn.XLOOKUP(AA58,Combos!AU:AU,Combos!AT:AT,"",0,1) | Z58: WIF-可爱胸针-42342 | AA58: WIF-可爱胸针-42342 | AB58: WF42342可爱胸针 | AC58: IFU-#支配-11554.① | AD58: ①.IFU-#支配-11554
E59: =_xlfn.XLOOKUP(G59,Combos!AB:AB,Combos!AA:AA,"",0,1) | F59: 3 | G59: Overcharged Tazer | H59: 过载电击枪 | I59: IFU-过载电击器-12444 | K59: Weapon | L59: =P59+Q59 -> 8 | M59: 1 | N59: 2 | O59: 4 | P59: 4 | Q59: 4 | R59: =SUM(M59:Q59) -> 15 | S59: =V59+Q59 -> 9 | T59: =W59+Q59 -> 10 | U59: =X59+Q59 -> 12 | V59: =M59+P59 -> 5 | W59: =N59+P59 -> 6 | X59: =O59+P59 -> 8 | Y59: =_xlfn.XLOOKUP(AA59,Combos!AU:AU,Combos!AT:AT,"",0,1) | Z59: IFU-过载电击器-12444 | AA59: IFU-过载电击器-12444 | AB59: IFU12444过载电击枪 | AC59: AU-破布礼服-24234 | AD59: AU-破布礼服-24234
E60: =_xlfn.XLOOKUP(G60,Combos!AB:AB,Combos!AA:AA,"",0,1) | G60: Tesla Gun | H60: 特斯拉枪 | I60: IF-特斯拉枪-31443 | K60: Weapon | L60: =P60+Q60 -> 7 | M60: 3 | N60: 1 | O60: 4 | P60: 4 | Q60: 3 | R60: =SUM(M60:Q60) -> 15 | S60: =V60+Q60 -> 10 | T60: =W60+Q60 -> 8 | U60: =X60+Q60 -> 11 | V60: =M60+P60 -> 7 | W60: =N60+P60 -> 5 | X60: =O60+P60 -> 8 | Y60: =_xlfn.XLOOKUP(AA60,Combos!AU:AU,Combos!AT:AT,"",0,1) | Z60: WIF-特斯拉枪-31443 | AA60: WIF-特斯拉枪-31443 | AB60: IF31443特斯拉枪 | AC60: F-小黄鸭-33243 | AD60: F-小黄鸭-33243
D61: I伤害最高 | E61: =_xlfn.XLOOKUP(G61,Combos!AB:AB,Combos!AA:AA,"",0,1) | G61: High-Volt Tazer | H61: 高压电击枪 | I61: IF-高压电击器-22443 | K61: Weapon | L61: =P61+Q61 -> 7 | M61: 2 | N61: 2 | O61: 4 | P61: 4 | Q61: 3 | R61: =SUM(M61:Q61) -> 15 | S61: =V61+Q61 -> 9 | T61: =W61+Q61 -> 9 | U61: =X61+Q61 -> 11 | V61: =M61+P61 -> 6 | W61: =N61+P61 -> 6 | X61: =O61+P61 -> 8 | Y61: =_xlfn.XLOOKUP(AA61,Combos!AU:AU,Combos!AT:AT,"",0,1) | Z61: IFU-高压电击器-22443 | AA61: IFU-高压电击器-22443 | AB61: IF22443高压电击枪 | AC61: FU-鸭鸭-23244 | AD61: FU-鸭鸭-23244
B62: 1 | E62: =_xlfn.XLOOKUP(G62,Combos!AB:AB,Combos!AA:AA,"",0,1) | G62: Dog Treat | H62: 狗狗零食 | I62: IF-狗狗零食-13443 | K62: Trinket | L62: =P62+Q62 -> 7 | M62: 1 | N62: 3 | O62: 4 | P62: 4 | Q62: 3 | R62: =SUM(M62:Q62) -> 15 | S62: =V62+Q62 -> 8 | T62: =W62+Q62 -> 10 | U62: =X62+Q62 -> 11 | V62: =M62+P62 -> 5 | W62: =N62+P62 -> 7 | X62: =O62+P62 -> 8 | Y62: =_xlfn.XLOOKUP(AA62,Combos!AU:AU,Combos!AT:AT,"",0,1) | Z62: IFU-狗狗零食-13443 | AA62: IFU-狗狗零食-13443 | AB62: IF13443狗狗零食 | AC62: 伊莲的护符(X)-00000 | AD62: 伊莲的护符(X)-00000
A63: Y | C63: X | E63: =_xlfn.XLOOKUP(G63,Combos!AB:AB,Combos!AA:AA,"",0,1) | G63: Duck | H63: 鸭子 | I63: F-小黄鸭-33243 | K63: Trinket | L63: =P63+Q63 -> 7 | M63: 3 | N63: 3 | O63: 2 | P63: 4 | Q63: 3 | R63: =SUM(M63:Q63) -> 15 | S63: =V63+Q63 -> 10 | T63: =W63+Q63 -> 10 | U63: =X63+Q63 -> 9 | V63: =M63+P63 -> 7 | W63: =N63+P63 -> 7 | X63: =O63+P63 -> 6 | Y63: =_xlfn.XLOOKUP(AA63,Combos!AU:AU,Combos!AT:AT,"",0,1) | Z63: WIF-小黄鸭-33243 | AA63: WIF-小黄鸭-33243 | AB63: F小鸭子33243 | AC63: FU-埃莉诺套装-11155 | AD63: FU-埃莉诺套装-11155
A64: Y | C64: X | E64: =_xlfn.XLOOKUP(G64,Combos!AB:AB,Combos!AA:AA,"",0,1) | G64: Lace-up Shorts | H64: 系带短裤 | I64: IF-系带短裤-23442 | K64: Bottom | L64: =P64+Q64 -> 6 | M64: 2 | N64: 3 | O64: 4 | P64: 4 | Q64: 2 | R64: =SUM(M64:Q64) -> 15 | S64: =V64+Q64 -> 8 | T64: =W64+Q64 -> 9 | U64: =X64+Q64 -> 10 | V64: =M64+P64 -> 6 | W64: =N64+P64 -> 7 | X64: =O64+P64 -> 8 | Y64: =_xlfn.XLOOKUP(AA64,Combos!AU:AU,Combos!AT:AT,"",0,1) | Z64: IFU-系带短裤-23442 | AA64: IFU-系带短裤-23442 | AB64: 系带短裤 | AC64: WU-艾米丽的大佬-41334 | AD64: WU-艾米丽的大佬-41334
A65: Y | C65: 1 | D65: 安德烈亚 | E65: =_xlfn.XLOOKUP(G65,Combos!AB:AB,Combos!AA:AA,"",0,1) | G65: Fireaxe | H65: 消防斧 | I65: IF-消防斧-13443 | K65: Weapon | L65: =P65+Q65 -> 7 | M65: 1 | N65: 3 | O65: 4 | P65: 4 | Q65: 3 | R65: =SUM(M65:Q65) -> 15 | S65: =V65+Q65 -> 8 | T65: =W65+Q65 -> 10 | U65: =X65+Q65 -> 11 | V65: =M65+P65 -> 5 | W65: =N65+P65 -> 7 | X65: =O65+P65 -> 8 | Y65: =_xlfn.XLOOKUP(AA65,Combos!AU:AU,Combos!AT:AT,"",0,1) | Z65: IFU-消防斧-13443 | AA65: IFU-消防斧-13443 | AB65: IF13443火斧 | AC65: WI-艾米丽的小弟们-51423 | AD65: WI-艾米丽的小弟们-51423
E66: =_xlfn.XLOOKUP(G66,Combos!AB:AB,Combos!AA:AA,"",0,1) | G66: Formal Skirt | H66: 正装裙 | I66: IF-正装短裙-31443 | K66: Bottom | L66: =P66+Q66 -> 7 | M66: 3 | N66: 1 | O66: 4 | P66: 4 | Q66: 3 | R66: =SUM(M66:Q66) -> 15 | S66: =V66+Q66 -> 10 | T66: =W66+Q66 -> 8 | U66: =X66+Q66 -> 11 | V66: =M66+P66 -> 7 | W66: =N66+P66 -> 5 | X66: =O66+P66 -> 8 | Y66: =_xlfn.XLOOKUP(AA66,Combos!AU:AU,Combos!AT:AT,"",0,1) | Z66: WIF-正装短裙-31443 | AA66: WIF-正装短裙-31443 | AB66: 正式裙装 | AC66: 能量自动手枪-33333 | AD66: 能量自动手枪-33333
A67: Y | C67: 1 | E67: =_xlfn.XLOOKUP(G67,Combos!AB:AB,Combos!AA:AA,"",0,1) | G67: Prototype Tesla Gun | H67: 原型特斯拉枪 | I67: IF-原型特斯拉枪-31443 | K67: Weapon | L67: =P67+Q67 -> 7 | M67: 3 | N67: 1 | O67: 4 | P67: 4 | Q67: 3 | R67: =SUM(M67:Q67) -> 15 | S67: =V67+Q67 -> 10 | T67: =W67+Q67 -> 8 | U67: =X67+Q67 -> 11 | V67: =M67+P67 -> 7 | W67: =N67+P67 -> 5 | X67: =O67+P67 -> 8 | Y67: =_xlfn.XLOOKUP(AA67,Combos!AU:AU,Combos!AT:AT,"",0,1) | Z67: WIF-原型特斯拉枪-31443 | AA67: WIF-原型特斯拉枪-31443 | AB67: IF31443特斯拉枪原型 | AC67: FU-探险者短裙-13344 | AD67: FU-探险者短裙-13344
B68: 1 | E68: =_xlfn.XLOOKUP(G68,Combos!AB:AB,Combos!AA:AA,"",0,1) | G68: El Patito | H68: 小鸭子 | I68: FU-鸭鸭-23244 | K68: Trinket | L68: =P68+Q68 -> 8 | M68: 2 | N68: 3 | O68: 2 | P68: 4 | Q68: 4 | R68: =SUM(M68:Q68) -> 15 | S68: =V68+Q68 -> 10 | T68: =W68+Q68 -> 11 | U68: =X68+Q68 -> 10 | V68: =M68+P68 -> 6 | W68: =N68+P68 -> 7 | X68: =O68+P68 -> 6 | Y68: =_xlfn.XLOOKUP(AA68,Combos!AU:AU,Combos!AT:AT,"",0,1) | Z68: IFU-鸭鸭-23244 | AA68: IFU-鸭鸭-23244 | AB68: FU艾尔23244 | AC68: F-探险者上衣-13353 | AD68: F-探险者上衣-13353
A69: y | B69: 1 | E69: =_xlfn.XLOOKUP(G69,Combos!AB:AB,Combos!AA:AA,"",0,1) | G69: Explorer's Ribbon | H69: 探险者缎带 | I69: WAI-#探险者的缎带-44433 | K69: Trinket | L69: =P69+Q69 -> 6 | M69: 4 | N69: 4 | O69: 4 | P69: 3 | Q69: 3 | R69: =SUM(M69:Q69) -> 18 | S69: =V69+Q69 -> 10 | T69: =W69+Q69 -> 10 | U69: =X69+Q69 -> 10 | V69: =M69+P69 -> 7 | W69: =N69+P69 -> 7 | X69: =O69+P69 -> 7 | Y69: =_xlfn.XLOOKUP(AA69,Combos!AU:AU,Combos!AT:AT,"",0,1) | Z69: WAI-探险者的缎带-44433 | AA69: WAI-探险者的缎带-44433 | AB69: WAI44433@探险家缎带 | AC69: WAI-#探险者的缎带-44433 | AD69: WAI-#探险者的缎带-44433
A70: Y | C70: 2 | E70: =_xlfn.XLOOKUP(G70,Combos!AB:AB,Combos!AA:AA,"",0,1) | G70: Classy Colours | H70: 优雅色彩 | I70: IU-上流色彩-22434 | K70: Dress | L70: =P70+Q70 -> 7 | M70: 2 | N70: 2 | O70: 4 | P70: 3 | Q70: 4 | R70: =SUM(M70:Q70) -> 15 | S70: =V70+Q70 -> 9 | T70: =W70+Q70 -> 9 | U70: =X70+Q70 -> 11 | V70: =M70+P70 -> 5 | W70: =N70+P70 -> 5 | X70: =O70+P70 -> 7 | Y70: =_xlfn.XLOOKUP(AA70,Combos!AU:AU,Combos!AT:AT,"",0,1) | Z70: IFU-上流色彩-22434 | AA70: IFU-上流色彩-22434 | AB70: ⑤IF434经典色彩 | AC70: AF-无畏战士服-14253.④ | AD70: ④.AF-无畏战士服-14253
A71: y | B71: 1 | E71: =_xlfn.XLOOKUP(G71,Combos!AB:AB,Combos!AA:AA,"",0,1) | G71: Business Ass | H71: 商务下装 | I71: IU-商务下装-31434 | K71: Bottom | L71: =P71+Q71 -> 7 | M71: 3 | N71: 1 | O71: 4 | P71: 3 | Q71: 4 | R71: =SUM(M71:Q71) -> 15 | S71: =V71+Q71 -> 10 | T71: =W71+Q71 -> 8 | U71: =X71+Q71 -> 11 | V71: =M71+P71 -> 6 | W71: =N71+P71 -> 4 | X71: =O71+P71 -> 7 | Y71: =_xlfn.XLOOKUP(AA71,Combos!AU:AU,Combos!AT:AT,"",0,1) | Z71: IFU-商务下装-31434 | AA71: IFU-商务下装-31434 | AB71: ⑤IF434商业助理裙 | AC71: IU-战地医疗兵套装-31434 | AD71: IU-战地医疗兵套装-31434
A72: Y | B72: 1 | E72: =_xlfn.XLOOKUP(G72,Combos!AB:AB,Combos!AA:AA,"",0,1) | G72: Business Top | H72: 商务上衣 | I72: IU-商务上衣-31434 | K72: Top | L72: =P72+Q72 -> 7 | M72: 3 | N72: 1 | O72: 4 | P72: 3 | Q72: 4 | R72: =SUM(M72:Q72) -> 15 | S72: =V72+Q72 -> 10 | T72: =W72+Q72 -> 8 | U72: =X72+Q72 -> 11 | V72: =M72+P72 -> 6 | W72: =N72+P72 -> 4 | X72: =O72+P72 -> 7 | Y72: =_xlfn.XLOOKUP(AA72,Combos!AU:AU,Combos!AT:AT,"",0,1) | Z72: IFU-商务上衣-31434 | AA72: IFU-商务上衣-31434 | AB72: ⑤IF434商业助理衣 | AC72: IF-消防斧-13443 | AD72: IF-消防斧-13443
A73: Y | C73: 1 | D73: 安德烈亚 | E73: =_xlfn.XLOOKUP(G73,Combos!AB:AB,Combos!AA:AA,"",0,1) | F73: 1 | G73: Cloe’s Sets | H73: 克洛伊的套装 | I73: ③.IF-克洛伊的套装-13542 | K73: Dress | L73: =P73+Q73 -> 6 | M73: 1 | N73: 3 | O73: 5 | P73: 4 | Q73: 2 | R73: =SUM(M73:Q73) -> 15 | S73: =V73+Q73 -> 7 | T73: =W73+Q73 -> 9 | U73: =X73+Q73 -> 11 | V73: =M73+P73 -> 5 | W73: =N73+P73 -> 7 | X73: =O73+P73 -> 9 | Y73: =_xlfn.XLOOKUP(AA73,Combos!AU:AU,Combos!AT:AT,"",0,1) | Z73: IAF-克洛伊的套装-13542=③ | AA73: IAF-克洛伊的套装-13542 | AB73: ③I13542克洛伊套 | AC73: U-火焰喷射器-23334 | AD73: U-火焰喷射器-23334
A74: Y | C74: 2 | E74: =_xlfn.XLOOKUP(G74,Combos!AB:AB,Combos!AA:AA,"",0,1) | G74: Wire Panties | H74: 钢丝内裤 | I74: IU-铁丝内裤-21435 | K74: Bottom | L74: =P74+Q74 -> 8 | M74: 2 | N74: 1 | O74: 4 | P74: 3 | Q74: 5 | R74: =SUM(M74:Q74) -> 15 | S74: =V74+Q74 -> 10 | T74: =W74+Q74 -> 9 | U74: =X74+Q74 -> 12 | V74: =M74+P74 -> 5 | W74: =N74+P74 -> 4 | X74: =O74+P74 -> 7 | Y74: =_xlfn.XLOOKUP(AA74,Combos!AU:AU,Combos!AT:AT,"",0,1) | Z74: UI-铁丝内裤-21435 | AA74: IFU-铁丝内裤-21435 | AB74: U金属丝内裤 | AC74: AFU-燃烧紧身裤-14244_3.③ | AD74: ③.AFU-燃烧紧身裤-14244_3
A75: Y | C75: X | E75: =_xlfn.XLOOKUP(G75,Combos!AB:AB,Combos!AA:AA,"",0,1) | G75: Full Bra | H75: 全罩杯文胸 | I75: I-全罩胸罩-33432 | K75: Top | L75: =P75+Q75 -> 5 | M75: 3 | N75: 3 | O75: 4 | P75: 3 | Q75: 2 | R75: =SUM(M75:Q75) -> 15 | S75: =V75+Q75 -> 8 | T75: =W75+Q75 -> 8 | U75: =X75+Q75 -> 9 | V75: =M75+P75 -> 6 | W75: =N75+P75 -> 6 | X75: =O75+P75 -> 7 | Y75: =_xlfn.XLOOKUP(AA75,Combos!AU:AU,Combos!AT:AT,"",0,1) | Z75: AIF-全罩胸罩-33432 | AA75: AIF-全罩胸罩-33432 | AB75: 全罩杯文胸 | AC75: AF-燃烧上衣-14343 | AD75: AF-燃烧上衣-14343
A76: Y | C76: 2 | E76: =_xlfn.XLOOKUP(G76,Combos!AB:AB,Combos!AA:AA,"",0,1) | G76: Neck-tied Bra | H76: 系颈文胸 | I76: I-系领胸罩-32433 | K76: Top | L76: =P76+Q76 -> 6 | M76: 3 | N76: 2 | O76: 4 | P76: 3 | Q76: 3 | R76: =SUM(M76:Q76) -> 15 | S76: =V76+Q76 -> 9 | T76: =W76+Q76 -> 8 | U76: =X76+Q76 -> 10 | V76: =M76+P76 -> 6 | W76: =N76+P76 -> 5 | X76: =O76+P76 -> 7 | Y76: =_xlfn.XLOOKUP(AA76,Combos!AU:AU,Combos!AT:AT,"",0,1) | Z76: WIF-系领胸罩-32433 | AA76: WIF-系领胸罩-32433 | AB76: 颈系式胸罩 | AC76: IF-正装短裙-31443 | AD76: IF-正装短裙-31443
A77: Y | C77: 2 | E77: =_xlfn.XLOOKUP(G77,Combos!AB:AB,Combos!AA:AA,"",0,1) | G77: Small Fireaxe | H77: 小消防斧 | I77: I-小型消防斧-23433 | K77: Weapon | L77: =P77+Q77 -> 6 | M77: 2 | N77: 3 | O77: 4 | P77: 3 | Q77: 3 | R77: =SUM(M77:Q77) -> 15 | S77: =V77+Q77 -> 8 | T77: =W77+Q77 -> 9 | U77: =X77+Q77 -> 10 | V77: =M77+P77 -> 5 | W77: =N77+P77 -> 6 | X77: =O77+P77 -> 7 | Y77: =_xlfn.XLOOKUP(AA77,Combos!AU:AU,Combos!AT:AT,"",0,1) | Z77: IFU-小型消防斧-23433 | AA77: IFU-小型消防斧-23433 | AB77: 小火斧 | AC77: 福克希套装-33333 | AD77: 福克希套装-33333
A78: Y | C78: 2 | E78: =_xlfn.XLOOKUP(G78,Combos!AB:AB,Combos!AA:AA,"",0,1) | G78: Last Resort | H78: 最后手段 | I78: I-最后手段-32433 | K78: Weapon | L78: =P78+Q78 -> 6 | M78: 3 | N78: 2 | O78: 4 | P78: 3 | Q78: 3 | R78: =SUM(M78:Q78) -> 15 | S78: =V78+Q78 -> 9 | T78: =W78+Q78 -> 8 | U78: =X78+Q78 -> 10 | V78: =M78+P78 -> 6 | W78: =N78+P78 -> 5 | X78: =O78+P78 -> 7 | Y78: =_xlfn.XLOOKUP(AA78,Combos!AU:AU,Combos!AT:AT,"",0,1) | Z78: WIF-最后手段-32433 | AA78: WIF-最后手段-32433 | AB78: 最后手段(小枪比I32433 | AC78: WA-流苏长裤-44331 | AD78: WA-流苏长裤-44331
E79: =_xlfn.XLOOKUP(G79,Combos!AB:AB,Combos!AA:AA,"",0,1) | G79: Cosmic Attire | H79: 宇宙装束 | I79: WI-宇宙装束-51513 | K79: Dress | L79: =P79+Q79 -> 4 | M79: 5 | N79: 1 | O79: 5 | P79: 1 | Q79: 3 | R79: =SUM(M79:Q79) -> 15 | S79: =V79+Q79 -> 9 | T79: =W79+Q79 -> 5 | U79: =X79+Q79 -> 9 | V79: =M79+P79 -> 6 | W79: =N79+P79 -> 2 | X79: =O79+P79 -> 6 | Y79: =_xlfn.XLOOKUP(AA79,Combos!AU:AU,Combos!AT:AT,"",0,1) | Z79: WI-宇宙装束-51513 | AA79: WIU-宇宙装束-51513 | AB79: 宇宙服饰 | AC79: W-流苏上衣-43332 | AD79: W-流苏上衣-43332
A80: Y | C80: 1 | E80: =_xlfn.XLOOKUP(G80,Combos!AB:AB,Combos!AA:AA,"",0,1) | G80: Hair Dye | H80: 染发剂 | I80: W-染发剂-53133 | K80: Trinket | L80: =P80+Q80 -> 6 | M80: 5 | N80: 3 | O80: 1 | P80: 3 | Q80: 3 | R80: =SUM(M80:Q80) -> 15 | S80: =V80+Q80 -> 11 | T80: =W80+Q80 -> 9 | U80: =X80+Q80 -> 7 | V80: =M80+P80 -> 8 | W80: =N80+P80 -> 6 | X80: =O80+P80 -> 4 | Y80: =_xlfn.XLOOKUP(AA80,Combos!AU:AU,Combos!AT:AT,"",0,1) | Z80: WIF-染发剂-53133 | AA80: WIF-染发剂-53133 | AB80: W53133染发剂 | AC80: WF-冰霜装束-51153.① | AD80: ①.WF-冰霜装束-51153
A81: Y | C81: 2 | E81: =_xlfn.XLOOKUP(G81,Combos!AB:AB,Combos!AA:AA,"",0,1) | F81: 2 | G81: Handmade Lollipop | H81: 手工棒棒糖 | I81: IUF-手工棒棒糖-11445 | K81: Trinket | L81: =P81+Q81 -> 9 | M81: 1 | N81: 1 | O81: 4 | P81: 4 | Q81: 5 | R81: =SUM(M81:Q81) -> 15 | S81: =V81+Q81 -> 10 | T81: =W81+Q81 -> 10 | U81: =X81+Q81 -> 13 | V81: =M81+P81 -> 5 | W81: =N81+P81 -> 5 | X81: =O81+P81 -> 8 | Y81: =_xlfn.XLOOKUP(AA81,Combos!AU:AU,Combos!AT:AT,"",0,1) | Z81: IFU-手工棒棒糖-11445 | AA81: IFU-手工棒棒糖-11445 | AB81: IFU11445手工棒棒糖 | AC81: I-全罩胸罩-33432 | AD81: I-全罩胸罩-33432
A82: Y | C82: 2 | E82: =_xlfn.XLOOKUP(G82,Combos!AB:AB,Combos!AA:AA,"",0,1) | F82: 3 | G82: Lollipop | H82: 棒棒糖 | I82: IFU-棒棒糖-12444 | K82: Trinket | L82: =P82+Q82 -> 8 | M82: 1 | N82: 2 | O82: 4 | P82: 4 | Q82: 4 | R82: =SUM(M82:Q82) -> 15 | S82: =V82+Q82 -> 9 | T82: =W82+Q82 -> 10 | U82: =X82+Q82 -> 12 | V82: =M82+P82 -> 5 | W82: =N82+P82 -> 6 | X82: =O82+P82 -> 8 | Y82: =_xlfn.XLOOKUP(AA82,Combos!AU:AU,Combos!AT:AT,"",0,1) | Z82: IFU-棒棒糖-12444 | AA82: IFU-棒棒糖-12444 | AB82: IFU12444棒棒糖 | AC82: FU-盖亚的套装-13254 | AD82: FU-盖亚的套装-13254
A83: Y | E83: =_xlfn.XLOOKUP(G83,Combos!AB:AB,Combos!AA:AA,"",0,1) | G83: Crazy’s Sets | H83: 疯狂的套装 | I83: ⑥.AF-疯狂套装-24342 | K83: Dress | L83: =P83+Q83 -> 6 | M83: 2 | N83: 4 | O83: 3 | P83: 4 | Q83: 2 | R83: =SUM(M83:Q83) -> 15 | S83: =V83+Q83 -> 8 | T83: =W83+Q83 -> 10 | U83: =X83+Q83 -> 9 | V83: =M83+P83 -> 6 | W83: =N83+P83 -> 8 | X83: =O83+P83 -> 7 | Y83: =_xlfn.XLOOKUP(AA83,Combos!AU:AU,Combos!AT:AT,"",0,1) | Z83: AFI-疯狂套装-24342=⑥ | AA83: AFI-疯狂套装-24342 | AB83: ⑤A24342疯狂套装 | AC83: FU-盖亚的上衣-13254 | AD83: FU-盖亚的上衣-13254
A84: Y | B84: 1 | E84: =_xlfn.XLOOKUP(G84,Combos!AB:AB,Combos!AA:AA,"",0,1) | G84: Love Cards | H84: 爱之卡片 | I84: WF-爱欲卡牌-41343 | K84: Trinket | L84: =P84+Q84 -> 7 | M84: 4 | N84: 1 | O84: 3 | P84: 4 | Q84: 3 | R84: =SUM(M84:Q84) -> 15 | S84: =V84+Q84 -> 11 | T84: =W84+Q84 -> 8 | U84: =X84+Q84 -> 10 | V84: =M84+P84 -> 8 | W84: =N84+P84 -> 5 | X84: =O84+P84 -> 7 | Y84: =_xlfn.XLOOKUP(AA84,Combos!AU:AU,Combos!AT:AT,"",0,1) | Z84: WAI-爱欲卡牌-41343 | AA84: WAI-爱欲卡牌-41343 | AB84: WF41343爱心卡片 | AC84: AUF-盖亚的下装-14145_2 | AD84: AUF-盖亚的下装-14145_2
A85: Y | C85: 1 | E85: =_xlfn.XLOOKUP(G85,Combos!AB:AB,Combos!AA:AA,"",0,1) | G85: Lovense Gift | H85: 震动棒 | I85: I震动棒-13533 | K85: Trinket | L85: =P85+Q85 -> 6 | M85: 1 | N85: 3 | O85: 5 | P85: 3 | Q85: 3 | R85: =SUM(M85:Q85) -> 15 | S85: =V85+Q85 -> 7 | T85: =W85+Q85 -> 9 | U85: =X85+Q85 -> 11 | V85: =M85+P85 -> 4 | W85: =N85+P85 -> 6 | X85: =O85+P85 -> 8 | Y85: =_xlfn.XLOOKUP(AA85,Combos!AU:AU,Combos!AT:AT,"",0,1) | Z85: IAL-Lovense的礼物-13533 | AA85: IAL-Lovense的礼物-13533 | AB85: I13533震动棒 | AC85: WU-吊带袜腰带-41334 | AD85: WU-吊带袜腰带-41334
C86: X | E86: =_xlfn.XLOOKUP(G86,Combos!AB:AB,Combos!AA:AA,"",0,1) | G86: Emily's Underlings | H86: 艾米莉的下属装 | I86: WI-艾米丽的小弟们-51423 | K86: Bottom | L86: =P86+Q86 -> 5 | M86: 5 | N86: 1 | O86: 4 | P86: 2 | Q86: 3 | R86: =SUM(M86:Q86) -> 15 | S86: =V86+Q86 -> 10 | T86: =W86+Q86 -> 6 | U86: =X86+Q86 -> 9 | V86: =M86+P86 -> 7 | W86: =N86+P86 -> 3 | X86: =O86+P86 -> 6 | Y86: =_xlfn.XLOOKUP(AA86,Combos!AU:AU,Combos!AT:AT,"",0,1) | Z86: WIF-艾米丽的小弟们-51423 | AA86: WIF-艾米丽的小弟们-51423 | AB86: WI艾米丽的下属 | AC86: FU-巨型扳手-11355 | AD86: FU-巨型扳手-11355
A87: Y | C87: 2 | E87: =_xlfn.XLOOKUP(G87,Combos!AB:AB,Combos!AA:AA,"",0,1) | G87: Subtle Shorts | H87: 精致短裤 | I87: WI-微妙的短裤-41433 | K87: Bottom | L87: =P87+Q87 -> 6 | M87: 4 | N87: 1 | O87: 4 | P87: 3 | Q87: 3 | R87: =SUM(M87:Q87) -> 15 | S87: =V87+Q87 -> 10 | T87: =W87+Q87 -> 7 | U87: =X87+Q87 -> 10 | V87: =M87+P87 -> 7 | W87: =N87+P87 -> 4 | X87: =O87+P87 -> 7 | Y87: =_xlfn.XLOOKUP(AA87,Combos!AU:AU,Combos!AT:AT,"",0,1) | Z87: WIF-微妙的短裤-41433 | AA87: WIF-微妙的短裤-41433 | AB87: 精致短裤 | AC87: FU-高尔夫球杆-13344 | AD87: FU-高尔夫球杆-13344
A88: Y | C88: X | E88: =_xlfn.XLOOKUP(G88,Combos!AB:AB,Combos!AA:AA,"",0,1) | G88: Cosmic Attire (top) | H88: 宇宙装束（上衣） | I88: WI-宇宙装束（上衣）-43422 | K88: Top | L88: =P88+Q88 -> 4 | M88: 4 | N88: 3 | O88: 4 | P88: 2 | Q88: 2 | R88: =SUM(M88:Q88) -> 15 | S88: =V88+Q88 -> 8 | T88: =W88+Q88 -> 7 | U88: =X88+Q88 -> 8 | V88: =M88+P88 -> 6 | W88: =N88+P88 -> 5 | X88: =O88+P88 -> 6 | Y88: =_xlfn.XLOOKUP(AA88,Combos!AU:AU,Combos!AT:AT,"",0,1) | Z88: WAI-宇宙装束（上衣）-43422 | AA88: WAI-宇宙装束（上衣）-43422 | AB88: 宇宙服饰上衣 | AC88: W-枪手长裤-42333 | AD88: W-枪手长裤-42333
A89: Y | C89: 2 | D89: + | E89: =_xlfn.XLOOKUP(G89,Combos!AB:AB,Combos!AA:AA,"",0,1) | G89: Serpentine Top | H89: 蛇纹上衣 | I89: ④.WF-蛇纹上衣-41343 | K89: Top | L89: =P89+Q89 -> 7 | M89: 4 | N89: 1 | O89: 3 | P89: 4 | Q89: 3 | R89: =SUM(M89:Q89) -> 15 | S89: =V89+Q89 -> 11 | T89: =W89+Q89 -> 8 | U89: =X89+Q89 -> 10 | V89: =M89+P89 -> 8 | W89: =N89+P89 -> 5 | X89: =O89+P89 -> 7 | Y89: =_xlfn.XLOOKUP(AA89,Combos!AU:AU,Combos!AT:AT,"",0,1) | Z89: WIF-蛇纹上衣-41343=④ | AA89: WIF-蛇纹上衣-41343 | AB89: 蛇形顶 | AC89: W-枪手上衣-51333 | AD89: W-枪手上衣-51333
A90: Y | C90: 1 | E90: =_xlfn.XLOOKUP(G90,Combos!AB:AB,Combos!AA:AA,"",0,1) | F90: 3 | G90: Cute Dress | H90: 可爱连衣裙 | I90: ④.IFU-可爱连衣裙-12444 | K90: Dress | L90: =P90+Q90 -> 8 | M90: 1 | N90: 2 | O90: 4 | P90: 4 | Q90: 4 | R90: =SUM(M90:Q90) -> 15 | S90: =V90+Q90 -> 9 | T90: =W90+Q90 -> 10 | U90: =X90+Q90 -> 12 | V90: =M90+P90 -> 5 | W90: =N90+P90 -> 6 | X90: =O90+P90 -> 8 | Y90: =_xlfn.XLOOKUP(AA90,Combos!AU:AU,Combos!AT:AT,"",0,1) | Z90: IFU-可爱连衣裙-12444=④ | AA90: IFU-可爱连衣裙-12444 | AB90: ④I12444可爱连裙 | AC90: W-染发剂-53133 | AD90: W-染发剂-53133
B91: 1 | G91: Dahia's Rituals | H91: 达希亚的仪式 | I91: 达希亚的仪式(X)-00000 | K91: Dress | L91: =P91+Q91 -> 0 | M91: 0 | N91: 0 | O91: 0 | P91: 0 | Q91: 0 | R91: =SUM(M91:Q91) -> 0 | S91: =V91+Q91 -> 0 | T91: =W91+Q91 -> 0 | U91: =X91+Q91 -> 0 | V91: =M91+P91 -> 0 | W91: =N91+P91 -> 0 | X91: =O91+P91 -> 0 | Z91: 达希亚的仪式(X)-00000 | AA91: 达希亚的仪式(X)-00000 | AB91: (?)达希亚的仪式 | AC91: IUF-手工棒棒糖-11445 | AD91: IUF-手工棒棒糖-11445
A92: Y | E92: =_xlfn.XLOOKUP(G92,Combos!AB:AB,Combos!AA:AA,"",0,1) | G92: Dangerous Set | H92: 危险套装 | I92: ⑤.AF-危险套装-24243 | K92: Dress | L92: =P92+Q92 -> 7 | M92: 2 | N92: 4 | O92: 2 | P92: 4 | Q92: 3 | R92: =SUM(M92:Q92) -> 15 | S92: =V92+Q92 -> 9 | T92: =W92+Q92 -> 11 | U92: =X92+Q92 -> 9 | V92: =M92+P92 -> 6 | W92: =N92+P92 -> 8 | X92: =O92+P92 -> 6 | Y92: =_xlfn.XLOOKUP(AA92,Combos!AU:AU,Combos!AT:AT,"",0,1) | Z92: AIF-危险套装-24243=⑤ | AA92: AIF-危险套装-24243 | AB92: ⑤A24243危险套装 | AC92: WAI-#痛苦先驱-54511.C | AD92: C.WAI-#痛苦先驱-54511
B93: 1 | E93: =_xlfn.XLOOKUP(G93,Combos!AB:AB,Combos!AA:AA,"",0,1) | F93: 1 | G93: Domination | H93: 支配 | I93: ①.IFU-#支配-11554 | K93: Dress | L93: =P93+Q93 -> 9 | M93: 1 | N93: 1 | O93: 5 | P93: 5 | Q93: 4 | R93: =SUM(M93:Q93) -> 16 | S93: =V93+Q93 -> 10 | T93: =W93+Q93 -> 10 | U93: =X93+Q93 -> 14 | V93: =M93+P93 -> 6 | W93: =N93+P93 -> 6 | X93: =O93+P93 -> 10 | Y93: =_xlfn.XLOOKUP(AA93,Combos!AU:AU,Combos!AT:AT,"",0,1) | Z93: IFU-支配-11554=① | AA93: IFU-支配-11554 | AB93: ①IF11554@支配 | AC93: WF-鱼叉枪-41343 | AD93: WF-鱼叉枪-41343
A94: Y | C94: X | E94: =_xlfn.XLOOKUP(G94,Combos!AB:AB,Combos!AA:AA,"",0,1) | G94: XX’s Formal Shirt | H94: XX的正式衬衫 | I94: AF-XX的正式衬衫-24342 | K94: Top | L94: =P94+Q94 -> 6 | M94: 2 | N94: 4 | O94: 3 | P94: 4 | Q94: 2 | R94: =SUM(M94:Q94) -> 15 | S94: =V94+Q94 -> 8 | T94: =W94+Q94 -> 10 | U94: =X94+Q94 -> 9 | V94: =M94+P94 -> 6 | W94: =N94+P94 -> 8 | X94: =O94+P94 -> 7 | Y94: =_xlfn.XLOOKUP(AA94,Combos!AU:AU,Combos!AT:AT,"",0,1) | Z94: AIF-XX的正式衬衫-24342 | AA94: AIF-XX的正式衬衫-24342 | AB94: XX的正式衬衫 | AC94: AFU-重型水管-14244 | AD94: AFU-重型水管-14244
A95: Y | C95: X | E95: =_xlfn.XLOOKUP(G95,Combos!AB:AB,Combos!AA:AA,"",0,1) | G95: Dagger | H95: 匕首 | I95: AF-匕首-24342 | K95: Weapon | L95: =P95+Q95 -> 6 | M95: 2 | N95: 4 | O95: 3 | P95: 4 | Q95: 2 | R95: =SUM(M95:Q95) -> 15 | S95: =V95+Q95 -> 8 | T95: =W95+Q95 -> 10 | U95: =X95+Q95 -> 9 | V95: =M95+P95 -> 6 | W95: =N95+P95 -> 8 | X95: =O95+P95 -> 7 | Y95: =_xlfn.XLOOKUP(AA95,Combos!AU:AU,Combos!AT:AT,"",0,1) | Z95: AFI-匕首-24342 | AA95: AFI-匕首-24342 | AB95: AF24342匕首 | AC95: FU-重型扳手-11355 | AD95: FU-重型扳手-11355
A96: Y | C96: X | E96: =_xlfn.XLOOKUP(G96,Combos!AB:AB,Combos!AA:AA,"",0,1) | G96: Makeup Kit | H96: 化妆包 | I96: F-化妆包-33342 | K96: Trinket | L96: =P96+Q96 -> 6 | M96: 3 | N96: 3 | O96: 3 | P96: 4 | Q96: 2 | R96: =SUM(M96:Q96) -> 15 | S96: =V96+Q96 -> 9 | T96: =W96+Q96 -> 9 | U96: =X96+Q96 -> 9 | V96: =M96+P96 -> 7 | W96: =N96+P96 -> 7 | X96: =O96+P96 -> 7 | Y96: =_xlfn.XLOOKUP(AA96,Combos!AU:AU,Combos!AT:AT,"",0,1) | Z96: AIF-化妆包-33342 | AA96: AIF-化妆包-33342 | AB96: F化妆盒33342 | AC96: IF-高压电击器-22443 | AD96: IF-高压电击器-22443
A97: Y | C97: 2 | E97: =_xlfn.XLOOKUP(G97,Combos!AB:AB,Combos!AA:AA,"",0,1) | G97: Starfish Bra | H97: 海星文胸 | I97: AF-海星胸罩-14343 | K97: Top | L97: =P97+Q97 -> 7 | M97: 1 | N97: 4 | O97: 3 | P97: 4 | Q97: 3 | R97: =SUM(M97:Q97) -> 15 | S97: =V97+Q97 -> 8 | T97: =W97+Q97 -> 11 | U97: =X97+Q97 -> 10 | V97: =M97+P97 -> 5 | W97: =N97+P97 -> 8 | X97: =O97+P97 -> 7 | Y97: =_xlfn.XLOOKUP(AA97,Combos!AU:AU,Combos!AT:AT,"",0,1) | Z97: AFI-海星胸罩-14343 | AA97: AFI-海星胸罩-14343 | AB97: 海星胸罩 | AC97: A-狩猎匕首-24333 | AD97: A-狩猎匕首-24333
A98: y | E98: =_xlfn.XLOOKUP(G98,Combos!AB:AB,Combos!AA:AA,"",0,1) | G98: Sea-themed Skirt | H98: 海洋主题裙 | I98: AF-海洋主题短裙-14343 | K98: Bottom | L98: =P98+Q98 -> 7 | M98: 1 | N98: 4 | O98: 3 | P98: 4 | Q98: 3 | R98: =SUM(M98:Q98) -> 15 | S98: =V98+Q98 -> 8 | T98: =W98+Q98 -> 11 | U98: =X98+Q98 -> 10 | V98: =M98+P98 -> 5 | W98: =N98+P98 -> 8 | X98: =O98+P98 -> 7 | Y98: =_xlfn.XLOOKUP(AA98,Combos!AU:AU,Combos!AT:AT,"",0,1) | Z98: AFI-海洋主题短裙-14343 | AA98: AFI-海洋主题短裙-14343 | AB98: 海洋主题裙子 | AC98: F-改良霰弹枪-32352 | AD98: F-改良霰弹枪-32352
E99: =_xlfn.XLOOKUP(G99,Combos!AB:AB,Combos!AA:AA,"",0,1) | G99: Sea-themed Top | H99: 海洋上衣 | I99: AF-海洋主题上衣-14343 | K99: Top | L99: =P99+Q99 -> 7 | M99: 1 | N99: 4 | O99: 3 | P99: 4 | Q99: 3 | R99: =SUM(M99:Q99) -> 15 | S99: =V99+Q99 -> 8 | T99: =W99+Q99 -> 11 | U99: =X99+Q99 -> 10 | V99: =M99+P99 -> 5 | W99: =N99+P99 -> 8 | X99: =O99+P99 -> 7 | Y99: =_xlfn.XLOOKUP(AA99,Combos!AU:AU,Combos!AT:AT,"",0,1) | Z99: AFI-海洋主题上衣-14343 | AA99: AFI-海洋主题上衣-14343 | AB99: 海洋主题上衣 | AC99: WF-渗透者套装-41343.④ | AD99: ④.WF-渗透者套装-41343
A100: Y | C100: 2 | D100: tess | E100: =_xlfn.XLOOKUP(G100,Combos!AB:AB,Combos!AA:AA,"",0,1) | G100: Pipe | H100: 水管 | I100: AF-水管-14343 | K100: Weapon | L100: =P100+Q100 -> 7 | M100: 1 | N100: 4 | O100: 3 | P100: 4 | Q100: 3 | R100: =SUM(M100:Q100) -> 15 | S100: =V100+Q100 -> 8 | T100: =W100+Q100 -> 11 | U100: =X100+Q100 -> 10 | V100: =M100+P100 -> 5 | W100: =N100+P100 -> 8 | X100: =O100+P100 -> 7 | Y100: =_xlfn.XLOOKUP(AA100,Combos!AU:AU,Combos!AT:AT,"",0,1) | Z100: AIF-水管-14343 | AA100: AIF-水管-14343 | AB100: AF14343管道 | AC100: AI-艾尔玛的上衣-24432 | AD100: AI-艾尔玛的上衣-24432
...

Sheet Weapons
I1: 列1 | J1: Owned | K1: Order | L1: Name | M1: 列12 | N1: W | O1: A | P1: I | Q1: F | R1: U | S1: Stat | T1: Boost | AN1: Name | AO1: W | AP1: A | AQ1: I | AR1: F | AS1: U | AT1: Order
I2: =IF(_xlfn.XLOOKUP(L2,全装!G:G,全装!A:A,"")="Y","Y","") | J2: Yes | K2: 3 | L2: Assassin’s Dagger | M2: 刺客匕首 | N2: 1 | O2: 5 | P2: 3 | Q2: 4 | R2: 2 | S2: A | AN2: Amorous Bow | AT2: 1
I3: =IF(_xlfn.XLOOKUP(L3,全装!G:G,全装!A:A,"")="Y","Y","") -> Y | J3: Yes | K3: 5 | L3: Butcher’s Chopper | M3: 屠夫砍刀 | N3: 1 | O3: 4 | P3: 2 | Q3: 4 | R3: 4 | S3: A | T3: A + F + U | V3: Name | W3: Rarity | X3: Level | AN3: XX's Last Resort | AT3: 2
I4: =IF(_xlfn.XLOOKUP(L4,全装!G:G,全装!A:A,"")="Y","Y","") -> Y | J4: Yes | K4: 8 | L4: Heavy Pipe | M4: 重型管道 | N4: 1 | O4: 4 | P4: 2 | Q4: 4 | R4: 4 | S4: A | T4: A + F + U | V4: Flamethrower | W4: epic | X4: 30 | AT4: 3
I5: =IF(_xlfn.XLOOKUP(L5,全装!G:G,全装!A:A,"")="Y","Y","") | J5: Yes | K5: 9 | L5: Reinforced Pipe | M5: 加固管道 | N5: 1 | O5: 4 | P5: 2 | Q5: 4 | R5: 4 | S5: A | W5: W | X5: A | Y5: I | Z5: F | AA5: U | AN5: Katana | AT5: 4
I6: =IF(_xlfn.XLOOKUP(L6,全装!G:G,全装!A:A,"")="Y","Y","") -> Y | J6: Yes | K6: 15 | L6: Wrench | M6: 扳手 | N6: 1 | O6: 1 | P6: 3 | Q6: 5 | R6: 5 | S6: A | T6: F + U | V6: Results | W6: =Weapon_Calc_Base_Stat_W+((Weapon_Calc_Level-1)*Weapon_Calc_Progress_Num_W) -> 59.5 | X6: =Weapon_Calc_Base_Stat_A+((Weapon_Calc_Level-1)*Weapon_Calc_Progress_Num_A) -> 78 | Y6: =Weapon_Calc_Base_Stat_I+((Weapon_Calc_Level-1)*Weapon_Calc_Progress_Num_I) -> 78 | Z6: =Weapon_Calc_Base_Stat_F+((Weapon_Calc_Level-1)*Weapon_Calc_Progress_Num_F) -> 78 | AA6: =Weapon_Calc_Base_Stat_U+((Weapon_Calc_Level-1)*Weapon_Calc_Progress_Num_U) -> 96.5 | AN6: Tazer | AT6: 5
I7: =IF(_xlfn.XLOOKUP(L7,全装!G:G,全装!A:A,"")="Y","Y","") -> Y | J7: Yes | K7: 16 | L7: Heavy Wrench | M7: 重型扳手 | N7: 1 | O7: 1 | P7: 3 | Q7: 5 | R7: 5 | S7: A | W7: 78 | X7: 59.5 | Y7: 59.5 | Z7: 96.5 | AA7: 96.5 | AN7: SMGl | AT7: 6
I8: =IF(_xlfn.XLOOKUP(L8,全装!G:G,全装!A:A,"")="Y","Y","") -> Y | J8: Yes | K8: 17 | L8: Giant Wrench | M8: 巨型扳手 | N8: 1 | O8: 1 | P8: 3 | Q8: 5 | R8: 5 | S8: A | V8: Stat Tiers | W8: =VLOOKUP(Weapon_Calc_Name,Weapons!Weapon_Calc_Base_Stat_List,2) -> 2 | X8: =VLOOKUP(Weapon_Calc_Name,Weapons!Weapon_Calc_Base_Stat_List,3) -> 3 | Y8: =VLOOKUP(Weapon_Calc_Name,Weapons!Weapon_Calc_Base_Stat_List,4) -> 3 | Z8: =VLOOKUP(Weapon_Calc_Name,Weapons!Weapon_Calc_Base_Stat_List,5) -> 3 | AA8: =VLOOKUP(Weapon_Calc_Name,Weapons!Weapon_Calc_Base_Stat_List,6) -> 4 | AN8: Spiked Club | AT8: 7
I9: =IF(_xlfn.XLOOKUP(L9,全装!G:G,全装!A:A,"")="Y","Y","") | J9: Yes | K9: 24 | L9: Tesla Gun | M9: 特斯拉枪 | N9: 3 | O9: 1 | P9: 4 | Q9: 4 | R9: 3 | S9: I | V9: Progress Number | W9: =IF(Weapon_Calc_Tier_W=1,1,IF(Weapon_Calc_Tier_W=2,1.5,IF(Weapon_Calc_Tier_W=3,2,IF(Weapon_Calc_Tier_W=4,2.5,IF(Weapon_Calc_Tier_W=5,3,"error6"))))) -> 1.5 | X9: =IF(Weapon_Calc_Tier_A=1,1,IF(Weapon_Calc_Tier_A=2,1.5,IF(Weapon_Calc_Tier_A=3,2,IF(Weapon_Calc_Tier_A=4,2.5,IF(Weapon_Calc_Tier_A=5,3,"error6"))))) -> 2 | Y9: =IF(Weapon_Calc_Tier_I=1,1,IF(Weapon_Calc_Tier_I=2,1.5,IF(Weapon_Calc_Tier_I=3,2,IF(Weapon_Calc_Tier_I=4,2.5,IF(Weapon_Calc_Tier_I=5,3,"error6"))))) -> 2 | Z9: =IF(Weapon_Calc_Tier_F=1,1,IF(Weapon_Calc_Tier_F=2,1.5,IF(Weapon_Calc_Tier_F=3,2,IF(Weapon_Calc_Tier_F=4,2.5,IF(Weapon_Calc_Tier_F=5,3,"error6"))))) -> 2 | AA9: =IF(Weapon_Calc_Tier_U=1,1,IF(Weapon_Calc_Tier_U=2,1.5,IF(Weapon_Calc_Tier_U=3,2,IF(Weapon_Calc_Tier_U=4,2.5,IF(Weapon_Calc_Tier_U=5,3,"error6"))))) -> 2.5 | AT9: 8
I10: =IF(_xlfn.XLOOKUP(L10,全装!G:G,全装!A:A,"")="Y","Y","") -> Y | J10: Yes | K10: 25 | L10: Prototype Tesla Gun | M10: 原型特斯拉枪 | N10: 3 | O10: 1 | P10: 4 | Q10: 4 | R10: 3 | S10: I | T10: I + F | V10: Base Stat (Lvl 1) | W10: =IF(Weapon_Calc_Rarity="common",(IF(Weapon_Calc_Tier_W=1,7,IF(Weapon_Calc_Tier_W=2,8,IF(Weapon_Calc_Tier_W=3,11,IF(Weapon_Calc_Tier_W=4,12,IF(Weapon_Calc_Tier_W=5,14)))))),IF(Weapon_Calc_Rarity="rare",(IF(Weapon_Calc_Tier_W=1,8,IF(Weapon_Calc_Tier_W=2,11,IF(Weapon_Calc_Tier_W=3,14,IF(Weapon_Calc_Tier_W=4,17,IF(Weapon_Calc_Tier_W=5,21)))))),IF(Weapon_Calc_Rarity="epic",(IF(Weapon_Calc_Tier_W=1,12,IF(Weapon_Calc_Tier_W=2,16,IF(Weapon_Calc_Tier_W=3,20,IF(Weapon_Calc_Tier_W=4,24,IF(Weapon_Calc_Tier_W=5,28)))))),IF(Weapon_Calc_Rarity="legendary",(IF(Weapon_Calc_Tier_W=1,17,IF(Weapon_Calc_Tier_W=2,22,IF(Weapon_Calc_Tier_W=3,27,IF(Weapon_Calc_Tier_W=4,32,IF(Weapon_Calc_Tier_W=5,38)))))),Error)))) -> 16 | X10: =IF(Weapon_Calc_Rarity="common",(IF(Weapon_Calc_Tier_A=1,7,IF(Weapon_Calc_Tier_A=2,8,IF(Weapon_Calc_Tier_A=3,11,IF(Weapon_Calc_Tier_A=4,12,IF(Weapon_Calc_Tier_A=5,14)))))),IF(Weapon_Calc_Rarity="rare",(IF(Weapon_Calc_Tier_A=1,8,IF(Weapon_Calc_Tier_A=2,11,IF(Weapon_Calc_Tier_A=3,14,IF(Weapon_Calc_Tier_A=4,17,IF(Weapon_Calc_Tier_A=5,21)))))),IF(Weapon_Calc_Rarity="epic",(IF(Weapon_Calc_Tier_A=1,12,IF(Weapon_Calc_Tier_A=2,16,IF(Weapon_Calc_Tier_A=3,20,IF(Weapon_Calc_Tier_A=4,24,IF(Weapon_Calc_Tier_A=5,28)))))),IF(Weapon_Calc_Rarity="legendary",(IF(Weapon_Calc_Tier_A=1,17,IF(Weapon_Calc_Tier_A=2,22,IF(Weapon_Calc_Tier_A=3,27,IF(Weapon_Calc_Tier_A=4,32,IF(Weapon_Calc_Tier_A=5,38)))))),Error)))) -> 20 | Y10: =IF(Weapon_Calc_Rarity="common",(IF(Weapon_Calc_Tier_I=1,7,IF(Weapon_Calc_Tier_I=2,8,IF(Weapon_Calc_Tier_I=3,11,IF(Weapon_Calc_Tier_I=4,12,IF(Weapon_Calc_Tier_I=5,14)))))),IF(Weapon_Calc_Rarity="rare",(IF(Weapon_Calc_Tier_I=1,8,IF(Weapon_Calc_Tier_I=2,11,IF(Weapon_Calc_Tier_I=3,14,IF(Weapon_Calc_Tier_I=4,17,IF(Weapon_Calc_Tier_I=5,21)))))),IF(Weapon_Calc_Rarity="epic",(IF(Weapon_Calc_Tier_I=1,12,IF(Weapon_Calc_Tier_I=2,16,IF(Weapon_Calc_Tier_I=3,20,IF(Weapon_Calc_Tier_I=4,24,IF(Weapon_Calc_Tier_I=5,28)))))),IF(Weapon_Calc_Rarity="legendary",(IF(Weapon_Calc_Tier_I=1,17,IF(Weapon_Calc_Tier_I=2,22,IF(Weapon_Calc_Tier_I=3,27,IF(Weapon_Calc_Tier_I=4,32,IF(Weapon_Calc_Tier_I=5,38)))))),Error)))) -> 20 | Z10: =IF(Weapon_Calc_Rarity="common",(IF(Weapon_Calc_Tier_F=1,7,IF(Weapon_Calc_Tier_F=2,8,IF(Weapon_Calc_Tier_F=3,11,IF(Weapon_Calc_Tier_F=4,12,IF(Weapon_Calc_Tier_F=5,14)))))),IF(Weapon_Calc_Rarity="rare",(IF(Weapon_Calc_Tier_F=1,8,IF(Weapon_Calc_Tier_F=2,11,IF(Weapon_Calc_Tier_F=3,14,IF(Weapon_Calc_Tier_F=4,17,IF(Weapon_Calc_Tier_F=5,21)))))),IF(Weapon_Calc_Rarity="epic",(IF(Weapon_Calc_Tier_F=1,12,IF(Weapon_Calc_Tier_F=2,16,IF(Weapon_Calc_Tier_F=3,20,IF(Weapon_Calc_Tier_F=4,24,IF(Weapon_Calc_Tier_F=5,28)))))),IF(Weapon_Calc_Rarity="legendary",(IF(Weapon_Calc_Tier_F=1,17,IF(Weapon_Calc_Tier_F=2,22,IF(Weapon_Calc_Tier_F=3,27,IF(Weapon_Calc_Tier_F=4,32,IF(Weapon_Calc_Tier_F=5,38)))))),Error)))) -> 20 | AA10: =IF(Weapon_Calc_Rarity="common",(IF(Weapon_Calc_Tier_U=1,7,IF(Weapon_Calc_Tier_U=2,8,IF(Weapon_Calc_Tier_U=3,11,IF(Weapon_Calc_Tier_U=4,12,IF(Weapon_Calc_Tier_U=5,14)))))),IF(Weapon_Calc_Rarity="rare",(IF(Weapon_Calc_Tier_U=1,8,IF(Weapon_Calc_Tier_U=2,11,IF(Weapon_Calc_Tier_U=3,14,IF(Weapon_Calc_Tier_U=4,17,IF(Weapon_Calc_Tier_U=5,21)))))),IF(Weapon_Calc_Rarity="epic",(IF(Weapon_Calc_Tier_U=1,12,IF(Weapon_Calc_Tier_U=2,16,IF(Weapon_Calc_Tier_U=3,20,IF(Weapon_Calc_Tier_U=4,24,IF(Weapon_Calc_Tier_U=5,28)))))),IF(Weapon_Calc_Rarity="legendary",(IF(Weapon_Calc_Tier_U=1,17,IF(Weapon_Calc_Tier_U=2,22,IF(Weapon_Calc_Tier_U=3,27,IF(Weapon_Calc_Tier_U=4,32,IF(Weapon_Calc_Tier_U=5,38)))))),Error)))) -> 24 | AN10: Chopper | AT10: 9
I11: =IF(_xlfn.XLOOKUP(L11,全装!G:G,全装!A:A,"")="Y","Y","") -> Y | J11: Yes | K11: 27 | L11: Combat Shotgun | M11: 战斗霰弹枪 | N11: 4 | O11: 1 | P11: 3 | Q11: 5 | R11: 2 | S11: W | T11: F | AN11: Butcher's Chopper | AT11: 10
I12: =IF(_xlfn.XLOOKUP(L12,全装!G:G,全装!A:A,"")="Y","Y","") | J12: Yes | K12: 21 | L12: Overcharged Tazer | M12: 过载电击枪 | N12: 1 | O12: 2 | P12: 4 | Q12: 4 | R12: 4 | S12: I | AT12: 11
I13: =IF(_xlfn.XLOOKUP(L13,全装!G:G,全装!A:A,"")="Y","Y","") | J13: Yes | K13: 39 | L13: SMG | M13: 冲锋枪 | N13: 4 | O13: 1 | P13: 3 | Q13: 3 | R13: 4 | S13: W | V13: Willpower | W13: Increases DPS with W weapons. | AN13: Small Harpoon Gun | AT13: 12
I14: =IF(_xlfn.XLOOKUP(L14,全装!G:G,全装!A:A,"")="Y","Y","") | J14: Yes | K14: 40 | L14: Specialized SMG | M14: 专用冲锋枪 | N14: 4 | O14: 1 | P14: 3 | Q14: 4 | R14: 3 | S14: W | V14: Agility | W14: Increases DPS with A weapons. | AN14: Harpoon Gun | AT14: 13
I15: =IF(_xlfn.XLOOKUP(L15,全装!G:G,全装!A:A,"")="Y","Y","") -> Y | J15: Meh | K15: 1 | L15: Dagger | M15: 匕首 | N15: 2 | O15: 4 | P15: 3 | Q15: 4 | R15: 2 | S15: A | T15: A + F | V15: Intelligence | W15: Increases DPS with I weapons. | AT15: 14
I16: =IF(_xlfn.XLOOKUP(L16,全装!G:G,全装!A:A,"")="Y","Y","") -> Y | J16: Meh | K16: 4 | L16: Chopper | M16: 砍刀 | N16: 2 | O16: 4 | P16: 2 | Q16: 4 | R16: 3 | S16: A | T16: A + F | V16: Fortitude | W16: Increases HP. | AN16: Shotgun | AT16: 15
I17: =IF(_xlfn.XLOOKUP(L17,全装!G:G,全装!A:A,"")="Y","Y","") -> Y | J17: Meh | K17: 6 | L17: Katana | M17: 武士刀 | N17: 2 | O17: 4 | P17: 3 | Q17: 2 | R17: 4 | S17: A | T17: A + U | V17: Utility | W17: Reduces damage taken. | AN17: Shotgun (with Scope) | AT17: 16
I18: =IF(_xlfn.XLOOKUP(L18,全装!G:G,全装!A:A,"")="Y","Y","") -> Y | J18: Meh | K18: 12 | L18: Fireaxe | M18: 消防斧 | N18: 1 | O18: 3 | P18: 4 | Q18: 4 | R18: 3 | S18: A | T18: I + F | AN18: Improved Shotgun | AT18: 17
I19: =IF(_xlfn.XLOOKUP(L19,全装!G:G,全装!A:A,"")="Y","Y","") -> Y | J19: Meh | K19: 18 | L19: Boomhammer | M19: 爆炸锤 | N19: 1 | O19: 3 | P19: 3 | Q19: 4 | R19: 4 | S19: A+I | V19: Old Manual Calculator | AN19: Combat Shotgun | AT19: 18
I20: =IF(_xlfn.XLOOKUP(L20,全装!G:G,全装!A:A,"")="Y","Y","") -> Y | J20: Meh | K20: 29 | L20: Harpoon Gun | M20: 鱼叉枪 | N20: 4 | O20: 1 | P20: 3 | Q20: 4 | R20: 3 | S20: W | T20: W + F | V20: Item Level | W20: Rarity | X20: Tier | AT20: 19
I21: =IF(_xlfn.XLOOKUP(L21,全装!G:G,全装!A:A,"")="Y","Y","") -> Y | J21: Meh | K21: 30 | L21: Small Harpoon Gun | M21: 小型鱼叉枪 | N21: 4 | O21: 1 | P21: 3 | Q21: 4 | R21: 3 | S21: W | T21: W + F | V21: 7 | W21: common | X21: Tier 3 | AN21: Machete | AT21: 20
I22: =IF(_xlfn.XLOOKUP(L22,全装!G:G,全装!A:A,"")="Y","Y","") -> Y | J22: Meh | K22: 7 | L22: Pipe | M22: 管道 | N22: 1 | O22: 4 | P22: 3 | Q22: 4 | R22: 3 | S22: A | T22: A + F | V22: Results | W22: Prog # | X22: Base Stat | AN22: Sharp Machete | AT22: 21
I23: =IF(_xlfn.XLOOKUP(L23,全装!G:G,全装!A:A,"")="Y","Y","") -> Y | J23: Meh | K23: 10 | L23: Machete | M23: 砍刀 | N23: 3 | O23: 3 | P23: 3 | Q23: 3 | R23: 3 | S23: A | V23: =Base_Stat_W+((Item_Level_W-1)*Prog_Number_W) -> 23 | W23: =IF(Weapon_Tier="Tier 1",1,IF(Weapon_Tier="Tier 2",1.5,IF(Weapon_Tier="Tier 3",2,IF(Weapon_Tier="Tier 4",2.5,IF(Weapon_Tier="Tier 5",3,"error6"))))) -> 2 | X23: =IF(Weapon_Rarity="common",(IF(Weapon_Tier="Tier 1",7,IF(Weapon_Tier="Tier 2",8,IF(Weapon_Tier="Tier 3",11,IF(Weapon_Tier="Tier 4",12,IF(Weapon_Tier="Tier 5",14)))))),IF(Weapon_Rarity="rare",(IF(Weapon_Tier="Tier 1",8,IF(Weapon_Tier="Tier 2",11,IF(Weapon_Tier="Tier 3",14,IF(Weapon_Tier="Tier 4",17,IF(Weapon_Tier="Tier 5",21)))))),IF(Weapon_Rarity="epic",(IF(Weapon_Tier="Tier 1",12,IF(Weapon_Tier="Tier 2",16,IF(Weapon_Tier="Tier 3",20,IF(Weapon_Tier="Tier 4",24,IF(Weapon_Tier="Tier 5",28)))))),IF(Weapon_Rarity="legendary",(IF(Weapon_Tier="Tier 1",17,IF(Weapon_Tier="Tier 2",22,IF(Weapon_Tier="Tier 3",27,IF(Weapon_Tier="Tier 4",32,IF(Weapon_Tier="Tier 5",38)))))),Error)))) -> 11 | AT23: 22
I24: =IF(_xlfn.XLOOKUP(L24,全装!G:G,全装!A:A,"")="Y","Y","") -> Y | J24: Meh | K24: 26 | L24: Shotgun | M24: 霰弹枪 | N24: 3 | O24: 2 | P24: 3 | Q24: 5 | R24: 2 | S24: W | T24: F | AN24: Prototype Tesla Gun | AT24: 23
I25: =IF(_xlfn.XLOOKUP(L25,全装!G:G,全装!A:A,"")="Y","Y","") -> Y | J25: Meh | K25: 32 | L25: Small Pistol | M25: 小型手枪 | N25: 3 | O25: 3 | P25: 3 | Q25: 3 | R25: 3 | S25: W | V25: Data and Stuff: | AN25: Prototype Tesla Gun (Sparks) | AT25: 24
I26: =IF(_xlfn.XLOOKUP(L26,全装!G:G,全装!A:A,"")="Y","Y","") | J26: Meh | K26: 34 | L26: Military Pistol | M26: 军用手枪 | N26: 3 | O26: 3 | P26: 3 | Q26: 3 | R26: 3 | S26: W | V26: P: | AT26: 25
I27: =IF(_xlfn.XLOOKUP(L27,全装!G:G,全装!A:A,"")="Y","Y","") -> Y | J27: Meh | K27: 35 | L27: Energy Pistol | M27: 能量手枪 | N27: 3 | O27: 3 | P27: 3 | Q27: 3 | R27: 3 | S27: W | V27: Stat points progression per level increase : | AN27: Small Fireaxe | AT27: 26
I28: =IF(_xlfn.XLOOKUP(L28,全装!G:G,全装!A:A,"")="Y","Y","") -> Y | J28: Meh | K28: 2 | L28: Hunting Dagger | M28: 狩猎匕首 | N28: 2 | O28: 4 | P28: 3 | Q28: 3 | R28: 3 | S28: A | V28: Type | W28: Tier 1 | X28: Tier 2 | Y28: Tier 3 | Z28: Tier 4 | AA28: Tier 5 | AN28: Fireaxe | AT28: 27
I29: =IF(_xlfn.XLOOKUP(L29,全装!G:G,全装!A:A,"")="Y","Y","") -> Y | J29: Meh | K29: 13 | L29: Small Fireaxe | M29: 小型消防斧 | N29: 2 | O29: 3 | P29: 4 | Q29: 3 | R29: 3 | S29: A | V29: Weapon | W29: 1 | X29: 1.5 | Y29: 2 | Z29: 2.5 | AA29: 3 | AT29: 28
I30: =IF(_xlfn.XLOOKUP(L30,全装!G:G,全装!A:A,"")="Y","Y","") -> Y | J30: Meh | K30: 19 | L30: Splathammer | M30: 碎击锤 | N30: 2 | O30: 3 | P30: 3 | Q30: 4 | R30: 3 | S30: A+I | AN30: Wrench | AT30: 29
I31: =IF(_xlfn.XLOOKUP(L31,全装!G:G,全装!A:A,"")="Y","Y","") | J31: Meh | K31: 28 | L31: Improved Shotgun | M31: 改进型霰弹枪 | N31: 3 | O31: 2 | P31: 3 | Q31: 5 | R31: 2 | S31: W | V31: B: | AN31: Wrench (legendary only?) | AT31: 30
I32: =IF(_xlfn.XLOOKUP(L32,全装!G:G,全装!A:A,"")="Y","Y","") -> Y | J32: Meh | K32: 31 | L32: Pistol | M32: 手枪 | N32: 4 | O32: 3 | P32: 3 | Q32: 3 | R32: 2 | S32: W | V32: Base points level 1 | W32: Tier 1 | X32: Tier 2 | Y32: Tier 3 | Z32: Tier 4 | AA32: Tier 5 | AN32: Heavy Wrench | AT32: 31
I33: =IF(_xlfn.XLOOKUP(L33,全装!G:G,全装!A:A,"")="Y","Y","") -> Y | J33: Meh | K33: 33 | L33: Civilian Pistol | M33: 民用手枪 | N33: 4 | O33: 3 | P33: 3 | Q33: 3 | R33: 2 | S33: W | V33: common | W33: 7 | X33: 8 | Y33: 11 | Z33: 12 | AA33: 14 | AT33: 32
I34: =IF(_xlfn.XLOOKUP(L34,全装!G:G,全装!A:A,"")="Y","Y","") -> Y | J34: Meh | K34: 36 | L34: Precision Laser Pistol | M34: 精密激光手枪 | N34: 4 | O34: 3 | P34: 3 | Q34: 2 | R34: 3 | S34: W | V34: rare | W34: 8 | X34: 11 | Y34: 14 | Z34: 17 | AA34: 21 | AN34: Boomhammer | AT34: 33
I35: =IF(_xlfn.XLOOKUP(L35,全装!G:G,全装!A:A,"")="Y","Y","") -> Y | J35: Meh | K35: 37 | L35: Flamethrower | M35: 火焰喷射器 | N35: 2 | O35: 3 | P35: 3 | Q35: 3 | R35: 4 | S35: W | V35: epic | W35: 12 | X35: 16 | Y35: 20 | Z35: 24 | AA35: 28 | AN35: Splathammer | AT35: 34
I36: =IF(_xlfn.XLOOKUP(L36,全装!G:G,全装!A:A,"")="Y","Y","") -> Y | J36: Yes | K36: 11 | L36: Sharp Machete | M36: 锋利弯刀 | N36: 3 | O36: 4 | P36: 2 | Q36: 3 | R36: 3 | S36: A | V36: legendary | W36: 17 | X36: 22 | Y36: 27 | Z36: 32 | AA36: 38 | AT36: 35
I37: =IF(_xlfn.XLOOKUP(L37,全装!G:G,全装!A:A,"")="Y","Y","") | J37: Yes | K37: 14 | L37: Spiked Club | M37: 尖刺棍棒 | N37: 1 | O37: 4 | P37: 2 | Q37: 4 | R37: 4 | S37: A | AN37: Pipe | AT37: 36
I38: =IF(_xlfn.XLOOKUP(L38,全装!G:G,全装!A:A,"")="Y","Y","") -> Y | J38: Yes | K38: 20 | L38: Tazer | M38: 电击枪 | N38: 2 | O38: 3 | P38: 3 | Q38: 4 | R38: 3 | S38: I | V38: ((L-1)*P)+B=S | X38: L = Item Level | AA38: Down = Column | AN38: Heavy Pipe | AT38: 37
I39: =IF(_xlfn.XLOOKUP(L39,全装!G:G,全装!A:A,"")="Y","Y","") | J39: Meh | K39: 22 | L39: High-Volt Tazer | M39: 高压电击枪 | N39: 2 | O39: 2 | P39: 4 | Q39: 4 | R39: 3 | S39: I | X39: P = Progression Per Level | AA39: Side = Row | AN39: Reinforced Pipe | AT39: 38
I40: =IF(_xlfn.XLOOKUP(L40,全装!G:G,全装!A:A,"")="Y","Y","") | J40: Meh | K40: 23 | L40: Large Tazer | M40: 大型电击枪 | N40: 2 | O40: 4 | P40: 2 | Q40: 5 | R40: 2 | S40: I | V40: S = Resulting Stat | X40: B = Base Points for Item Type & Rarity | AT40: 39
I41: =IF(_xlfn.XLOOKUP(L41,全装!G:G,全装!A:A,"")="Y","Y","") -> Y | J41: Yes | K41: 38 | L41: Scorcher | M41: 灼烧者 | N41: 3 | O41: 2 | P41: 2 | Q41: 4 | R41: 4 | S41: W | AN41: Small Pistol | AT41: 40
I42: =IF(_xlfn.XLOOKUP(L42,全装!G:G,全装!A:A,"")="Y","Y","") | J42: Yes | K42: 41 | L42: XX's Last Resort | M42: XX的最后手段 | N42: 4 | O42: 2 | P42: 3 | Q42: 2 | R42: 4 | S42: W | V42: Sheet is locked only to avoid accidentally modifying a formula :) no password is set | AN42: Pistol | AT42: 41
I43: =IF(_xlfn.XLOOKUP(L43,全装!G:G,全装!A:A,"")="Y","Y","") -> Y | J43: Yes | K43: 42 | L43: Last Resort | M43: 最后手段 | N43: 3 | O43: 2 | P43: 4 | Q43: 3 | R43: 3 | S43: W | AN43: Pistol (with Scope) | AT43: 42
I44: =IF(_xlfn.XLOOKUP(L44,全装!G:G,全装!A:A,"")="Y","Y","") | J44: Yes | K44: 43 | L44: Amorous Bow | M44: 情爱之弓 | N44: 3 | O44: 4 | P44: 3 | Q44: 3 | R44: 2 | S44: W+A | AN44: Civilian Pistol | AT44: 43
I45: =IF(_xlfn.XLOOKUP(L45,全装!G:G,全装!A:A,"")="Y","Y","") | J45: Yes | K45: 44 | L45: Blaster | M45: 爆破枪 | N45: 4 | O45: 3 | P45: 3 | Q45: 3 | R45: 2 | S45: W+I | AN45: Military Pistol | AT45: 44
K46: 45 | V46: Unlocked cell | AN46: Energy Pistol | AT46: 45
K47: 46 | AN47: Precision Laser Pistol | AT47: 46
K48: 47 | AT48: 47
K49: 48 | AN49: Dagger | AT49: 48
K50: 49 | AN50: Hunting Dagger | AT50: 49
K51: 50 | AT51: 50
AN52: Flamethrower | AT52: 51
J53: "common" | AN53: Scorcher | AT53: 52
J54: "Rare" | V54: NEW CALC Formulas: | AT54: 53
J55: "Unobtainium" (aka are event/reward/mission/purchase locked) | V55: data Transposing: | AT55: 54
J56: Yellow Name | L56: Yellow Name | V56: '=VLOOKUP(Weapon_Calc_Name_List,Weapon_Calc_Base_Stat_List,2)
J57: Sort "Formula"=
J58: Name | K58: Cell Color | L58: Green | N58: On Top | V58: Progress Number:
J59: Name | K59: Cell Color | L59: Yellow | N59: On Top | V59: '=IF(Weapon_Calc_Tier_W=1, 1,IF(Weapon_Calc_Tier_W=2, 1.5,IF(Weapon_Calc_Tier_W=3, 2,IF(Weapon_Calc_Tier_W=4, 2.5,IF(Weapon_Calc_Tier_W=5, 3, "error6")))))
J60: Name | K60: Cell Color | L60: Orange | N60: On Top | V60: '=IF(Weapon_Calc_Tier_A=1, 1,IF(Weapon_Calc_Tier_A=2, 1.5,IF(Weapon_Calc_Tier_A=3, 2,IF(Weapon_Calc_Tier_A=4, 2.5,IF(Weapon_Calc_Tier_A=5, 3, "error6")))))
J61: Name | K61: Cell Color | L61: Red | N61: On Top | V61: '=IF(Weapon_Calc_Tier_I=1, 1,IF(Weapon_Calc_Tier_I=2, 1.5,IF(Weapon_Calc_Tier_I=3, 2,IF(Weapon_Calc_Tier_I=4, 2.5,IF(Weapon_Calc_Tier_I=5, 3, "error6")))))
J62: Order | K62: Values | L62: Smallest to Largest | V62: '=IF(Weapon_Calc_Tier_F=1, 1,IF(Weapon_Calc_Tier_F=2, 1.5,IF(Weapon_Calc_Tier_F=3, 2,IF(Weapon_Calc_Tier_F=4, 2.5,IF(Weapon_Calc_Tier_F=5, 3, "error6")))))
V63: '=IF(Weapon_Calc_Tier_U=1, 1,IF(Weapon_Calc_Tier_U=2, 1.5,IF(Weapon_Calc_Tier_U=3, 2,IF(Weapon_Calc_Tier_U=4, 2.5,IF(Weapon_Calc_Tier_U=5, 3, "error6")))))
J65: Yes = Owned | V65: Base Stats:
J66: Meh = Common Drop (often Dissassembled) | V66: '=IF(Weapon_Calc_Rarity="common", (IF(Weapon_Calc_Tier_W=1, 7,IF(Weapon_Calc_Tier_W=2, 8,IF(Weapon_Calc_Tier_W=3, 11,IF(Weapon_Calc_Tier_W=4, 12,IF(Weapon_Calc_Tier_W=5, 14)))))), IF(Weapon_Calc_Rarity="rare", (IF(Weapon_Calc_Tier_W=1, 8,IF(Weapon_Calc_Tier_W=2, 11,IF(Weapon_Calc_Tier_W=3, 14,IF(Weapon_Calc_Tier_W=4, 17,IF(Weapon_Calc_Tier_W=5, 21)))))), IF(Weapon_Calc_Rarity="epic", (IF(Weapon_Calc_Tier_W=1, 12,IF(Weapon_Calc_Tier_W=2, 16,IF(Weapon_Calc_Tier_W=3, 20,IF(Weapon_Calc_Tier_W=4, 24,IF(Weapon_Calc_Tier_W=5, 28)))))), IF(Weapon_Calc_Rarity="legendary", (IF(Weapon_Calc_Tier_W=1, 17,IF(Weapon_Calc_Tier_W=2, 22,IF(Weapon_Calc_Tier_W=3, 27,IF(Weapon_Calc_Tier_W=4, 32,IF(Weapon_Calc_Tier_W=5, 38)))))), Error))))
J67: No = Not Owned at all | V67: '=IF(Weapon_Calc_Rarity="common", (IF(Weapon_Calc_Tier_A=1, 7,IF(Weapon_Calc_Tier_A=2, 8,IF(Weapon_Calc_Tier_A=3, 11,IF(Weapon_Calc_Tier_A=4, 12,IF(Weapon_Calc_Tier_A=5, 14)))))), IF(Weapon_Calc_Rarity="rare", (IF(Weapon_Calc_Tier_A=1, 8,IF(Weapon_Calc_Tier_A=2, 11,IF(Weapon_Calc_Tier_A=3, 14,IF(Weapon_Calc_Tier_A=4, 17,IF(Weapon_Calc_Tier_A=5, 21)))))), IF(Weapon_Calc_Rarity="epic", (IF(Weapon_Calc_Tier_A=1, 12,IF(Weapon_Calc_Tier_A=2, 16,IF(Weapon_Calc_Tier_A=3, 20,IF(Weapon_Calc_Tier_A=4, 24,IF(Weapon_Calc_Tier_A=5, 28)))))), IF(Weapon_Calc_Rarity="legendary", (IF(Weapon_Calc_Tier_A=1, 17,IF(Weapon_Calc_Tier_A=2, 22,IF(Weapon_Calc_Tier_A=3, 27,IF(Weapon_Calc_Tier_A=4, 32,IF(Weapon_Calc_Tier_A=5, 38)))))), Error))))
V68: '=IF(Weapon_Calc_Rarity="common", (IF(Weapon_Calc_Tier_I=1, 7,IF(Weapon_Calc_Tier_I=2, 8,IF(Weapon_Calc_Tier_I=3, 11,IF(Weapon_Calc_Tier_I=4, 12,IF(Weapon_Calc_Tier_I=5, 14)))))), IF(Weapon_Calc_Rarity="rare", (IF(Weapon_Calc_Tier_I=1, 8,IF(Weapon_Calc_Tier_I=2, 11,IF(Weapon_Calc_Tier_I=3, 14,IF(Weapon_Calc_Tier_I=4, 17,IF(Weapon_Calc_Tier_I=5, 21)))))), IF(Weapon_Calc_Rarity="epic", (IF(Weapon_Calc_Tier_I=1, 12,IF(Weapon_Calc_Tier_I=2, 16,IF(Weapon_Calc_Tier_I=3, 20,IF(Weapon_Calc_Tier_I=4, 24,IF(Weapon_Calc_Tier_I=5, 28)))))), IF(Weapon_Calc_Rarity="legendary", (IF(Weapon_Calc_Tier_I=1, 17,IF(Weapon_Calc_Tier_I=2, 22,IF(Weapon_Calc_Tier_I=3, 27,IF(Weapon_Calc_Tier_I=4, 32,IF(Weapon_Calc_Tier_I=5, 38)))))), Error))))
J69: “普通” | V69: '=IF(Weapon_Calc_Rarity="common", (IF(Weapon_Calc_Tier_F=1, 7,IF(Weapon_Calc_Tier_F=2, 8,IF(Weapon_Calc_Tier_F=3, 11,IF(Weapon_Calc_Tier_F=4, 12,IF(Weapon_Calc_Tier_F=5, 14)))))), IF(Weapon_Calc_Rarity="rare", (IF(Weapon_Calc_Tier_F=1, 8,IF(Weapon_Calc_Tier_F=2, 11,IF(Weapon_Calc_Tier_F=3, 14,IF(Weapon_Calc_Tier_F=4, 17,IF(Weapon_Calc_Tier_F=5, 21)))))), IF(Weapon_Calc_Rarity="epic", (IF(Weapon_Calc_Tier_F=1, 12,IF(Weapon_Calc_Tier_F=2, 16,IF(Weapon_Calc_Tier_F=3, 20,IF(Weapon_Calc_Tier_F=4, 24,IF(Weapon_Calc_Tier_F=5, 28)))))), IF(Weapon_Calc_Rarity="legendary", (IF(Weapon_Calc_Tier_F=1, 17,IF(Weapon_Calc_Tier_F=2, 22,IF(Weapon_Calc_Tier_F=3, 27,IF(Weapon_Calc_Tier_F=4, 32,IF(Weapon_Calc_Tier_F=5, 38)))))), Error))))
J70: “稀有” | V70: '=IF(Weapon_Calc_Rarity="common", (IF(Weapon_Calc_Tier_U=1, 7,IF(Weapon_Calc_Tier_U=2, 8,IF(Weapon_Calc_Tier_U=3, 11,IF(Weapon_Calc_Tier_U=4, 12,IF(Weapon_Calc_Tier_U=5, 14)))))), IF(Weapon_Calc_Rarity="rare", (IF(Weapon_Calc_Tier_U=1, 8,IF(Weapon_Calc_Tier_U=2, 11,IF(Weapon_Calc_Tier_U=3, 14,IF(Weapon_Calc_Tier_U=4, 17,IF(Weapon_Calc_Tier_U=5, 21)))))), IF(Weapon_Calc_Rarity="epic", (IF(Weapon_Calc_Tier_U=1, 12,IF(Weapon_Calc_Tier_U=2, 16,IF(Weapon_Calc_Tier_U=3, 20,IF(Weapon_Calc_Tier_U=4, 24,IF(Weapon_Calc_Tier_U=5, 28)))))), IF(Weapon_Calc_Rarity="legendary", (IF(Weapon_Calc_Tier_U=1, 17,IF(Weapon_Calc_Tier_U=2, 22,IF(Weapon_Calc_Tier_U=3, 27,IF(Weapon_Calc_Tier_U=4, 32,IF(Weapon_Calc_Tier_U=5, 38)))))), Error))))
J71: “无法获取的材料”（也就是说，事件/奖励/任务/购买锁定）
J72: 黄色名字 | L72: 黄色名字 | V72: Final Calculations:
J73: 是 = 拥有 | V73: '=Weapon_Calc_Base_Stat_W+((Weapon_Calc_Level-1)*Weapon_Calc_Progress_Num_W)
J74: 常见掉落（通常为拆解） | V74: '=Weapon_Calc_Base_Stat_A+((Weapon_Calc_Level-1)*Weapon_Calc_Progress_Num_A)
J75: 不拥有 | V75: '=Weapon_Calc_Base_Stat_I+((Weapon_Calc_Level-1)*Weapon_Calc_Progress_Num_I)
V76: '=Weapon_Calc_Base_Stat_F+((Weapon_Calc_Level-1)*Weapon_Calc_Progress_Num_F)
V77: '=Weapon_Calc_Base_Stat_U+((Weapon_Calc_Level-1)*Weapon_Calc_Progress_Num_U)
V79: New Calc Hard Variables:
V80: Weapon_Calc_Tier_W
V81: Weapon_Calc_Tier_A
V82: Weapon_Calc_Tier_I
V83: Weapon_Calc_Tier_F
V84: Weapon_Calc_Tier_U
V86: Weapon_Calc_Progress_Num_W
V87: Weapon_Calc_Progress_Num_A
V88: Weapon_Calc_Progress_Num_I
V89: Weapon_Calc_Progress_Num_F
... V110: =Base_Stat_W+((Item_Level_W-1)*Prog_Number_W)

Sheet 同样效果
A1: 类型 | B1: 相等 | C1: 名字 | D1: 中文
A2: 1 | C2: Casual Suit | D2: 休闲西装
A3: 1 | C3: CB-69's Armour | D3: CB-69的盔甲
A4: 1 | B4: A | C4: Chelsea’s Bodysuit | D4: 切尔西的紧身衣
A5: 1 | C5: Chivalry | D5: 骑士精神
A6: 1 | C6: Classy Colours | D6: 经典色彩
A7: 1 | C7: Cloe’s Sets | D7: Cloe的套装
A8: 1 | C8: Cosmic Attire | D8: 宇宙服装
A9: 1 | C9: Crazy’s Sets | D9: 疯狂的套装
A10: 1 | B10: I | C10: Cute Dress | D10: 可爱裙子
A11: 1 | C11: Dahia's Rituals | D11: 达希亚的仪式
A12: 1 | C12: Dangerous Set | D12: 危险套装
A13: 1 | C13: Domination | D13: 统治
A14: 1 | C14: Dress To Rugs | D14: 裙装改为地毯
A15: 1 | C15: Elaine's Charm | D15: 伊莱恩的魅力
A16: 1 | C16: Eleanor Set | D16: 埃莉诺套装
A17: 1 | C17: Fearless Warrior Suit | D17: 无畏战士套装
A18: 1 | C18: Field Medic Suit | D18: 战地医疗服
A19: 1 | C19: Foxy’s Set | D19: 狐狸的套装
A20: 1 | B20: W | C20: Frozen’s Attire | D20: 冰冻的服装
A21: 1 | C21: Gaia’s Sets | D21: 盖亚的套装
A22: 1 | C22: Guinevere's Cool | D22: 桂妮薇尔的酷炫
A23: 1 | C23: Harbringers Of Pain | D23: 痛苦的先驱者
A24: 1 | C24: Harriet's Chaps | D24: 哈丽特的裤子
A25: 1 | C25: Infiltrator Suit | D25: 入侵者套装
A26: 1 | C26: Jasmine's Nights | D26: 茉莉的夜晚
A27: 1 | C27: Jealousy Bringer | D27: 嫉妒的使者
A28: 1 | C28: JNT Set | D28: JNT套装
A29: 1 | C29: Killer Dress | D29: 杀手裙
A30: 1 | B30: I | C30: Kim’s Swimsuit | D30: 金的泳衣
A31: 1 | B31: I | C31: Leader Set | D31: 领导者套装
A32: 1 | C32: Liberator Suit | D32: 解放者套装
A33: 1 | C33: Liza’s Chitina | D33: 丽莎的奇蒂娜
A34: 1 | C34: Momoka’s Sets | D34: 桃花的套装
A35: 1 | C35: Opalescent Set | D35: 璀璨套装
A36: 1 | C36: Postapo Suit | D36: 后启时代服装
A37: 1 | C37: Power Set | D37: 力量套装
A38: 1 | C38: Raven Hide | D38: 乌鸦皮
A39: 1 | C39: Reznor's Decision | D39: 雷兹诺的决定
A40: 1 | C40: Sexting Uniform | D40: 调情制服
A41: 1 | C41: Sisterhood Dress | D41: 姐妹会裙
A42: 1 | C42: Skalds Poem | D42: Skalds Poem
A43: 1 | C43: Stella's Sunshine | D43: 斯特拉的阳光
... A48: 1 | C48: XX’s Sol Uniform | D48: XX的制服
A49: 2 | B49: W | C49: Army Top | D49: 军装上装
A50: 2 | B50: W | C50: Army Bottom | D50: 军队的底部
A51: 2 | C51: Veneza’s Top | D51: 威尼斯之巅
A52: 2 | C52: Gaia's Bottom | D52: 盖亚底部
A53: 2 | B53: A | C53: Ashley’s Top | D53: 阿什利的上衣
A54: 2 | B54: A | C54: Liza’s Wings | D54: 莉扎之翼
A55: 2 | B55: A | C55: Flaming Leggings | D55: 火焰护腿
A56: 2 | B56: A | C56: Space Leggings | D56: 太空紧身裤
A57: 2 | B57: I | C57: Black-red Bra | D57: 黑红文胸
A58: 2 | B58: I | C58: Mechanic's Skirt | D58: 机械师半身裙
A59: 2 | B59: I | C59: Momoka's Bottom | D59: 桃香的臀部
A60: 2 | C60: Mechanic’s Top | D60: 机械师上衣
A61: 2 | C61: Veneza's Bottom | D61: 维内扎的下装
A62: 2 | C62: Open Top | D62: 敞口
A63: 2 | C63: Wide Bottom | D63: 宽裤脚
A64: 2 | C64: Barbarian Top | D64: 野蛮人上装
A65: 2 | C65: Barbarian Skirt | D65: 野蛮人短裙
A66: 2 | B66: A | C66: Chelsea’s Favor | D66: 切尔西的恩惠
A67: 2 | B67: A | C67: Chelsea's Blessing | D67: 切尔西的祝福
A68: 2 | C68: Dissolved Top | D68: 溶解上衣
A69: 2 | C69: Prisoners Panties | D69: 囚犯内裤
A70: 2 | C70: Baseball Star Bra | D70: 棒球明星胸罩
A71: 2 | C71: Baseball Star Panties | D71: 棒球明星内裤
A72: 2 | C72: Waifu’s Special (top) | D72: 老婆专属（上衣）
A73: 2 | C73: Waifu's Special (bottom) | D73: 老婆专属（下装）
A74: 2 | C74: XX’s Blessing | D74: XX的祝福
A75: 2 | C75: XX's Prayer | D75: XX的祈祷
A76: 2 | C76: Neon Lights (top) | D76: 霓虹灯（上衣）
